Workbook

Sheet General
A1: Food cost per 1k cal | B1: 5 | C1: $/ppm | D1: 100 | G1: Generic BU Level | H1: Generic BU Multiplier | I1: Generic AU Level | J1: Generic AU Multiplier | K1: Generic MU Level | L1: Generic MU Multiplier
A2: Min Wage $/1k | B2: 40 | C2: $/ppm-s | D2: =D1/3600 -> 0.027777778 | G2: 4 | H2: =SWITCH(G2, 0, 1, 1, 0.9,2,0.75,3,0.6,4,0.55,5,0.5) -> 0.55 | I2: 0 | J2: =SWITCH(I2, 0, 1, 1, 0.9,2,0.75,3,0.6,4,0.55,5,0.5) -> 1 | K2: 0 | L2: =SWITCH(K2, 0, 1, 1, 0.9,2,0.75,3,0.6,4,0.55,5,0.5) -> 1
A4: Skills | B4: Level | C4: Calorie Multiplier | D4: Food cost per 1k calories calc | E4: Min Wage calc | F4: Cost per 1k cal. | G4: BU Level | H4: BU Multi | I4: AU Level | J4: AU Multi | K4: MU Level | L4: MU Multi
A5: Carpentry | B5: 0 | C5: =IF(B5>0, 1-(0.15+B5*0.05), 1) -> 1 | D5: =$B$1 -> 5 | E5: =$B$2 -> 40 | F5: =IF(B5>0, D5*C5,E5) -> 40 | G5: =$G$2 -> 4 | H5: =SWITCH(G5, 0, 1, 1, 0.9,2,0.75,3,0.6,4,0.55,5,0.5)*IF(B5>=6, 0.95, 1) -> 0.55 | I5: =$I$2 -> 0 | J5: =SWITCH(I5, 0, 1, 1, 0.9,2,0.75,3,0.6,4,0.55,5,0.5)*IF(B5>=6, 0.95, 1) -> 1 | K5: =$K$2 -> 0 | L5: =SWITCH(K5, 0, 1, 1, 0.9,2,0.75,3,0.6,4,0.55,5,0.5)*IF(B5>=6, 0.95, 1) -> 1
A6: Logging | B6: 0 | C6: =IF(B6>0, 1-(0.15+B6*0.05), 1) -> 1 | D6: =$B$1 -> 5 | E6: =$B$2 -> 40 | F6: =IF(B6>0, D6*C6,E6) -> 40 | G6: =$G$2 -> 4 | H6: =SWITCH(G6, 0, 1, 1, 0.9,2,0.75,3,0.6,4,0.55,5,0.5) -> 0.55 | I6: =$I$2 -> 0 | J6: =SWITCH(I6, 0, 1, 1, 0.9,2,0.75,3,0.6,4,0.55,5,0.5) -> 1 | K6: =$K$2 -> 0 | L6: =SWITCH(K6, 0, 1, 1, 0.9,2,0.75,3,0.6,4,0.55,5,0.5) -> 1
A7: Composites | B7: 0 | C7: =IF(B7>0, 1-(0.15+B7*0.05), 1) -> 1 | D7: =$B$1 -> 5 | E7: =$B$2 -> 40 | F7: =IF(B7>0, D7*C7,E7) -> 40 | G7: =$G$2 -> 4 | H7: =SWITCH(G7, 0, 1, 1, 0.9,2,0.75,3,0.6,4,0.55,5,0.5)*IF(B7>=6, 0.95, 1) -> 0.55 | I7: =$I$2 -> 0 | J7: =SWITCH(I7, 0, 1, 1, 0.9,2,0.75,3,0.6,4,0.55,5,0.5)*IF(B7>=6, 0.95, 1) -> 1 | K7: =$K$2 -> 0 | L7: =SWITCH(K7, 0, 1, 1, 0.9,2,0.75,3,0.6,4,0.55,5,0.5)*IF(B7>=6, 0.95, 1) -> 1
A8: Paper Milling | B8: 0 | C8: =IF(B8>0, 1-(0.15+B8*0.05), 1) -> 1 | D8: =$B$1 -> 5 | E8: =$B$2 -> 40 | F8: =IF(B8>0, D8*C8,E8) -> 40 | G8: =$G$2 -> 4 | H8: =SWITCH(G8, 0, 1, 1, 0.9,2,0.75,3,0.6,4,0.55,5,0.5)*IF(B8>=6, 0.95, 1) -> 0.55 | I8: =$I$2 -> 0 | J8: =SWITCH(I8, 0, 1, 1, 0.9,2,0.75,3,0.6,4,0.55,5,0.5)*IF(B8>=6, 0.95, 1) -> 1 | K8: =$K$2 -> 0 | L8: =SWITCH(K8, 0, 1, 1, 0.9,2,0.75,3,0.6,4,0.55,5,0.5)*IF(B8>=6, 0.95, 1) -> 1
A9: Masonry | B9: 0 | C9: =IF(B9>0, 1-(0.15+B9*0.05), 1) -> 1 | D9: =$B$1 -> 5 | E9: =$B$2 -> 40 | F9: =IF(B9>0, D9*C9,E9) -> 40 | G9: =$G$2 -> 4 | H9: =SWITCH(G9, 0, 1, 1, 0.9,2,0.75,3,0.6,4,0.55,5,0.5)*IF(B9>=6, 0.95, 1) -> 0.55 | I9: =$I$2 -> 0 | J9: =SWITCH(I9, 0, 1, 1, 0.9,2,0.75,3,0.6,4,0.55,5,0.5)*IF(B9>=6, 0.95, 1) -> 1 | K9: =$K$2 -> 0 | L9: =SWITCH(K9, 0, 1, 1, 0.9,2,0.75,3,0.6,4,0.55,5,0.5)*IF(B9>=6, 0.95, 1) -> 1
A10: Mining | B10: 0 | C10: =IF(B10>0, 1-(0.15+B10*0.05), 1) -> 1 | D10: =$B$1 -> 5 | E10: =$B$2 -> 40 | F10: =IF(B10>0, D10*C10,E10) -> 40 | G10: =$G$2 -> 4 | H10: =SWITCH(G10, 0, 1, 1, 0.9,2,0.75,3,0.6,4,0.55,5,0.5) -> 0.55 | I10: =$I$2 -> 0 | J10: =SWITCH(I10, 0, 1, 1, 0.9,2,0.75,3,0.6,4,0.55,5,0.5)*IF(B10>=6, 0.95, 1) -> 1 | K10: =$K$2 -> 0 | L10: =SWITCH(K10, 0, 1, 1, 0.9,2,0.75,3,0.6,4,0.55,5,0.5) -> 1
A11: Advanced Masonry | B11: 0 | C11: =IF(B11>0, 1-(0.15+B11*0.05), 1) -> 1 | D11: =$B$1 -> 5 | E11: =$B$2 -> 40 | F11: =IF(B11>0, D11*C11,E11) -> 40 | G11: =$G$2 -> 4 | H11: =SWITCH(G11, 0, 1, 1, 0.9,2,0.75,3,0.6,4,0.55,5,0.5)*IF(B11>=6, 0.95, 1) -> 0.55 | I11: =$I$2 -> 0 | J11: =SWITCH(I11, 0, 1, 1, 0.9,2,0.75,3,0.6,4,0.55,5,0.5)*IF(B11>=6, 0.95, 1) -> 1 | K11: =$K$2 -> 0 | L11: =SWITCH(K11, 0, 1, 1, 0.9,2,0.75,3,0.6,4,0.55,5,0.5)*IF(B11>=6, 0.95, 1) -> 1
A12: Glassworking | B12: 0 | C12: =IF(B12>0, 1-(0.15+B12*0.05), 1) -> 1 | D12: =$B$1 -> 5 | E12: =$B$2 -> 40 | F12: =IF(B12>0, D12*C12,E12) -> 40 | G12: =$G$2 -> 4 | H12: =SWITCH(G12, 0, 1, 1, 0.9,2,0.75,3,0.6,4,0.55,5,0.5)*IF(B12>=6, 0.95, 1) -> 0.55 | I12: 5 | J12: =SWITCH(I12, 0, 1, 1, 0.9,2,0.75,3,0.6,4,0.55,5,0.5)*IF(B12>=6, 0.95, 1) -> 0.5 | K12: =$K$2 -> 0 | L12: =SWITCH(K12, 0, 1, 1, 0.9,2,0.75,3,0.6,4,0.55,5,0.5)*IF(B12>=6, 0.95, 1) -> 1
A13: Pottery | B13: 0 | C13: =IF(B13>0, 1-(0.15+B13*0.05), 1) -> 1 | D13: =$B$1 -> 5 | E13: =$B$2 -> 40 | F13: =IF(B13>0, D13*C13,E13) -> 40 | G13: =$G$2 -> 4 | H13: =SWITCH(G13, 0, 1, 1, 0.9,2,0.75,3,0.6,4,0.55,5,0.5)*IF(B13>=6, 0.95, 1) -> 0.55 | I13: =$I$2 -> 0 | J13: =SWITCH(I13, 0, 1, 1, 0.9,2,0.75,3,0.6,4,0.55,5,0.5)*IF(B13>=6, 0.95, 1) -> 1 | K13: =$K$2 -> 0 | L13: =SWITCH(K13, 0, 1, 1, 0.9,2,0.75,3,0.6,4,0.55,5,0.5)*IF(B13>=6, 0.95, 1) -> 1
A14: Campfire Cooking | B14: 0 | C14: =IF(B14>0, 1-(0.15+B14*0.05), 1) -> 1 | D14: =$B$1 -> 5 | E14: =$B$2 -> 40 | F14: =IF(B14>0, D14*C14,E14) -> 40 | G14: =$G$2 -> 4 | H14: =SWITCH(G14, 0, 1, 1, 0.9,2,0.75,3,0.6,4,0.55,5,0.5)*IF(B14>=6, 0.95, 1) -> 0.55 | I14: =$I$2 -> 0 | J14: =SWITCH(I14, 0, 1, 1, 0.9,2,0.75,3,0.6,4,0.55,5,0.5)*IF(B14>=6, 0.95, 1) -> 1 | K14: =$K$2 -> 0 | L14: =SWITCH(K14, 0, 1, 1, 0.9,2,0.75,3,0.6,4,0.55,5,0.5)*IF(B14>=6, 0.95, 1) -> 1
A15: Advanced Baking | B15: 0 | C15: =IF(B15>0, 1-(0.15+B15*0.05), 1) -> 1 | D15: =$B$1 -> 5 | E15: =$B$2 -> 40 | F15: =IF(B15>0, D15*C15,E15) -> 40 | G15: =$G$2 -> 4 | H15: =SWITCH(G15, 0, 1, 1, 0.9,2,0.75,3,0.6,4,0.55,5,0.5)*IF(B15>=6, 0.95, 1) -> 0.55 | I15: =$I$2 -> 0 | J15: =SWITCH(I15, 0, 1, 1, 0.9,2,0.75,3,0.6,4,0.55,5,0.5)*IF(B15>=6, 0.95, 1) -> 1 | K15: =$K$2 -> 0 | L15: =SWITCH(K15, 0, 1, 1, 0.9,2,0.75,3,0.6,4,0.55,5,0.5)*IF(B15>=6, 0.95, 1) -> 1
A16: Advanced Cooking | B16: 0 | C16: =IF(B16>0, 1-(0.15+B16*0.05), 1) -> 1 | D16: =$B$1 -> 5 | E16: =$B$2 -> 40 | F16: =IF(B16>0, D16*C16,E16) -> 40 | G16: =$G$2 -> 4 | H16: =SWITCH(G16, 0, 1, 1, 0.9,2,0.75,3,0.6,4,0.55,5,0.5)*IF(B16>=6, 0.95, 1) -> 0.55 | I16: =$I$2 -> 0 | J16: =SWITCH(I16, 0, 1, 1, 0.9,2,0.75,3,0.6,4,0.55,5,0.5)*IF(B16>=6, 0.95, 1) -> 1 | K16: =$K$2 -> 0 | L16: =SWITCH(K16, 0, 1, 1, 0.9,2,0.75,3,0.6,4,0.55,5,0.5)*IF(B16>=6, 0.95, 1) -> 1
A17: Baking | B17: 0 | C17: =IF(B17>0, 1-(0.15+B17*0.05), 1) -> 1 | D17: =$B$1 -> 5 | E17: =$B$2 -> 40 | F17: =IF(B17>0, D17*C17,E17) -> 40 | G17: =$G$2 -> 4 | H17: =SWITCH(G17, 0, 1, 1, 0.9,2,0.75,3,0.6,4,0.55,5,0.5)*IF(B17>=6, 0.95, 1) -> 0.55 | I17: =$I$2 -> 0 | J17: =SWITCH(I17, 0, 1, 1, 0.9,2,0.75,3,0.6,4,0.55,5,0.5)*IF(B17>=6, 0.95, 1) -> 1 | K17: =$K$2 -> 0 | L17: =SWITCH(K17, 0, 1, 1, 0.9,2,0.75,3,0.6,4,0.55,5,0.5)*IF(B17>=6, 0.95, 1) -> 1
A18: Cooking | B18: 0 | C18: =IF(B18>0, 1-(0.15+B18*0.05), 1) -> 1 | D18: =$B$1 -> 5 | E18: =$B$2 -> 40 | F18: =IF(B18>0, D18*C18,E18) -> 40 | G18: =$G$2 -> 4 | H18: =SWITCH(G18, 0, 1, 1, 0.9,2,0.75,3,0.6,4,0.55,5,0.5)*IF(B18>=6, 0.95, 1) -> 0.55 | I18: =$I$2 -> 0 | J18: =SWITCH(I18, 0, 1, 1, 0.9,2,0.75,3,0.6,4,0.55,5,0.5)*IF(B18>=6, 0.95, 1) -> 1 | K18: =$K$2 -> 0 | L18: =SWITCH(K18, 0, 1, 1, 0.9,2,0.75,3,0.6,4,0.55,5,0.5)*IF(B18>=6, 0.95, 1) -> 1
A19: Basic Engineering | B19: 0 | C19: =IF(B19>0, 1-(0.15+B19*0.05), 1) -> 1 | D19: =$B$1 -> 5 | E19: =$B$2 -> 40 | F19: =IF(B19>0, D19*C19,E19) -> 40 | G19: =$G$2 -> 4 | H19: =SWITCH(G19, 0, 1, 1, 0.9,2,0.75,3,0.6,4,0.55,5,0.5)*IF(B19>=6, 0.95, 1) -> 0.55 | I19: =$I$2 -> 0 | J19: =SWITCH(I19, 0, 1, 1, 0.9,2,0.75,3,0.6,4,0.55,5,0.5)*IF(B19>=6, 0.95, 1) -> 1 | K19: =$K$2 -> 0 | L19: =SWITCH(K19, 0, 1, 1, 0.9,2,0.75,3,0.6,4,0.55,5,0.5)*IF(B19>=6, 0.95, 1) -> 1
A20: Electronics | B20: 0 | C20: =IF(B20>0, 1-(0.15+B20*0.05), 1) -> 1 | D20: =$B$1 -> 5 | E20: =$B$2 -> 40 | F20: =IF(B20>0, D20*C20,E20) -> 40 | G20: =$G$2 -> 4 | H20: =SWITCH(G20, 0, 1, 1, 0.9,2,0.75,3,0.6,4,0.55,5,0.5)*IF(B20>=6, 0.95, 1) -> 0.55 | I20: =$I$2 -> 0 | J20: =SWITCH(I20, 0, 1, 1, 0.9,2,0.75,3,0.6,4,0.55,5,0.5)*IF(B20>=6, 0.95, 1) -> 1 | K20: =$K$2 -> 0 | L20: =SWITCH(K20, 0, 1, 1, 0.9,2,0.75,3,0.6,4,0.55,5,0.5)*IF(B20>=6, 0.95, 1) -> 1
A21: Industry | B21: 0 | C21: =IF(B21>0, 1-(0.15+B21*0.05), 1) -> 1 | D21: =$B$1 -> 5 | E21: =$B$2 -> 40 | F21: =IF(B21>0, D21*C21,E21) -> 40 | G21: =$G$2 -> 4 | H21: =SWITCH(G21, 0, 1, 1, 0.9,2,0.75,3,0.6,4,0.55,5,0.5)*IF(B21>=6, 0.95, 1) -> 0.55 | I21: =$I$2 -> 0 | J21: =SWITCH(I21, 0, 1, 1, 0.9,2,0.75,3,0.6,4,0.55,5,0.5)*IF(B21>=6, 0.95, 1) -> 1 | K21: =$K$2 -> 0 | L21: =SWITCH(K21, 0, 1, 1, 0.9,2,0.75,3,0.6,4,0.55,5,0.5)*IF(B21>=6, 0.95, 1) -> 1
A22: Mechanics | B22: 0 | C22: =IF(B22>0, 1-(0.15+B22*0.05), 1) -> 1 | D22: =$B$1 -> 5 | E22: =$B$2 -> 40 | F22: =IF(B22>0, D22*C22,E22) -> 40 | G22: =$G$2 -> 4 | H22: =SWITCH(G22, 0, 1, 1, 0.9,2,0.75,3,0.6,4,0.55,5,0.5)*IF(B22>=6, 0.95, 1) -> 0.55 | I22: =$I$2 -> 0 | J22: =SWITCH(I22, 0, 1, 1, 0.9,2,0.75,3,0.6,4,0.55,5,0.5)*IF(B22>=6, 0.95, 1) -> 1 | K22: =$K$2 -> 0 | L22: =SWITCH(K22, 0, 1, 1, 0.9,2,0.75,3,0.6,4,0.55,5,0.5)*IF(B22>=6, 0.95, 1) -> 1
A23: Oil Drilling | B23: 0 | C23: =IF(B23>0, 1-(0.15+B23*0.05), 1) -> 1 | D23: =$B$1 -> 5 | E23: =$B$2 -> 40 | F23: =IF(B23>0, D23*C23,E23) -> 40 | G23: =$G$2 -> 4 | H23: =SWITCH(G23, 0, 1, 1, 0.9,2,0.75,3,0.6,4,0.55,5,0.5)*IF(B23>=6, 0.95, 1) -> 0.55 | I23: =$I$2 -> 0 | J23: =SWITCH(I23, 0, 1, 1, 0.9,2,0.75,3,0.6,4,0.55,5,0.5)*IF(B23>=6, 0.95, 1) -> 1 | K23: =$K$2 -> 0 | L23: =SWITCH(K23, 0, 1, 1, 0.9,2,0.75,3,0.6,4,0.55,5,0.5)*IF(B23>=6, 0.95, 1) -> 1
A24: Farming | B24: 0 | C24: =IF(B24>0, 1-(0.15+B24*0.05), 1) -> 1 | D24: =$B$1 -> 5 | E24: =$B$2 -> 40 | F24: =IF(B24>0, D24*C24,E24) -> 40 | G24: =$G$2 -> 4 | H24: =SWITCH(G24, 0, 1, 1, 0.9,2,0.75,3,0.6,4,0.55,5,0.5)*IF(B24>=6, 0.95, 1) -> 0.55 | I24: =$I$2 -> 0 | J24: =SWITCH(I24, 0, 1, 1, 0.9,2,0.75,3,0.6,4,0.55,5,0.5)*IF(B24>=6, 0.95, 1) -> 1 | K24: =$K$2 -> 0 | L24: =SWITCH(K24, 0, 1, 1, 0.9,2,0.75,3,0.6,4,0.55,5,0.5)*IF(B24>=6, 0.95, 1) -> 1
... A26: Fertilizers | B26: 0 | C26: =IF(B26>0, 1-(0.15+B26*0.05), 1) -> 1 | D26: =$B$1 -> 5 | E26: =$B$2 -> 40 | F26: =IF(B26>0, D26*C26,E26) -> 40 | G26: =$G$2 -> 4 | H26: =SWITCH(G26, 0, 1, 1, 0.9,2,0.75,3,0.6,4,0.55,5,0.5)*IF(B26>=6, 0.95, 1) -> 0.55 | I26: =$I$2 -> 0 | J26: =SWITCH(I26, 0, 1, 1, 0.9,2,0.75,3,0.6,4,0.55,5,0.5)*IF(B26>=6, 0.95, 1) -> 1 | K26: =$K$2 -> 0 | L26: =SWITCH(K26, 0, 1, 1, 0.9,2,0.75,3,0.6,4,0.55,5,0.5)*IF(B26>=6, 0.95, 1) -> 1
A27: Milling | B27: 7 | C27: =IF(B27>0, 1-(0.15+B27*0.05), 1) -> 0.5 | D27: =$B$1 -> 5 | E27: =$B$2 -> 40 | F27: =IF(B27>0, D27*C27,E27) -> 2.5 | G27: 5 | H27: =SWITCH(G27, 0, 1, 1, 0.9,2,0.75,3,0.6,4,0.55,5,0.5)*IF(B27>=6, 0.95, 1) -> 0.475 | I27: =$I$2 -> 0 | J27: =SWITCH(I27, 0, 1, 1, 0.9,2,0.75,3,0.6,4,0.55,5,0.5)*IF(B27>=6, 0.95, 1) -> 0.95 | K27: =$K$2 -> 0 | L27: =SWITCH(K27, 0, 1, 1, 0.9,2,0.75,3,0.6,4,0.55,5,0.5)*IF(B27>=6, 0.95, 1) -> 0.95
A28: Butchery | B28: 0 | C28: =IF(B28>0, 1-(0.15+B28*0.05), 1) -> 1 | D28: =$B$1 -> 5 | E28: =$B$2 -> 40 | F28: =IF(B28>0, D28*C28,E28) -> 40 | G28: =$G$2 -> 4 | H28: =SWITCH(G28, 0, 1, 1, 0.9,2,0.75,3,0.6,4,0.55,5,0.5)*IF(B28>=6, 0.95, 1) -> 0.55 | I28: =$I$2 -> 0 | J28: =SWITCH(I28, 0, 1, 1, 0.9,2,0.75,3,0.6,4,0.55,5,0.5)*IF(B28>=6, 0.95, 1) -> 1 | K28: =$K$2 -> 0 | L28: =SWITCH(K28, 0, 1, 1, 0.9,2,0.75,3,0.6,4,0.55,5,0.5)*IF(B28>=6, 0.95, 1) -> 1
A29: Hunting | B29: 0 | C29: =IF(B29>0, 1-(0.15+B29*0.05), 1) -> 1 | D29: =$B$1 -> 5 | E29: =$B$2 -> 40 | F29: =IF(B29>0, D29*C29,E29) -> 40 | G29: =$G$2 -> 4 | H29: =SWITCH(G29, 0, 1, 1, 0.9,2,0.75,3,0.6,4,0.55,5,0.5)*IF(B29>=6, 0.95, 1) -> 0.55 | I29: =$I$2 -> 0 | J29: =SWITCH(I29, 0, 1, 1, 0.9,2,0.75,3,0.6,4,0.55,5,0.5)*IF(B29>=6, 0.95, 1) -> 1 | K29: =$K$2 -> 0 | L29: =SWITCH(K29, 0, 1, 1, 0.9,2,0.75,3,0.6,4,0.55,5,0.5)*IF(B29>=6, 0.95, 1) -> 1
A30: Smelting | B30: 0 | C30: =IF(B30>0, 1-(0.15+B30*0.05), 1) -> 1 | D30: =$B$1 -> 5 | E30: =$B$2 -> 40 | F30: =IF(B30>0, D30*C30,E30) -> 40 | G30: =$G$2 -> 4 | H30: =SWITCH(G30, 0, 1, 1, 0.9,2,0.75,3,0.6,4,0.55,5,0.5)*IF(B30>=6, 0.95, 1) -> 0.55 | I30: =$I$2 -> 0 | J30: =SWITCH(I30, 0, 1, 1, 0.9,2,0.75,3,0.6,4,0.55,5,0.5)*IF(B30>=6, 0.95, 1) -> 1 | K30: =$K$2 -> 0 | L30: =SWITCH(K30, 0, 1, 1, 0.9,2,0.75,3,0.6,4,0.55,5,0.5)*IF(B30>=6, 0.95, 1) -> 1
A31: Advanced Smelting | B31: 0 | C31: =IF(B31>0, 1-(0.15+B31*0.05), 1) -> 1 | D31: =$B$1 -> 5 | E31: =$B$2 -> 40 | F31: =IF(B31>0, D31*C31,E31) -> 40 | G31: =$G$2 -> 4 | H31: =SWITCH(G31, 0, 1, 1, 0.9,2,0.75,3,0.6,4,0.55,5,0.5)*IF(B31>=6, 0.95, 1) -> 0.55 | I31: =$I$2 -> 0 | J31: =SWITCH(I31, 0, 1, 1, 0.9,2,0.75,3,0.6,4,0.55,5,0.5)*IF(B31>=6, 0.95, 1) -> 1 | K31: =$K$2 -> 0 | L31: =SWITCH(K31, 0, 1, 1, 0.9,2,0.75,3,0.6,4,0.55,5,0.5)*IF(B31>=6, 0.95, 1) -> 1
A32: Shipwright | B32: 0 | C32: =IF(B32>0, 1-(0.15+B32*0.05), 1) -> 1 | D32: =$B$1 -> 5 | E32: =$B$2 -> 40 | F32: =IF(B32>0, D32*C32,E32) -> 40 | G32: =$G$2 -> 4 | H32: =SWITCH(G32, 0, 1, 1, 0.9,2,0.75,3,0.6,4,0.55,5,0.5)*IF(B32>=6, 0.95, 1) -> 0.55 | I32: =$I$2 -> 0 | J32: =SWITCH(I32, 0, 1, 1, 0.9,2,0.75,3,0.6,4,0.55,5,0.5)*IF(B32>=6, 0.95, 1) -> 1 | K32: =$K$2 -> 0 | L32: =SWITCH(K32, 0, 1, 1, 0.9,2,0.75,3,0.6,4,0.55,5,0.5)*IF(B32>=6, 0.95, 1) -> 1
A33: Painting | B33: 3 | C33: =IF(B33>0, 1-(0.15+B33*0.05), 1) -> 0.7 | D33: =$B$1 -> 5 | E33: =$B$2 -> 40 | F33: =IF(B33>0, D33*C33,E33) -> 3.5 | G33: =$G$2 -> 4 | H33: =SWITCH(G33, 0, 1, 1, 0.9,2,0.75,3,0.6,4,0.55,5,0.5)*IF(B33>=6, 0.95, 1) -> 0.55 | I33: =$I$2 -> 0 | J33: =SWITCH(I33, 0, 1, 1, 0.9,2,0.75,3,0.6,4,0.55,5,0.5)*IF(B33>=6, 0.95, 1) -> 1 | K33: =$K$2 -> 0 | L33: =SWITCH(K33, 0, 1, 1, 0.9,2,0.75,3,0.6,4,0.55,5,0.5)*IF(B33>=6, 0.95, 1) -> 1
A34: None | B34: 0 | C34: =IF(B34>0, 1-(0.15+B34*0.05), 1) -> 1 | D34: =$B$1 -> 5 | E34: =$B$2 -> 40 | F34: =IF(B34>0, D34*C34,E34) -> 40 | G34: =$G$2 -> 4 | H34: =SWITCH(G34, 0, 1, 1, 0.9,2,0.75,3,0.6,4,0.55,5,0.5)*IF(B34>=6, 0.95, 1) -> 0.55 | I34: =$I$2 -> 0 | J34: =SWITCH(I34, 0, 1, 1, 0.9,2,0.75,3,0.6,4,0.55,5,0.5)*IF(B34>=6, 0.95, 1) -> 1 | K34: =$K$2 -> 0 | L34: =SWITCH(K34, 0, 1, 1, 0.9,2,0.75,3,0.6,4,0.55,5,0.5)*IF(B34>=6, 0.95, 1) -> 1
A35: Tailoring | B35: 0 | C35: =IF(B35>0, 1-(0.15+B35*0.05), 1) -> 1 | D35: =$B$1 -> 5 | E35: =$B$2 -> 40 | F35: =IF(B35>0, D35*C35,E35) -> 40 | G35: =$G$2 -> 4 | H35: =SWITCH(G35, 0, 1, 1, 0.9,2,0.75,3,0.6,4,0.55,5,0.5)*IF(B35>=6, 0.95, 1) -> 0.55 | I35: =$I$2 -> 0 | J35: =SWITCH(I35, 0, 1, 1, 0.9,2,0.75,3,0.6,4,0.55,5,0.5)*IF(B35>=6, 0.95, 1) -> 1 | K35: =$K$2 -> 0 | L35: =SWITCH(K35, 0, 1, 1, 0.9,2,0.75,3,0.6,4,0.55,5,0.5)*IF(B35>=6, 0.95, 1) -> 1
A39: Burnables | B39: Price | C39: Joules | D39: $/J
A40: Charcoal | B40: 1.2 | C40: 20000 | D40: =B40/C40 -> 6e-05
A41: Crushed Coal | B41: 3 | C41: 80000 | D41: =B41/C41 -> 3.75e-05
A42: Cheapest | D42: =MIN(D40:D41) -> 3.75e-05
A44: Electricity | B44: Watts Produced | C44: Watts Consumed | D44: $/s | E44: $/w Electric | F44: PPM/h
A45: Combustion Generator | B45: 3000 | C45: 0 | D45: =$D$42*C45 -> 0 | E45: =D45/B45 -> 0 | F45: 1.12

Sheet Shop 1 Prices
A1: Selling | B1: Total Markup: | C1: =(1+G1)*(1/(1-$E$1)) -> 1.875 | D1: Tax | E1: 0.2 | F1: Markup: | G1: 0.5 | I1: Buying | J1: Markup: | K1: 0.8
A2: Item | B2: Shop Price | C2: Flat Addition | D2: Individual Markup | E2: Override? | F2: Cost Override | G2: Cost | H2: Test | I2: Item | J2: Shop Price | K2: Individual Markup | L2: Override? | M2: Cost Override | N2: Cost
A3: Basic Upgrade 1 | B3: =IF(ISBLANK(A3),"", IFERROR(IF(E3, F3, G3) * IF(ISBLANK(D3), C$1,D3) + C3, "")) -> 129.375 | E3: FALSE | G3: =IFERROR(VLOOKUP(A3, 'Price Sheet'!$A$2:$B1010, 2, false), "") -> 69 | I3: Wood (Tag) | J3: =IF(ISBLANK(I3),"", IFERROR(IF(L3, M3, N3) * IF(ISBLANK(K3), K$1,K3), "")) -> 0.4 | L3: FALSE | N3: =IFERROR(VLOOKUP(I3, 'Price Sheet'!$A$2:$B1010, 2, false), "") -> 0.5
A4: Basic Upgrade 2 | B4: =IF(ISBLANK(A4),"", IFERROR(IF(E4, F4, G4) * IF(ISBLANK(D4), C$1,D4) + C4, "")) -> 238.125 | E4: FALSE | G4: =IFERROR(VLOOKUP(A4, 'Price Sheet'!$A$2:$B1010, 2, false), "") -> 127 | J4: =IF(ISBLANK(I4),"", IFERROR(IF(L4, M4, N4) * IF(ISBLANK(K4), K$1,K4), "")) | L4: FALSE | N4: =IFERROR(VLOOKUP(I4, 'Price Sheet'!$A$2:$B1010, 2, false), "")
A5: Basic Upgrade 3 | B5: =IF(ISBLANK(A5),"", IFERROR(IF(E5, F5, G5) * IF(ISBLANK(D5), C$1,D5) + C5, "")) -> 871.875 | E5: FALSE | G5: =IFERROR(VLOOKUP(A5, 'Price Sheet'!$A$2:$B1010, 2, false), "") -> 465 | J5: =IF(ISBLANK(I5),"", IFERROR(IF(L5, M5, N5) * IF(ISBLANK(K5), K$1,K5), "")) | L5: FALSE | N5: =IFERROR(VLOOKUP(I5, 'Price Sheet'!$A$2:$B1010, 2, false), "")
A6: Basic Upgrade 4 | B6: =IF(ISBLANK(A6),"", IFERROR(IF(E6, F6, G6) * IF(ISBLANK(D6), C$1,D6) + C6, "")) -> 1229.1562 | E6: FALSE | G6: =IFERROR(VLOOKUP(A6, 'Price Sheet'!$A$2:$B1010, 2, false), "") -> 655.55 | J6: =IF(ISBLANK(I6),"", IFERROR(IF(L6, M6, N6) * IF(ISBLANK(K6), K$1,K6), "")) | L6: FALSE | N6: =IFERROR(VLOOKUP(I6, 'Price Sheet'!$A$2:$B1010, 2, false), "")
B7: =IF(ISBLANK(A7),"", IFERROR(IF(E7, F7, G7) * IF(ISBLANK(D7), C$1,D7) + C7, "")) | E7: FALSE | G7: =IFERROR(VLOOKUP(A7, 'Price Sheet'!$A$2:$B1010, 2, false), "") | J7: =IF(ISBLANK(I7),"", IFERROR(IF(L7, M7, N7) * IF(ISBLANK(K7), K$1,K7), "")) | L7: FALSE | N7: =IFERROR(VLOOKUP(I7, 'Price Sheet'!$A$2:$B1010, 2, false), "")
A8: Blue Powder | B8: =IF(ISBLANK(A8),"", IFERROR(IF(E8, F8, G8) * IF(ISBLANK(D8), C$1,D8) + C8, "")) -> 0.04921875 | E8: FALSE | G8: =IFERROR(VLOOKUP(A8, 'Price Sheet'!$A$2:$B1010, 2, false), "") -> 0.02625 | J8: =IF(ISBLANK(I8),"", IFERROR(IF(L8, M8, N8) * IF(ISBLANK(K8), K$1,K8), "")) | L8: FALSE | N8: =IFERROR(VLOOKUP(I8, 'Price Sheet'!$A$2:$B1010, 2, false), "")
A9: Colored Powder | B9: =IF(ISBLANK(A9),"", IFERROR(IF(E9, F9, G9) * IF(ISBLANK(D9), C$1,D9) + C9, "")) -> 0.46875 | E9: FALSE | G9: =IFERROR(VLOOKUP(A9, 'Price Sheet'!$A$2:$B1010, 2, false), "") -> 0.25 | J9: =IF(ISBLANK(I9),"", IFERROR(IF(L9, M9, N9) * IF(ISBLANK(K9), K$1,K9), "")) | L9: FALSE | N9: =IFERROR(VLOOKUP(I9, 'Price Sheet'!$A$2:$B1010, 2, false), "")
A10: Copper Hydroxide | B10: =IF(ISBLANK(A10),"", IFERROR(IF(E10, F10, G10) * IF(ISBLANK(D10), C$1,D10) + C10, "")) -> 0.38046875 | E10: FALSE | G10: =IFERROR(VLOOKUP(A10, 'Price Sheet'!$A$2:$B1010, 2, false), "") -> 0.20291667 | J10: =IF(ISBLANK(I10),"", IFERROR(IF(L10, M10, N10) * IF(ISBLANK(K10), K$1,K10), "")) | L10: FALSE | N10: =IFERROR(VLOOKUP(I10, 'Price Sheet'!$A$2:$B1010, 2, false), "")
A11: Cyan Powder | B11: =IF(ISBLANK(A11),"", IFERROR(IF(E11, F11, G11) * IF(ISBLANK(D11), C$1,D11) + C11, "")) -> 0.18633333 | E11: FALSE | G11: =IFERROR(VLOOKUP(A11, 'Price Sheet'!$A$2:$B1010, 2, false), "") -> 0.099377778 | J11: =IF(ISBLANK(I11),"", IFERROR(IF(L11, M11, N11) * IF(ISBLANK(K11), K$1,K11), "")) | L11: FALSE | N11: =IFERROR(VLOOKUP(I11, 'Price Sheet'!$A$2:$B1010, 2, false), "")
A12: Iron Oxide | B12: =IF(ISBLANK(A12),"", IFERROR(IF(E12, F12, G12) * IF(ISBLANK(D12), C$1,D12) + C12, "")) -> 0.29238281 | E12: FALSE | G12: =IFERROR(VLOOKUP(A12, 'Price Sheet'!$A$2:$B1010, 2, false), "") -> 0.1559375 | J12: =IF(ISBLANK(I12),"", IFERROR(IF(L12, M12, N12) * IF(ISBLANK(K12), K$1,K12), "")) | L12: FALSE | N12: =IFERROR(VLOOKUP(I12, 'Price Sheet'!$A$2:$B1010, 2, false), "")
A13: Charcoal Powder | B13: =IF(ISBLANK(A13),"", IFERROR(IF(E13, F13, G13) * IF(ISBLANK(D13), C$1,D13) + C13, "")) -> 0.200625 | E13: FALSE | G13: =IFERROR(VLOOKUP(A13, 'Price Sheet'!$A$2:$B1010, 2, false), "") -> 0.107 | J13: =IF(ISBLANK(I13),"", IFERROR(IF(L13, M13, N13) * IF(ISBLANK(K13), K$1,K13), "")) | L13: FALSE | N13: =IFERROR(VLOOKUP(I13, 'Price Sheet'!$A$2:$B1010, 2, false), "")
A14: Magenta Powder | B14: =IF(ISBLANK(A14),"", IFERROR(IF(E14, F14, G14) * IF(ISBLANK(D14), C$1,D14) + C14, "")) -> 0.200625 | E14: FALSE | G14: =IFERROR(VLOOKUP(A14, 'Price Sheet'!$A$2:$B1010, 2, false), "") -> 0.107 | J14: =IF(ISBLANK(I14),"", IFERROR(IF(L14, M14, N14) * IF(ISBLANK(K14), K$1,K14), "")) | L14: FALSE | N14: =IFERROR(VLOOKUP(I14, 'Price Sheet'!$A$2:$B1010, 2, false), "")
A15: White Powder | B15: =IF(ISBLANK(A15),"", IFERROR(IF(E15, F15, G15) * IF(ISBLANK(D15), C$1,D15) + C15, "")) -> 0.0403125 | E15: FALSE | G15: =IFERROR(VLOOKUP(A15, 'Price Sheet'!$A$2:$B1010, 2, false), "") -> 0.0215 | J15: =IF(ISBLANK(I15),"", IFERROR(IF(L15, M15, N15) * IF(ISBLANK(K15), K$1,K15), "")) | L15: FALSE | N15: =IFERROR(VLOOKUP(I15, 'Price Sheet'!$A$2:$B1010, 2, false), "")
A16: Yellow Powder | B16: =IF(ISBLANK(A16),"", IFERROR(IF(E16, F16, G16) * IF(ISBLANK(D16), C$1,D16) + C16, "")) -> 0.075 | E16: FALSE | G16: =IFERROR(VLOOKUP(A16, 'Price Sheet'!$A$2:$B1010, 2, false), "") -> 0.04 | J16: =IF(ISBLANK(I16),"", IFERROR(IF(L16, M16, N16) * IF(ISBLANK(K16), K$1,K16), "")) | L16: FALSE | N16: =IFERROR(VLOOKUP(I16, 'Price Sheet'!$A$2:$B1010, 2, false), "")
B17: =IF(ISBLANK(A17),"", IFERROR(IF(E17, F17, G17) * IF(ISBLANK(D17), C$1,D17) + C17, "")) | E17: FALSE | G17: =IFERROR(VLOOKUP(A17, 'Price Sheet'!$A$2:$B1010, 2, false), "") | J17: =IF(ISBLANK(I17),"", IFERROR(IF(L17, M17, N17) * IF(ISBLANK(K17), K$1,K17), "")) | L17: FALSE | N17: =IFERROR(VLOOKUP(I17, 'Price Sheet'!$A$2:$B1010, 2, false), "")
B18: =IF(ISBLANK(A18),"", IFERROR(IF(E18, F18, G18) * IF(ISBLANK(D18), C$1,D18) + C18, "")) | E18: FALSE | G18: =IFERROR(VLOOKUP(A18, 'Price Sheet'!$A$2:$B1010, 2, false), "") | J18: =IF(ISBLANK(I18),"", IFERROR(IF(L18, M18, N18) * IF(ISBLANK(K18), K$1,K18), "")) | L18: FALSE | N18: =IFERROR(VLOOKUP(I18, 'Price Sheet'!$A$2:$B1010, 2, false), "")
A19: Flaxseed Oil | B19: =IF(ISBLANK(A19),"", IFERROR(IF(E19, F19, G19) * IF(ISBLANK(D19), C$1,D19) + C19, "")) -> 2.2546875 | E19: FALSE | G19: =IFERROR(VLOOKUP(A19, 'Price Sheet'!$A$2:$B1010, 2, false), "") -> 1.2025 | J19: =IF(ISBLANK(I19),"", IFERROR(IF(L19, M19, N19) * IF(ISBLANK(K19), K$1,K19), "")) | L19: FALSE | N19: =IFERROR(VLOOKUP(I19, 'Price Sheet'!$A$2:$B1010, 2, false), "")
A20: Oil | B20: =IF(ISBLANK(A20),"", IFERROR(IF(E20, F20, G20) * IF(ISBLANK(D20), C$1,D20) + C20, "")) -> 0.992 | D20: 1.6 | E20: FALSE | G20: =IFERROR(VLOOKUP(A20, 'Price Sheet'!$A$2:$B1010, 2, false), "") -> 0.62 | J20: =IF(ISBLANK(I20),"", IFERROR(IF(L20, M20, N20) * IF(ISBLANK(K20), K$1,K20), "")) | L20: FALSE | N20: =IFERROR(VLOOKUP(I20, 'Price Sheet'!$A$2:$B1010, 2, false), "")
A21: Flour | B21: =IF(ISBLANK(A21),"", IFERROR(IF(E21, F21, G21) * IF(ISBLANK(D21), C$1,D21) + C21, "")) -> 0.8953125 | E21: FALSE | G21: =IFERROR(VLOOKUP(A21, 'Price Sheet'!$A$2:$B1010, 2, false), "") -> 0.4775 | J21: =IF(ISBLANK(I21),"", IFERROR(IF(L21, M21, N21) * IF(ISBLANK(K21), K$1,K21), "")) | L21: FALSE | N21: =IFERROR(VLOOKUP(I21, 'Price Sheet'!$A$2:$B1010, 2, false), "")
A22: Rice Flour | B22: =IF(ISBLANK(A22),"", IFERROR(IF(E22, F22, G22) * IF(ISBLANK(D22), C$1,D22) + C22, "")) -> 0.3609375 | E22: FALSE | G22: =IFERROR(VLOOKUP(A22, 'Price Sheet'!$A$2:$B1010, 2, false), "") -> 0.1925 | L22: FALSE
A23: Cornmeal | B23: =IF(ISBLANK(A23),"", IFERROR(IF(E23, F23, G23) * IF(ISBLANK(D23), C$1,D23) + C23, "")) -> 1.7203125 | E23: FALSE | G23: =IFERROR(VLOOKUP(A23, 'Price Sheet'!$A$2:$B1010, 2, false), "") -> 0.9175 | L23: FALSE
A24: Sugar | B24: =IF(ISBLANK(A24),"", IFERROR(IF(E24, F24, G24) * IF(ISBLANK(D24), C$1,D24) + C24, "")) -> 1.1390625 | E24: FALSE | G24: =IFERROR(VLOOKUP(A24, 'Price Sheet'!$A$2:$B1010, 2, false), "") -> 0.6075 | L24: FALSE
A25: Simple Syrup | B25: =IF(ISBLANK(A25),"", IFERROR(IF(E25, F25, G25) * IF(ISBLANK(D25), C$1,D25) + C25, "")) -> 5.4808594 | E25: FALSE | G25: =IFERROR(VLOOKUP(A25, 'Price Sheet'!$A$2:$B1010, 2, false), "") -> 2.923125 | L25: FALSE
A26: Huckleberry Extract | B26: =IF(ISBLANK(A26),"", IFERROR(IF(E26, F26, G26) * IF(ISBLANK(D26), C$1,D26) + C26, "")) -> 2.7421875 | E26: FALSE | G26: =IFERROR(VLOOKUP(A26, 'Price Sheet'!$A$2:$B1010, 2, false), "") -> 1.4625 | L26: TRUE
A27: Yeast | B27: =IF(ISBLANK(A27),"", IFERROR(IF(E27, F27, G27) * IF(ISBLANK(D27), C$1,D27) + C27, "")) -> 1.1524219 | E27: FALSE | G27: =IFERROR(VLOOKUP(A27, 'Price Sheet'!$A$2:$B1010, 2, false), "") -> 0.614625 | L27: FALSE
A28: Sun Cheese | B28: =IF(ISBLANK(A28),"", IFERROR(IF(E28, F28, G28) * IF(ISBLANK(D28), C$1,D28) + C28, "")) -> 4.4069883 | E28: FALSE | G28: =IFERROR(VLOOKUP(A28, 'Price Sheet'!$A$2:$B1010, 2, false), "") -> 2.3503937 | L28: FALSE
A29: Camas Paste | B29: =IF(ISBLANK(A29),"", IFERROR(IF(E29, F29, G29) * IF(ISBLANK(D29), C$1,D29) + C29, "")) -> 1.8515625 | E29: FALSE | G29: =IFERROR(VLOOKUP(A29, 'Price Sheet'!$A$2:$B1010, 2, false), "") -> 0.9875 | L29: FALSE
B30: =IF(ISBLANK(A30),"", IFERROR(IF(E30, F30, G30) * IF(ISBLANK(D30), C$1,D30) + C30, "")) | E30: FALSE | G30: =IFERROR(VLOOKUP(A30, 'Price Sheet'!$A$2:$B1010, 2, false), "") | L30: FALSE
A31: Base Paint | B31: =IF(ISBLANK(A31),"", IFERROR(IF(E31, F31, G31) * IF(ISBLANK(D31), C$1,D31) + C31, "")) -> 0.36924375 | E31: FALSE | G31: =IFERROR(VLOOKUP(A31, 'Price Sheet'!$A$2:$B1010, 2, false), "") -> 0.19693 | L31: FALSE
A32: Art Supplies | B32: =IF(ISBLANK(A32),"", IFERROR(IF(E32, F32, G32) * IF(ISBLANK(D32), C$1,D32) + C32, "")) -> 4.5195718 | E32: FALSE | G32: =IFERROR(VLOOKUP(A32, 'Price Sheet'!$A$2:$B1010, 2, false), "") -> 2.4104383 | J32: =IF(ISBLANK(I32),"", IFERROR(IF(L32, M32, N32) * IF(ISBLANK(K32), K$1,K32), "")) | L32: FALSE | N32: =IFERROR(VLOOKUP(I32, 'Price Sheet'!$A$2:$B1010, 2, false), "")
A33: Ink | B33: =IF(ISBLANK(A33),"", IFERROR(IF(E33, F33, G33) * IF(ISBLANK(D33), C$1,D33) + C33, "")) -> 2.5675313 | E33: FALSE | G33: =IFERROR(VLOOKUP(A33, 'Price Sheet'!$A$2:$B1010, 2, false), "") -> 1.36935 | J33: =IF(ISBLANK(I33),"", IFERROR(IF(L33, M33, N33) * IF(ISBLANK(K33), K$1,K33), "")) | L33: FALSE | N33: =IFERROR(VLOOKUP(I33, 'Price Sheet'!$A$2:$B1010, 2, false), "")
A34: Decorative Book | B34: =IF(ISBLANK(A34),"", IFERROR(IF(E34, F34, G34) * IF(ISBLANK(D34), C$1,D34) + C34, "")) -> 69.611784 | E34: FALSE | G34: =IFERROR(VLOOKUP(A34, 'Price Sheet'!$A$2:$B1010, 2, false), "") -> 37.126285 | J34: =IF(ISBLANK(I34),"", IFERROR(IF(L34, M34, N34) * IF(ISBLANK(K34), K$1,K34), "")) | L34: FALSE | N34: =IFERROR(VLOOKUP(I34, 'Price Sheet'!$A$2:$B1010, 2, false), "")
B35: =IF(ISBLANK(A35),"", IFERROR(IF(E35, F35, G35) * IF(ISBLANK(D35), C$1,D35) + C35, "")) | E35: FALSE | G35: =IFERROR(VLOOKUP(A35, 'Price Sheet'!$A$2:$B1010, 2, false), "") | J35: =IF(ISBLANK(I35),"", IFERROR(IF(L35, M35, N35) * IF(ISBLANK(K35), K$1,K35), "")) | L35: FALSE | N35: =IFERROR(VLOOKUP(I35, 'Price Sheet'!$A$2:$B1010, 2, false), "")
B36: =IF(ISBLANK(A36),"", IFERROR(IF(E36, F36, G36) * IF(ISBLANK(D36), C$1,D36) + C36, "")) | E36: FALSE | G36: =IFERROR(VLOOKUP(A36, 'Price Sheet'!$A$2:$B1010, 2, false), "") | J36: =IF(ISBLANK(I36),"", IFERROR(IF(L36, M36, N36) * IF(ISBLANK(K36), K$1,K36), "")) | L36: FALSE | N36: =IFERROR(VLOOKUP(I36, 'Price Sheet'!$A$2:$B1010, 2, false), "")
B37: =IF(ISBLANK(A37),"", IFERROR(IF(E37, F37, G37) * IF(ISBLANK(D37), C$1,D37) + C37, "")) | E37: FALSE | G37: =IFERROR(VLOOKUP(A37, 'Price Sheet'!$A$2:$B1010, 2, false), "") | J37: =IF(ISBLANK(I37),"", IFERROR(IF(L37, M37, N37) * IF(ISBLANK(K37), K$1,K37), "")) | L37: FALSE | N37: =IFERROR(VLOOKUP(I37, 'Price Sheet'!$A$2:$B1010, 2, false), "")
B38: =IF(ISBLANK(A38),"", IFERROR(IF(E38, F38, G38) * IF(ISBLANK(D38), C$1,D38) + C38, "")) | E38: FALSE | G38: =IFERROR(VLOOKUP(A38, 'Price Sheet'!$A$2:$B1010, 2, false), "") | J38: =IF(ISBLANK(I38),"", IFERROR(IF(L38, M38, N38) * IF(ISBLANK(K38), K$1,K38), "")) | L38: FALSE | N38: =IFERROR(VLOOKUP(I38, 'Price Sheet'!$A$2:$B1010, 2, false), "")
B39: =IF(ISBLANK(A39),"", IFERROR(IF(E39, F39, G39) * IF(ISBLANK(D39), C$1,D39) + C39, "")) | E39: FALSE | G39: =IFERROR(VLOOKUP(A39, 'Price Sheet'!$A$2:$B1010, 2, false), "") | J39: =IF(ISBLANK(I39),"", IFERROR(IF(L39, M39, N39) * IF(ISBLANK(K39), K$1,K39), "")) | L39: FALSE | N39: =IFERROR(VLOOKUP(I39, 'Price Sheet'!$A$2:$B1010, 2, false), "")
B40: =IF(ISBLANK(A40),"", IFERROR(IF(E40, F40, G40) * IF(ISBLANK(D40), C$1,D40) + C40, "")) | E40: FALSE | G40: =IFERROR(VLOOKUP(A40, 'Price Sheet'!$A$2:$B1010, 2, false), "") | J40: =IF(ISBLANK(I40),"", IFERROR(IF(L40, M40, N40) * IF(ISBLANK(K40), K$1,K40), "")) | L40: FALSE | N40: =IFERROR(VLOOKUP(I40, 'Price Sheet'!$A$2:$B1010, 2, false), "")
B41: =IF(ISBLANK(A41),"", IFERROR(IF(E41, F41, G41) * IF(ISBLANK(D41), C$1,D41) + C41, "")) | E41: FALSE | G41: =IFERROR(VLOOKUP(A41, 'Price Sheet'!$A$2:$B1010, 2, false), "") | J41: =IF(ISBLANK(I41),"", IFERROR(IF(L41, M41, N41) * IF(ISBLANK(K41), K$1,K41), "")) | L41: FALSE | N41: =IFERROR(VLOOKUP(I41, 'Price Sheet'!$A$2:$B1010, 2, false), "")
B42: =IF(ISBLANK(A42),"", IFERROR(IF(E42, F42, G42) * IF(ISBLANK(D42), C$1,D42) + C42, "")) | E42: FALSE | G42: =IFERROR(VLOOKUP(A42, 'Price Sheet'!$A$2:$B1010, 2, false), "") | J42: =IF(ISBLANK(I42),"", IFERROR(IF(L42, M42, N42) * IF(ISBLANK(K42), K$1,K42), "")) | L42: FALSE | N42: =IFERROR(VLOOKUP(I42, 'Price Sheet'!$A$2:$B1010, 2, false), "")
B43: =IF(ISBLANK(A43),"", IFERROR(IF(E43, F43, G43) * IF(ISBLANK(D43), C$1,D43) + C43, "")) | E43: FALSE | G43: =IFERROR(VLOOKUP(A43, 'Price Sheet'!$A$2:$B1010, 2, false), "") | J43: =IF(ISBLANK(I43),"", IFERROR(IF(L43, M43, N43) * IF(ISBLANK(K43), K$1,K43), "")) | L43: FALSE | N43: =IFERROR(VLOOKUP(I43, 'Price Sheet'!$A$2:$B1010, 2, false), "")
B44: =IF(ISBLANK(A44),"", IFERROR(IF(E44, F44, G44) * IF(ISBLANK(D44), C$1,D44) + C44, "")) | E44: FALSE | G44: =IFERROR(VLOOKUP(A44, 'Price Sheet'!$A$2:$B1010, 2, false), "") | J44: =IF(ISBLANK(I44),"", IFERROR(IF(L44, M44, N44) * IF(ISBLANK(K44), K$1,K44), "")) | L44: FALSE | N44: =IFERROR(VLOOKUP(I44, 'Price Sheet'!$A$2:$B1010, 2, false), "")
B45: =IF(ISBLANK(A45),"", IFERROR(IF(E45, F45, G45) * IF(ISBLANK(D45), C$1,D45) + C45, "")) | E45: FALSE | G45: =IFERROR(VLOOKUP(A45, 'Price Sheet'!$A$2:$B1010, 2, false), "") | J45: =IF(ISBLANK(I45),"", IFERROR(IF(L45, M45, N45) * IF(ISBLANK(K45), K$1,K45), "")) | L45: FALSE | N45: =IFERROR(VLOOKUP(I45, 'Price Sheet'!$A$2:$B1010, 2, false), "")
B46: =IF(ISBLANK(A46),"", IFERROR(IF(E46, F46, G46) * IF(ISBLANK(D46), C$1,D46) + C46, "")) | E46: FALSE | G46: =IFERROR(VLOOKUP(A46, 'Price Sheet'!$A$2:$B1010, 2, false), "") | J46: =IF(ISBLANK(I46),"", IFERROR(IF(L46, M46, N46) * IF(ISBLANK(K46), K$1,K46), "")) | L46: FALSE | N46: =IFERROR(VLOOKUP(I46, 'Price Sheet'!$A$2:$B1010, 2, false), "")
B47: =IF(ISBLANK(A47),"", IFERROR(IF(E47, F47, G47) * IF(ISBLANK(D47), C$1,D47) + C47, "")) | E47: FALSE | G47: =IFERROR(VLOOKUP(A47, 'Price Sheet'!$A$2:$B1010, 2, false), "") | J47: =IF(ISBLANK(I47),"", IFERROR(IF(L47, M47, N47) * IF(ISBLANK(K47), K$1,K47), "")) | L47: FALSE | N47: =IFERROR(VLOOKUP(I47, 'Price Sheet'!$A$2:$B1010, 2, false), "")
B48: =IF(ISBLANK(A48),"", IFERROR(IF(E48, F48, G48) * IF(ISBLANK(D48), C$1,D48) + C48, "")) | E48: FALSE | G48: =IFERROR(VLOOKUP(A48, 'Price Sheet'!$A$2:$B1010, 2, false), "") | J48: =IF(ISBLANK(I48),"", IFERROR(IF(L48, M48, N48) * IF(ISBLANK(K48), K$1,K48), "")) | L48: FALSE | N48: =IFERROR(VLOOKUP(I48, 'Price Sheet'!$A$2:$B1010, 2, false), "")
B49: =IF(ISBLANK(A49),"", IFERROR(IF(E49, F49, G49) * IF(ISBLANK(D49), C$1,D49) + C49, "")) | E49: FALSE | G49: =IFERROR(VLOOKUP(A49, 'Price Sheet'!$A$2:$B1010, 2, false), "") | J49: =IF(ISBLANK(I49),"", IFERROR(IF(L49, M49, N49) * IF(ISBLANK(K49), K$1,K49), "")) | L49: FALSE | N49: =IFERROR(VLOOKUP(I49, 'Price Sheet'!$A$2:$B1010, 2, false), "")
B50: =IF(ISBLANK(A50),"", IFERROR(IF(E50, F50, G50) * IF(ISBLANK(D50), C$1,D50) + C50, "")) | E50: FALSE | G50: =IFERROR(VLOOKUP(A50, 'Price Sheet'!$A$2:$B1010, 2, false), "") | J50: =IF(ISBLANK(I50),"", IFERROR(IF(L50, M50, N50) * IF(ISBLANK(K50), K$1,K50), "")) | L50: FALSE | N50: =IFERROR(VLOOKUP(I50, 'Price Sheet'!$A$2:$B1010, 2, false), "")
B51: =IF(ISBLANK(A51),"", IFERROR(IF(E51, F51, G51) * IF(ISBLANK(D51), C$1,D51) + C51, "")) | E51: FALSE | G51: =IFERROR(VLOOKUP(A51, 'Price Sheet'!$A$2:$B1010, 2, false), "") | J51: =IF(ISBLANK(I51),"", IFERROR(IF(L51, M51, N51) * IF(ISBLANK(K51), K$1,K51), "")) | L51: FALSE | N51: =IFERROR(VLOOKUP(I51, 'Price Sheet'!$A$2:$B1010, 2, false), "")
B52: =IF(ISBLANK(A52),"", IFERROR(IF(E52, F52, G52) * IF(ISBLANK(D52), C$1,D52) + C52, "")) | E52: FALSE | G52: =IFERROR(VLOOKUP(A52, 'Price Sheet'!$A$2:$B1010, 2, false), "") | J52: =IF(ISBLANK(I52),"", IFERROR(IF(L52, M52, N52) * IF(ISBLANK(K52), K$1,K52), "")) | L52: FALSE | N52: =IFERROR(VLOOKUP(I52, 'Price Sheet'!$A$2:$B1010, 2, false), "")
B53: =IF(ISBLANK(A53),"", IFERROR(IF(E53, F53, G53) * IF(ISBLANK(D53), C$1,D53) + C53, "")) | E53: FALSE | G53: =IFERROR(VLOOKUP(A53, 'Price Sheet'!$A$2:$B1010, 2, false), "") | J53: =IF(ISBLANK(I53),"", IFERROR(IF(L53, M53, N53) * IF(ISBLANK(K53), K$1,K53), "")) | L53: FALSE | N53: =IFERROR(VLOOKUP(I53, 'Price Sheet'!$A$2:$B1010, 2, false), "")
B54: =IF(ISBLANK(A54),"", IFERROR(IF(E54, F54, G54) * IF(ISBLANK(D54), C$1,D54) + C54, "")) | E54: FALSE | G54: =IFERROR(VLOOKUP(A54, 'Price Sheet'!$A$2:$B1010, 2, false), "") | J54: =IF(ISBLANK(I54),"", IFERROR(IF(L54, M54, N54) * IF(ISBLANK(K54), K$1,K54), "")) | L54: FALSE | N54: =IFERROR(VLOOKUP(I54, 'Price Sheet'!$A$2:$B1010, 2, false), "")
B55: =IF(ISBLANK(A55),"", IFERROR(IF(E55, F55, G55) * IF(ISBLANK(D55), C$1,D55) + C55, "")) | E55: FALSE | G55: =IFERROR(VLOOKUP(A55, 'Price Sheet'!$A$2:$B1010, 2, false), "") | J55: =IF(ISBLANK(I55),"", IFERROR(IF(L55, M55, N55) * IF(ISBLANK(K55), K$1,K55), "")) | L55: FALSE | N55: =IFERROR(VLOOKUP(I55, 'Price Sheet'!$A$2:$B1010, 2, false), "")
B56: =IF(ISBLANK(A56),"", IFERROR(IF(E56, F56, G56) * IF(ISBLANK(D56), C$1,D56) + C56, "")) | E56: FALSE | G56: =IFERROR(VLOOKUP(A56, 'Price Sheet'!$A$2:$B1010, 2, false), "") | J56: =IF(ISBLANK(I56),"", IFERROR(IF(L56, M56, N56) * IF(ISBLANK(K56), K$1,K56), "")) | L56: FALSE | N56: =IFERROR(VLOOKUP(I56, 'Price Sheet'!$A$2:$B1010, 2, false), "")
B57: =IF(ISBLANK(A57),"", IFERROR(IF(E57, F57, G57) * IF(ISBLANK(D57), C$1,D57) + C57, "")) | E57: FALSE | G57: =IFERROR(VLOOKUP(A57, 'Price Sheet'!$A$2:$B1010, 2, false), "") | J57: =IF(ISBLANK(I57),"", IFERROR(IF(L57, M57, N57) * IF(ISBLANK(K57), K$1,K57), "")) | L57: FALSE | N57: =IFERROR(VLOOKUP(I57, 'Price Sheet'!$A$2:$B1010, 2, false), "")
B58: =IF(ISBLANK(A58),"", IFERROR(IF(E58, F58, G58) * IF(ISBLANK(D58), C$1,D58) + C58, "")) | E58: FALSE | G58: =IFERROR(VLOOKUP(A58, 'Price Sheet'!$A$2:$B1010, 2, false), "") | J58: =IF(ISBLANK(I58),"", IFERROR(IF(L58, M58, N58) * IF(ISBLANK(K58), K$1,K58), "")) | L58: FALSE | N58: =IFERROR(VLOOKUP(I58, 'Price Sheet'!$A$2:$B1010, 2, false), "")
B59: =IF(ISBLANK(A59),"", IFERROR(IF(E59, F59, G59) * IF(ISBLANK(D59), C$1,D59) + C59, "")) | E59: FALSE | G59: =IFERROR(VLOOKUP(A59, 'Price Sheet'!$A$2:$B1010, 2, false), "") | J59: =IF(ISBLANK(I59),"", IFERROR(IF(L59, M59, N59) * IF(ISBLANK(K59), K$1,K59), "")) | L59: FALSE | N59: =IFERROR(VLOOKUP(I59, 'Price Sheet'!$A$2:$B1010, 2, false), "")
B60: =IF(ISBLANK(A60),"", IFERROR(IF(E60, F60, G60) * IF(ISBLANK(D60), C$1,D60) + C60, "")) | E60: FALSE | G60: =IFERROR(VLOOKUP(A60, 'Price Sheet'!$A$2:$B1010, 2, false), "") | J60: =IF(ISBLANK(I60),"", IFERROR(IF(L60, M60, N60) * IF(ISBLANK(K60), K$1,K60), "")) | L60: FALSE | N60: =IFERROR(VLOOKUP(I60, 'Price Sheet'!$A$2:$B1010, 2, false), "")
B61: =IF(ISBLANK(A61),"", IFERROR(IF(E61, F61, G61) * IF(ISBLANK(D61), C$1,D61) + C61, "")) | E61: FALSE | G61: =IFERROR(VLOOKUP(A61, 'Price Sheet'!$A$2:$B1010, 2, false), "") | J61: =IF(ISBLANK(I61),"", IFERROR(IF(L61, M61, N61) * IF(ISBLANK(K61), K$1,K61), "")) | L61: FALSE | N61: =IFERROR(VLOOKUP(I61, 'Price Sheet'!$A$2:$B1010, 2, false), "")
B62: =IF(ISBLANK(A62),"", IFERROR(IF(E62, F62, G62) * IF(ISBLANK(D62), C$1,D62) + C62, "")) | E62: FALSE | G62: =IFERROR(VLOOKUP(A62, 'Price Sheet'!$A$2:$B1010, 2, false), "") | J62: =IF(ISBLANK(I62),"", IFERROR(IF(L62, M62, N62) * IF(ISBLANK(K62), K$1,K62), "")) | L62: FALSE | N62: =IFERROR(VLOOKUP(I62, 'Price Sheet'!$A$2:$B1010, 2, false), "")
B63: =IF(ISBLANK(A63),"", IFERROR(IF(E63, F63, G63) * IF(ISBLANK(D63), C$1,D63) + C63, "")) | E63: FALSE | G63: =IFERROR(VLOOKUP(A63, 'Price Sheet'!$A$2:$B1010, 2, false), "") | J63: =IF(ISBLANK(I63),"", IFERROR(IF(L63, M63, N63) * IF(ISBLANK(K63), K$1,K63), "")) | L63: FALSE | N63: =IFERROR(VLOOKUP(I63, 'Price Sheet'!$A$2:$B1010, 2, false), "")
B64: =IF(ISBLANK(A64),"", IFERROR(IF(E64, F64, G64) * IF(ISBLANK(D64), C$1,D64) + C64, "")) | E64: FALSE | G64: =IFERROR(VLOOKUP(A64, 'Price Sheet'!$A$2:$B1010, 2, false), "") | J64: =IF(ISBLANK(I64),"", IFERROR(IF(L64, M64, N64) * IF(ISBLANK(K64), K$1,K64), "")) | L64: FALSE | N64: =IFERROR(VLOOKUP(I64, 'Price Sheet'!$A$2:$B1010, 2, false), "")
B65: =IF(ISBLANK(A65),"", IFERROR(IF(E65, F65, G65) * IF(ISBLANK(D65), C$1,D65) + C65, "")) | E65: FALSE | G65: =IFERROR(VLOOKUP(A65, 'Price Sheet'!$A$2:$B1010, 2, false), "") | J65: =IF(ISBLANK(I65),"", IFERROR(IF(L65, M65, N65) * IF(ISBLANK(K65), K$1,K65), "")) | L65: FALSE | N65: =IFERROR(VLOOKUP(I65, 'Price Sheet'!$A$2:$B1010, 2, false), "")
B66: =IF(ISBLANK(A66),"", IFERROR(IF(E66, F66, G66) * IF(ISBLANK(D66), C$1,D66) + C66, "")) | E66: FALSE | G66: =IFERROR(VLOOKUP(A66, 'Price Sheet'!$A$2:$B1010, 2, false), "") | J66: =IF(ISBLANK(I66),"", IFERROR(IF(L66, M66, N66) * IF(ISBLANK(K66), K$1,K66), "")) | L66: FALSE | N66: =IFERROR(VLOOKUP(I66, 'Price Sheet'!$A$2:$B1010, 2, false), "")
B67: =IF(ISBLANK(A67),"", IFERROR(IF(E67, F67, G67) * IF(ISBLANK(D67), C$1,D67) + C67, "")) | E67: FALSE | G67: =IFERROR(VLOOKUP(A67, 'Price Sheet'!$A$2:$B1010, 2, false), "") | J67: =IF(ISBLANK(I67),"", IFERROR(IF(L67, M67, N67) * IF(ISBLANK(K67), K$1,K67), "")) | L67: FALSE | N67: =IFERROR(VLOOKUP(I67, 'Price Sheet'!$A$2:$B1010, 2, false), "")
B68: =IF(ISBLANK(A68),"", IFERROR(IF(E68, F68, G68) * IF(ISBLANK(D68), C$1,D68) + C68, "")) | E68: FALSE | G68: =IFERROR(VLOOKUP(A68, 'Price Sheet'!$A$2:$B1010, 2, false), "") | J68: =IF(ISBLANK(I68),"", IFERROR(IF(L68, M68, N68) * IF(ISBLANK(K68), K$1,K68), "")) | L68: FALSE | N68: =IFERROR(VLOOKUP(I68, 'Price Sheet'!$A$2:$B1010, 2, false), "")
B69: =IF(ISBLANK(A69),"", IFERROR(IF(E69, F69, G69) * IF(ISBLANK(D69), C$1,D69) + C69, "")) | E69: FALSE | G69: =IFERROR(VLOOKUP(A69, 'Price Sheet'!$A$2:$B1010, 2, false), "") | J69: =IF(ISBLANK(I69),"", IFERROR(IF(L69, M69, N69) * IF(ISBLANK(K69), K$1,K69), "")) | L69: FALSE | N69: =IFERROR(VLOOKUP(I69, 'Price Sheet'!$A$2:$B1010, 2, false), "")
B70: =IF(ISBLANK(A70),"", IFERROR(IF(E70, F70, G70) * IF(ISBLANK(D70), C$1,D70) + C70, "")) | E70: FALSE | G70: =IFERROR(VLOOKUP(A70, 'Price Sheet'!$A$2:$B1010, 2, false), "") | J70: =IF(ISBLANK(I70),"", IFERROR(IF(L70, M70, N70) * IF(ISBLANK(K70), K$1,K70), "")) | L70: FALSE | N70: =IFERROR(VLOOKUP(I70, 'Price Sheet'!$A$2:$B1010, 2, false), "")
B71: =IF(ISBLANK(A71),"", IFERROR(IF(E71, F71, G71) * IF(ISBLANK(D71), C$1,D71) + C71, "")) | E71: FALSE | G71: =IFERROR(VLOOKUP(A71, 'Price Sheet'!$A$2:$B1010, 2, false), "") | J71: =IF(ISBLANK(I71),"", IFERROR(IF(L71, M71, N71) * IF(ISBLANK(K71), K$1,K71), "")) | L71: FALSE | N71: =IFERROR(VLOOKUP(I71, 'Price Sheet'!$A$2:$B1010, 2, false), "")
B72: =IF(ISBLANK(A72),"", IFERROR(IF(E72, F72, G72) * IF(ISBLANK(D72), C$1,D72) + C72, "")) | E72: FALSE | G72: =IFERROR(VLOOKUP(A72, 'Price Sheet'!$A$2:$B1010, 2, false), "") | J72: =IF(ISBLANK(I72),"", IFERROR(IF(L72, M72, N72) * IF(ISBLANK(K72), K$1,K72), "")) | L72: FALSE | N72: =IFERROR(VLOOKUP(I72, 'Price Sheet'!$A$2:$B1010, 2, false), "")
B73: =IF(ISBLANK(A73),"", IFERROR(IF(E73, F73, G73) * IF(ISBLANK(D73), C$1,D73) + C73, "")) | E73: FALSE | G73: =IFERROR(VLOOKUP(A73, 'Price Sheet'!$A$2:$B1010, 2, false), "") | J73: =IF(ISBLANK(I73),"", IFERROR(IF(L73, M73, N73) * IF(ISBLANK(K73), K$1,K73), "")) | L73: FALSE | N73: =IFERROR(VLOOKUP(I73, 'Price Sheet'!$A$2:$B1010, 2, false), "")
B74: =IF(ISBLANK(A74),"", IFERROR(IF(E74, F74, G74) * IF(ISBLANK(D74), C$1,D74) + C74, "")) | E74: FALSE | G74: =IFERROR(VLOOKUP(A74, 'Price Sheet'!$A$2:$B1010, 2, false), "") | J74: =IF(ISBLANK(I74),"", IFERROR(IF(L74, M74, N74) * IF(ISBLANK(K74), K$1,K74), "")) | L74: FALSE | N74: =IFERROR(VLOOKUP(I74, 'Price Sheet'!$A$2:$B1010, 2, false), "")
B75: =IF(ISBLANK(A75),"", IFERROR(IF(E75, F75, G75) * IF(ISBLANK(D75), C$1,D75) + C75, "")) | E75: FALSE | G75: =IFERROR(VLOOKUP(A75, 'Price Sheet'!$A$2:$B1010, 2, false), "") | J75: =IF(ISBLANK(I75),"", IFERROR(IF(L75, M75, N75) * IF(ISBLANK(K75), K$1,K75), "")) | L75: FALSE | N75: =IFERROR(VLOOKUP(I75, 'Price Sheet'!$A$2:$B1010, 2, false), "")
B76: =IF(ISBLANK(A76),"", IFERROR(IF(E76, F76, G76) * IF(ISBLANK(D76), C$1,D76) + C76, "")) | E76: FALSE | G76: =IFERROR(VLOOKUP(A76, 'Price Sheet'!$A$2:$B1010, 2, false), "") | J76: =IF(ISBLANK(I76),"", IFERROR(IF(L76, M76, N76) * IF(ISBLANK(K76), K$1,K76), "")) | L76: FALSE | N76: =IFERROR(VLOOKUP(I76, 'Price Sheet'!$A$2:$B1010, 2, false), "")
B77: =IF(ISBLANK(A77),"", IFERROR(IF(E77, F77, G77) * IF(ISBLANK(D77), C$1,D77) + C77, "")) | E77: FALSE | G77: =IFERROR(VLOOKUP(A77, 'Price Sheet'!$A$2:$B1010, 2, false), "") | J77: =IF(ISBLANK(I77),"", IFERROR(IF(L77, M77, N77) * IF(ISBLANK(K77), K$1,K77), "")) | L77: FALSE | N77: =IFERROR(VLOOKUP(I77, 'Price Sheet'!$A$2:$B1010, 2, false), "")
B78: =IF(ISBLANK(A78),"", IFERROR(IF(E78, F78, G78) * IF(ISBLANK(D78), C$1,D78) + C78, "")) | E78: FALSE | G78: =IFERROR(VLOOKUP(A78, 'Price Sheet'!$A$2:$B1010, 2, false), "") | J78: =IF(ISBLANK(I78),"", IFERROR(IF(L78, M78, N78) * IF(ISBLANK(K78), K$1,K78), "")) | L78: FALSE | N78: =IFERROR(VLOOKUP(I78, 'Price Sheet'!$A$2:$B1010, 2, false), "")
B79: =IF(ISBLANK(A79),"", IFERROR(IF(E79, F79, G79) * IF(ISBLANK(D79), C$1,D79) + C79, "")) | E79: FALSE | G79: =IFERROR(VLOOKUP(A79, 'Price Sheet'!$A$2:$B1010, 2, false), "") | J79: =IF(ISBLANK(I79),"", IFERROR(IF(L79, M79, N79) * IF(ISBLANK(K79), K$1,K79), "")) | L79: FALSE | N79: =IFERROR(VLOOKUP(I79, 'Price Sheet'!$A$2:$B1010, 2, false), "")
B80: =IF(ISBLANK(A80),"", IFERROR(IF(E80, F80, G80) * IF(ISBLANK(D80), C$1,D80) + C80, "")) | E80: FALSE | G80: =IFERROR(VLOOKUP(A80, 'Price Sheet'!$A$2:$B1010, 2, false), "") | J80: =IF(ISBLANK(I80),"", IFERROR(IF(L80, M80, N80) * IF(ISBLANK(K80), K$1,K80), "")) | L80: FALSE | N80: =IFERROR(VLOOKUP(I80, 'Price Sheet'!$A$2:$B1010, 2, false), "")
B81: =IF(ISBLANK(A81),"", IFERROR(IF(E81, F81, G81) * IF(ISBLANK(D81), C$1,D81) + C81, "")) | E81: FALSE | G81: =IFERROR(VLOOKUP(A81, 'Price Sheet'!$A$2:$B1010, 2, false), "") | J81: =IF(ISBLANK(I81),"", IFERROR(IF(L81, M81, N81) * IF(ISBLANK(K81), K$1,K81), "")) | L81: FALSE | N81: =IFERROR(VLOOKUP(I81, 'Price Sheet'!$A$2:$B1010, 2, false), "")
B82: =IF(ISBLANK(A82),"", IFERROR(IF(E82, F82, G82) * IF(ISBLANK(D82), C$1,D82) + C82, "")) | E82: FALSE | G82: =IFERROR(VLOOKUP(A82, 'Price Sheet'!$A$2:$B1010, 2, false), "") | J82: =IF(ISBLANK(I82),"", IFERROR(IF(L82, M82, N82) * IF(ISBLANK(K82), K$1,K82), "")) | L82: FALSE | N82: =IFERROR(VLOOKUP(I82, 'Price Sheet'!$A$2:$B1010, 2, false), "")
B83: =IF(ISBLANK(A83),"", IFERROR(IF(E83, F83, G83) * IF(ISBLANK(D83), C$1,D83) + C83, "")) | E83: FALSE | G83: =IFERROR(VLOOKUP(A83, 'Price Sheet'!$A$2:$B1010, 2, false), "") | J83: =IF(ISBLANK(I83),"", IFERROR(IF(L83, M83, N83) * IF(ISBLANK(K83), K$1,K83), "")) | L83: FALSE | N83: =IFERROR(VLOOKUP(I83, 'Price Sheet'!$A$2:$B1010, 2, false), "")
B84: =IF(ISBLANK(A84),"", IFERROR(IF(E84, F84, G84) * IF(ISBLANK(D84), C$1,D84) + C84, "")) | E84: FALSE | G84: =IFERROR(VLOOKUP(A84, 'Price Sheet'!$A$2:$B1010, 2, false), "") | J84: =IF(ISBLANK(I84),"", IFERROR(IF(L84, M84, N84) * IF(ISBLANK(K84), K$1,K84), "")) | L84: FALSE | N84: =IFERROR(VLOOKUP(I84, 'Price Sheet'!$A$2:$B1010, 2, false), "")
B85: =IF(ISBLANK(A85),"", IFERROR(IF(E85, F85, G85) * IF(ISBLANK(D85), C$1,D85) + C85, "")) | E85: FALSE | G85: =IFERROR(VLOOKUP(A85, 'Price Sheet'!$A$2:$B1010, 2, false), "") | J85: =IF(ISBLANK(I85),"", IFERROR(IF(L85, M85, N85) * IF(ISBLANK(K85), K$1,K85), "")) | L85: FALSE | N85: =IFERROR(VLOOKUP(I85, 'Price Sheet'!$A$2:$B1010, 2, false), "")
B86: =IF(ISBLANK(A86),"", IFERROR(IF(E86, F86, G86) * IF(ISBLANK(D86), C$1,D86), "")) | E86: FALSE | G86: =IFERROR(VLOOKUP(A86, 'Price Sheet'!$A$2:$B1010, 2, false), "") | J86: =IF(ISBLANK(I86),"", IFERROR(IF(L86, M86, N86) * IF(ISBLANK(K86), K$1,K86), "")) | L86: FALSE | N86: =IFERROR(VLOOKUP(I86, 'Price Sheet'!$A$2:$B1010, 2, false), "")
B87: =IF(ISBLANK(A87),"", IFERROR(IF(E87, F87, G87) * IF(ISBLANK(D87), C$1,D87), "")) | E87: FALSE | G87: =IFERROR(VLOOKUP(A87, 'Price Sheet'!$A$2:$B1010, 2, false), "") | J87: =IF(ISBLANK(I87),"", IFERROR(IF(L87, M87, N87) * IF(ISBLANK(K87), K$1,K87), "")) | L87: FALSE | N87: =IFERROR(VLOOKUP(I87, 'Price Sheet'!$A$2:$B1010, 2, false), "")
B88: =IF(ISBLANK(A88),"", IFERROR(IF(E88, F88, G88) * IF(ISBLANK(D88), C$1,D88), "")) | E88: FALSE | G88: =IFERROR(VLOOKUP(A88, 'Price Sheet'!$A$2:$B1010, 2, false), "") | J88: =IF(ISBLANK(I88),"", IFERROR(IF(L88, M88, N88) * IF(ISBLANK(K88), K$1,K88), "")) | L88: FALSE | N88: =IFERROR(VLOOKUP(I88, 'Price Sheet'!$A$2:$B1010, 2, false), "")
B89: =IF(ISBLANK(A89),"", IFERROR(IF(E89, F89, G89) * IF(ISBLANK(D89), C$1,D89), "")) | E89: FALSE | G89: =IFERROR(VLOOKUP(A89, 'Price Sheet'!$A$2:$B1010, 2, false), "") | J89: =IF(ISBLANK(I89),"", IFERROR(IF(L89, M89, N89) * IF(ISBLANK(K89), K$1,K89), "")) | L89: FALSE | N89: =IFERROR(VLOOKUP(I89, 'Price Sheet'!$A$2:$B1010, 2, false), "")
B90: =IF(ISBLANK(A90),"", IFERROR(IF(E90, F90, G90) * IF(ISBLANK(D90), C$1,D90), "")) | E90: FALSE | G90: =IFERROR(VLOOKUP(A90, 'Price Sheet'!$A$2:$B1010, 2, false), "") | J90: =IF(ISBLANK(I90),"", IFERROR(IF(L90, M90, N90) * IF(ISBLANK(K90), K$1,K90), "")) | L90: FALSE | N90: =IFERROR(VLOOKUP(I90, 'Price Sheet'!$A$2:$B1010, 2, false), "")
B91: =IF(ISBLANK(A91),"", IFERROR(IF(E91, F91, G91) * IF(ISBLANK(D91), C$1,D91), "")) | E91: FALSE | G91: =IFERROR(VLOOKUP(A91, 'Price Sheet'!$A$2:$B1010, 2, false), "") | J91: =IF(ISBLANK(I91),"", IFERROR(IF(L91, M91, N91) * IF(ISBLANK(K91), K$1,K91), "")) | L91: FALSE | N91: =IFERROR(VLOOKUP(I91, 'Price Sheet'!$A$2:$B1010, 2, false), "")
B92: =IF(ISBLANK(A92),"", IFERROR(IF(E92, F92, G92) * IF(ISBLANK(D92), C$1,D92), "")) | E92: FALSE | G92: =IFERROR(VLOOKUP(A92, 'Price Sheet'!$A$2:$B1010, 2, false), "") | J92: =IF(ISBLANK(I92),"", IFERROR(IF(L92, M92, N92) * IF(ISBLANK(K92), K$1,K92), "")) | L92: FALSE | N92: =IFERROR(VLOOKUP(I92, 'Price Sheet'!$A$2:$B1010, 2, false), "")
B93: =IF(ISBLANK(A93),"", IFERROR(IF(E93, F93, G93) * IF(ISBLANK(D93), C$1,D93), "")) | E93: FALSE | G93: =IFERROR(VLOOKUP(A93, 'Price Sheet'!$A$2:$B1010, 2, false), "") | J93: =IF(ISBLANK(I93),"", IFERROR(IF(L93, M93, N93) * IF(ISBLANK(K93), K$1,K93), "")) | L93: FALSE | N93: =IFERROR(VLOOKUP(I93, 'Price Sheet'!$A$2:$B1010, 2, false), "")
B94: =IF(ISBLANK(A94),"", IFERROR(IF(E94, F94, G94) * IF(ISBLANK(D94), C$1,D94), "")) | E94: FALSE | G94: =IFERROR(VLOOKUP(A94, 'Price Sheet'!$A$2:$B1010, 2, false), "") | J94: =IF(ISBLANK(I94),"", IFERROR(IF(L94, M94, N94) * IF(ISBLANK(K94), K$1,K94), "")) | L94: FALSE | N94: =IFERROR(VLOOKUP(I94, 'Price Sheet'!$A$2:$B1010, 2, false), "")
B95: =IF(ISBLANK(A95),"", IFERROR(IF(E95, F95, G95) * IF(ISBLANK(D95), C$1,D95), "")) | E95: FALSE | G95: =IFERROR(VLOOKUP(A95, 'Price Sheet'!$A$2:$B1010, 2, false), "") | J95: =IF(ISBLANK(I95),"", IFERROR(IF(L95, M95, N95) * IF(ISBLANK(K95), K$1,K95), "")) | L95: FALSE | N95: =IFERROR(VLOOKUP(I95, 'Price Sheet'!$A$2:$B1010, 2, false), "")
B96: =IF(ISBLANK(A96),"", IFERROR(IF(E96, F96, G96) * IF(ISBLANK(D96), C$1,D96), "")) | E96: FALSE | G96: =IFERROR(VLOOKUP(A96, 'Price Sheet'!$A$2:$B1010, 2, false), "") | J96: =IF(ISBLANK(I96),"", IFERROR(IF(L96, M96, N96) * IF(ISBLANK(K96), K$1,K96), "")) | L96: FALSE | N96: =IFERROR(VLOOKUP(I96, 'Price Sheet'!$A$2:$B1010, 2, false), "")
B97: =IF(ISBLANK(A97),"", IFERROR(IF(E97, F97, G97) * IF(ISBLANK(D97), C$1,D97), "")) | E97: FALSE | G97: =IFERROR(VLOOKUP(A97, 'Price Sheet'!$A$2:$B1010, 2, false), "") | J97: =IF(ISBLANK(I97),"", IFERROR(IF(L97, M97, N97) * IF(ISBLANK(K97), K$1,K97), "")) | L97: FALSE | N97: =IFERROR(VLOOKUP(I97, 'Price Sheet'!$A$2:$B1010, 2, false), "")
B98: =IF(ISBLANK(A98),"", IFERROR(IF(E98, F98, G98) * IF(ISBLANK(D98), C$1,D98), "")) | E98: FALSE | G98: =IFERROR(VLOOKUP(A98, 'Price Sheet'!$A$2:$B1010, 2, false), "") | J98: =IF(ISBLANK(I98),"", IFERROR(IF(L98, M98, N98) * IF(ISBLANK(K98), K$1,K98), "")) | L98: FALSE | N98: =IFERROR(VLOOKUP(I98, 'Price Sheet'!$A$2:$B1010, 2, false), "")
B99: =IF(ISBLANK(A99),"", IFERROR(IF(E99, F99, G99) * IF(ISBLANK(D99), C$1,D99), "")) | E99: FALSE | G99: =IFERROR(VLOOKUP(A99, 'Price Sheet'!$A$2:$B1010, 2, false), "") | J99: =IF(ISBLANK(I99),"", IFERROR(IF(L99, M99, N99) * IF(ISBLANK(K99), K$1,K99), "")) | L99: FALSE | N99: =IFERROR(VLOOKUP(I99, 'Price Sheet'!$A$2:$B1010, 2, false), "")
B100: =IF(ISBLANK(A100),"", IFERROR(IF(E100, F100, G100) * IF(ISBLANK(D100), C$1,D100), "")) | E100: FALSE | G100: =IFERROR(VLOOKUP(A100, 'Price Sheet'!$A$2:$B1010, 2, false), "") | J100: =IF(ISBLANK(I100),"", IFERROR(IF(L100, M100, N100) * IF(ISBLANK(K100), K$1,K100), "")) | L100: FALSE | N100: =IFERROR(VLOOKUP(I100, 'Price Sheet'!$A$2:$B1010, 2, false), "")
...

Sheet Recipes
L1: Product 1 | P1: Input 1 | V1: Input 2 | AB1: Input 3 | AH1: Input 4 | AN1: Input 5 | AT1: Input 6 | AZ1: Input 7 | BF1: Input 8 | BL1: Input 9
A2: Recipe Name | B2: Recipe Cost | C2: Skill | D2: Crafting Table | E2: Upgrade Used | F2: Input Multiplier | G2: Labor | H2: Cost from Calories | I2: Time | J2: Cost from time | K2: Active? | L2: Product | M2: Amount | N2: Cost Per | O2: unused | P2: Input Name | Q2: Input Amount | R2: Input Static | S2: Input Final Amount | T2: Input Per Ea. Cost | U2: Input Total Cost | V2: Input Name | W2: Input Amount | X2: Input Static | Y2: Input Final Amount | Z2: Input Per Ea. Cost | AA2: Input Total Cost | AB2: Input Name | AC2: Input Amount | AD2: Input Static | AE2: Input Final Amount | AF2: Input Per Ea. Cost | AG2: Input Total Cost | AH2: Input Name | AI2: Input Amount | AJ2: Input Static | AK2: Input Final Amount | AL2: Input Per Ea. Cost | AM2: Input Total Cost | AN2: Input Name | AO2: Input Amount | AP2: Input Static | AQ2: Input Final Amount | AR2: Input Per Ea. Cost | AS2: Input Total Cost | AT2: Input Name | AU2: Input Amount | AV2: Input Static | AW2: Input Final Amount | AX2: Input Per Ea. Cost | AY2: Input Total Cost | AZ2: Input Name | BA2: Input Amount | BB2: Input Static | BC2: Input Final Amount | BD2: Input Per Ea. Cost | BE2: Input Total Cost | BF2: Input Name | BG2: Input Amount | BH2: Input Static | BI2: Input Final Amount | BJ2: Input Per Ea. Cost | BK2: Input Total Cost | BL2: Input Name | BM2: Input Amount | BN2: Input Static | BO2: Input Final Amount | BP2: Input Per Ea. Cost | BQ2: Input Total Cost
A3: Dowel | B3: =H3+U3+AA3+AG3+AM3+AS3+AY3+BE3+BK3+J3+BQ3 -> 2.15 | C3: Logging | D3: Carpentry Table | E3: =IF(ISBLANK(D3), "", VLOOKUP(D3,'Crafting Tables'!$A$2:$B1015, 2, false)) -> Basic | F3: =IFERROR(IF(E3 = "None", 1, VLOOKUP(C3,General!$A$5:$L$35, SWITCH(E3, "Basic", 8, "Advanced", 10, "Modern", 12), false)),"") -> 0.55 | G3: 40 | H3: =IFERROR(VLOOKUP(C3, General!$A$5:$L$35, 6, false) * G3 / 1000, 0) -> 1.6 | I3: =0.4*60 -> 24 | J3: =IFERROR(I3*VLOOKUP(D3,'Crafting Tables'!$1:$1000, 4, false)*F3,"") -> 0 | K3: TRUE | L3: Dowel | M3: 16 | N3: =IF(ISBLANK(M3), "", $B3 / M3) -> 0.134375 | P3: Wood (Tag) | Q3: 2 | R3: FALSE | S3: =IF(ISBLANK(Q3), "", IF(R3, Q3, Q3*$F3 ) ) -> 1.1 | T3: =IF(ISBLANK(P3), 0, VLOOKUP(P3, 'Price Sheet'!$A$2:$B1015, 2, false)) -> 0.5 | U3: =IF(OR(ISBLANK(Q3), ISBLANK(T3)), "", T3*S3) -> 0.55 | X3: FALSE | Y3: =IF(ISBLANK(W3), "", IF(X3, W3, W3*$F3 ) ) | Z3: =IF(ISBLANK(V3), 0, VLOOKUP(V3, 'Price Sheet'!$A$2:$B1015, 2, false)) -> 0 | AA3: =IF(OR(ISBLANK(W3), ISBLANK(Z3)), "", Z3*Y3) | AD3: FALSE | AE3: =IF(ISBLANK(AC3), "", IF(AD3, AC3, AC3*$F3 ) ) | AF3: =IF(ISBLANK(AB3), 0, VLOOKUP(AB3, 'Price Sheet'!$A$2:$B1015, 2, false)) -> 0 | AG3: =IF(OR(ISBLANK(AC3), ISBLANK(AF3)), "", AF3*AE3) | AJ3: FALSE | AK3: =IF(ISBLANK(AI3), "", IF(AJ3, AI3, AI3*$F3 ) ) | AL3: =IF(ISBLANK(AH3), 0, VLOOKUP(AH3, 'Price Sheet'!$A$2:$B1015, 2, false)) -> 0 | AM3: =IF(OR(ISBLANK(AI3), ISBLANK(AL3)), "", AL3*AK3) | AP3: FALSE | AQ3: =IF(ISBLANK(AO3), "", IF(AP3, AO3, AO3*$F3 ) ) | AR3: =IF(ISBLANK(AN3), 0, VLOOKUP(AN3, 'Price Sheet'!$A$2:$B1015, 2, false)) -> 0 | AS3: =IF(OR(ISBLANK(AO3), ISBLANK(AR3)), "", AR3*AQ3) | AV3: FALSE | AW3: =IF(ISBLANK(AU3), "", IF(AV3, AU3, AU3*$F3 ) ) | AX3: =IF(ISBLANK(AT3), 0, VLOOKUP(AT3, 'Price Sheet'!$A$2:$B1015, 2, false)) -> 0 | AY3: =IF(OR(ISBLANK(AU3), ISBLANK(AX3)), "", AX3*AW3) | BB3: FALSE | BC3: =IF(ISBLANK(BA3), "", IF(BB3, BA3, BA3*$F3 ) ) | BD3: =IF(ISBLANK(AZ3), 0, VLOOKUP(AZ3, 'Price Sheet'!$A$2:$B1015, 2, false)) -> 0 | BE3: =IF(OR(ISBLANK(BA3), ISBLANK(BD3)), "", BD3*BC3) | BH3: FALSE | BI3: =IF(ISBLANK(BG3), "", IF(BH3, BG3, BG3*$F3 ) ) | BJ3: =IF(ISBLANK(BF3), 0, VLOOKUP(BF3, 'Price Sheet'!$A$2:$B1015, 2, false)) -> 0 | BK3: =IF(OR(ISBLANK(BG3), ISBLANK(BJ3)), "", BJ3*BI3) | BN3: FALSE | BO3: =IF(ISBLANK(BM3), "", IF(BN3, BM3, BM3*$F3 ) ) | BP3: =IF(ISBLANK(BL3), 0, VLOOKUP(BL3, 'Price Sheet'!$A$2:$B1015, 2, false)) -> 0 | BQ3: =IF(OR(ISBLANK(BM3), ISBLANK(BP3)), "", BP3*BO3)
A4: Hewn Log | B4: =H4+U4+AA4+AG4+AM4+AS4+AY4+BE4+BK4+J4+BQ4 -> 1.4978125 | C4: Logging | D4: Carpentry Table | E4: =IF(ISBLANK(D4), "", VLOOKUP(D4,'Crafting Tables'!$A$2:$B1015, 2, false)) -> Basic | F4: =IFERROR(IF(E4 = "None", 1, VLOOKUP(C4,General!$A$5:$L$35, SWITCH(E4, "Basic", 8, "Advanced", 10, "Modern", 12), false)),"") -> 0.55 | G4: 20 | H4: =IFERROR(VLOOKUP(C4, General!$A$5:$L$35, 6, false) * G4 / 1000, 0) -> 0.8 | J4: =IFERROR(I4*VLOOKUP(D4,'Crafting Tables'!$1:$1000, 4, false)*F4,"") -> 0 | K4: TRUE | L4: Hewn Log | M4: 1 | N4: =IF(ISBLANK(M4), "", $B4 / M4) -> 1.4978125 | P4: Wood (Tag) | Q4: 2 | R4: FALSE | S4: =IF(ISBLANK(Q4), "", IF(R4, Q4, Q4*$F4 ) ) -> 1.1 | T4: =IF(ISBLANK(P4), 0, VLOOKUP(P4, 'Price Sheet'!$A$2:$B1015, 2, false)) -> 0.5 | U4: =IF(OR(ISBLANK(Q4), ISBLANK(T4)), "", T4*S4) -> 0.55 | V4: Dowel | W4: 2 | X4: FALSE | Y4: =IF(ISBLANK(W4), "", IF(X4, W4, W4*$F4 ) ) -> 1.1 | Z4: =IF(ISBLANK(V4), 0, VLOOKUP(V4, 'Price Sheet'!$A$2:$B1015, 2, false)) -> 0.134375 | AA4: =IF(OR(ISBLANK(W4), ISBLANK(Z4)), "", Z4*Y4) -> 0.1478125 | AD4: FALSE | AE4: =IF(ISBLANK(AC4), "", IF(AD4, AC4, AC4*$F4 ) ) | AF4: =IF(ISBLANK(AB4), 0, VLOOKUP(AB4, 'Price Sheet'!$A$2:$B1015, 2, false)) -> 0 | AG4: =IF(OR(ISBLANK(AC4), ISBLANK(AF4)), "", AF4*AE4) | AJ4: FALSE | AK4: =IF(ISBLANK(AI4), "", IF(AJ4, AI4, AI4*$F4 ) ) | AL4: =IF(ISBLANK(AH4), 0, VLOOKUP(AH4, 'Price Sheet'!$A$2:$B1015, 2, false)) -> 0 | AM4: =IF(OR(ISBLANK(AI4), ISBLANK(AL4)), "", AL4*AK4) | AP4: FALSE | AQ4: =IF(ISBLANK(AO4), "", IF(AP4, AO4, AO4*$F4 ) ) | AR4: =IF(ISBLANK(AN4), 0, VLOOKUP(AN4, 'Price Sheet'!$A$2:$B1015, 2, false)) -> 0 | AS4: =IF(OR(ISBLANK(AO4), ISBLANK(AR4)), "", AR4*AQ4) | AV4: FALSE | AW4: =IF(ISBLANK(AU4), "", IF(AV4, AU4, AU4*$F4 ) ) | AX4: =IF(ISBLANK(AT4), 0, VLOOKUP(AT4, 'Price Sheet'!$A$2:$B1015, 2, false)) -> 0 | AY4: =IF(OR(ISBLANK(AU4), ISBLANK(AX4)), "", AX4*AW4) | BB4: FALSE | BC4: =IF(ISBLANK(BA4), "", IF(BB4, BA4, BA4*$F4 ) ) | BD4: =IF(ISBLANK(AZ4), 0, VLOOKUP(AZ4, 'Price Sheet'!$A$2:$B1015, 2, false)) -> 0 | BE4: =IF(OR(ISBLANK(BA4), ISBLANK(BD4)), "", BD4*BC4) | BH4: FALSE | BI4: =IF(ISBLANK(BG4), "", IF(BH4, BG4, BG4*$F4 ) ) | BJ4: =IF(ISBLANK(BF4), 0, VLOOKUP(BF4, 'Price Sheet'!$A$2:$B1015, 2, false)) -> 0 | BK4: =IF(OR(ISBLANK(BG4), ISBLANK(BJ4)), "", BJ4*BI4) | BN4: FALSE | BO4: =IF(ISBLANK(BM4), "", IF(BN4, BM4, BM4*$F4 ) ) | BP4: =IF(ISBLANK(BL4), 0, VLOOKUP(BL4, 'Price Sheet'!$A$2:$B1015, 2, false)) -> 0 | BQ4: =IF(OR(ISBLANK(BM4), ISBLANK(BP4)), "", BP4*BO4)
A5: Hewn (Workbench) | B5: =H5+U5+AA5+AG5+AM5+AS5+AY5+BE5+BK5+J5+BQ5 -> 1.8 | C5: None | D5: Workbench | E5: =IF(ISBLANK(D5), "", VLOOKUP(D5,'Crafting Tables'!$A$2:$B1015, 2, false)) -> None | F5: =IFERROR(IF(E5 = "None", 1, VLOOKUP(C5,General!$A$5:$L$35, SWITCH(E5, "Basic", 8, "Advanced", 10, "Modern", 12), false)),"") -> 1 | G5: 20 | H5: =IFERROR(VLOOKUP(C5, General!$A$5:$L$35, 6, false) * G5 / 1000, 0) -> 0.8 | J5: =IFERROR(I5*VLOOKUP(D5,'Crafting Tables'!$1:$1000, 4, false)*F5,"") -> 0 | K5: TRUE | L5: Hewn Log | M5: 1 | N5: =IF(ISBLANK(M5), "", $B5 / M5) -> 1.8 | P5: Wood (Tag) | Q5: 2 | R5: TRUE | S5: =IF(ISBLANK(Q5), "", IF(R5, Q5, Q5*$F5 ) ) -> 2 | T5: =IF(ISBLANK(P5), 0, VLOOKUP(P5, 'Price Sheet'!$A$2:$B1015, 2, false)) -> 0.5 | U5: =IF(OR(ISBLANK(Q5), ISBLANK(T5)), "", T5*S5) -> 1 | X5: FALSE | Y5: =IF(ISBLANK(W5), "", IF(X5, W5, W5*$F5 ) ) | Z5: =IF(ISBLANK(V5), 0, VLOOKUP(V5, 'Price Sheet'!$A$2:$B1015, 2, false)) -> 0 | AA5: =IF(OR(ISBLANK(W5), ISBLANK(Z5)), "", Z5*Y5) | AD5: FALSE | AE5: =IF(ISBLANK(AC5), "", IF(AD5, AC5, AC5*$F5 ) ) | AF5: =IF(ISBLANK(AB5), 0, VLOOKUP(AB5, 'Price Sheet'!$A$2:$B1015, 2, false)) -> 0 | AG5: =IF(OR(ISBLANK(AC5), ISBLANK(AF5)), "", AF5*AE5) | AJ5: FALSE | AK5: =IF(ISBLANK(AI5), "", IF(AJ5, AI5, AI5*$F5 ) ) | AL5: =IF(ISBLANK(AH5), 0, VLOOKUP(AH5, 'Price Sheet'!$A$2:$B1015, 2, false)) -> 0 | AM5: =IF(OR(ISBLANK(AI5), ISBLANK(AL5)), "", AL5*AK5) | AP5: FALSE | AQ5: =IF(ISBLANK(AO5), "", IF(AP5, AO5, AO5*$F5 ) ) | AR5: =IF(ISBLANK(AN5), 0, VLOOKUP(AN5, 'Price Sheet'!$A$2:$B1015, 2, false)) -> 0 | AS5: =IF(OR(ISBLANK(AO5), ISBLANK(AR5)), "", AR5*AQ5) | AV5: FALSE | AW5: =IF(ISBLANK(AU5), "", IF(AV5, AU5, AU5*$F5 ) ) | AX5: =IF(ISBLANK(AT5), 0, VLOOKUP(AT5, 'Price Sheet'!$A$2:$B1015, 2, false)) -> 0 | AY5: =IF(OR(ISBLANK(AU5), ISBLANK(AX5)), "", AX5*AW5) | BB5: FALSE | BC5: =IF(ISBLANK(BA5), "", IF(BB5, BA5, BA5*$F5 ) ) | BD5: =IF(ISBLANK(AZ5), 0, VLOOKUP(AZ5, 'Price Sheet'!$A$2:$B1015, 2, false)) -> 0 | BE5: =IF(OR(ISBLANK(BA5), ISBLANK(BD5)), "", BD5*BC5) | BH5: FALSE | BI5: =IF(ISBLANK(BG5), "", IF(BH5, BG5, BG5*$F5 ) ) | BJ5: =IF(ISBLANK(BF5), 0, VLOOKUP(BF5, 'Price Sheet'!$A$2:$B1015, 2, false)) -> 0 | BK5: =IF(OR(ISBLANK(BG5), ISBLANK(BJ5)), "", BJ5*BI5) | BN5: FALSE | BO5: =IF(ISBLANK(BM5), "", IF(BN5, BM5, BM5*$F5 ) ) | BP5: =IF(ISBLANK(BL5), 0, VLOOKUP(BL5, 'Price Sheet'!$A$2:$B1015, 2, false)) -> 0 | BQ5: =IF(OR(ISBLANK(BM5), ISBLANK(BP5)), "", BP5*BO5)
A6: Board (Workbench) | B6: =H6+U6+AA6+AG6+AM6+AS6+AY6+BE6+BK6+J6+BQ6 -> 2.6 | C6: None | D6: Workbench | E6: =IF(ISBLANK(D6), "", VLOOKUP(D6,'Crafting Tables'!$A$2:$B1015, 2, false)) -> None | F6: =IFERROR(IF(E6 = "None", 1, VLOOKUP(C6,General!$A$5:$L$35, SWITCH(E6, "Basic", 8, "Advanced", 10, "Modern", 12), false)),"") -> 1 | G6: 40 | H6: =IFERROR(VLOOKUP(C6, General!$A$5:$L$35, 6, false) * G6 / 1000, 0) -> 1.6 | J6: =IFERROR(I6*VLOOKUP(D6,'Crafting Tables'!$1:$1000, 4, false)*F6,"") -> 0 | K6: TRUE | L6: Board | M6: 1 | N6: =IF(ISBLANK(M6), "", $B6 / M6) -> 2.6 | P6: Wood (Tag) | Q6: 2 | R6: TRUE | S6: =IF(ISBLANK(Q6), "", IF(R6, Q6, Q6*$F6 ) ) -> 2 | T6: =IF(ISBLANK(P6), 0, VLOOKUP(P6, 'Price Sheet'!$A$2:$B1015, 2, false)) -> 0.5 | U6: =IF(OR(ISBLANK(Q6), ISBLANK(T6)), "", T6*S6) -> 1 | X6: FALSE | Y6: =IF(ISBLANK(W6), "", IF(X6, W6, W6*$F6 ) ) | Z6: =IF(ISBLANK(V6), 0, VLOOKUP(V6, 'Price Sheet'!$A$2:$B1015, 2, false)) -> 0 | AA6: =IF(OR(ISBLANK(W6), ISBLANK(Z6)), "", Z6*Y6) | AD6: FALSE | AE6: =IF(ISBLANK(AC6), "", IF(AD6, AC6, AC6*$F6 ) ) | AF6: =IF(ISBLANK(AB6), 0, VLOOKUP(AB6, 'Price Sheet'!$A$2:$B1015, 2, false)) -> 0 | AG6: =IF(OR(ISBLANK(AC6), ISBLANK(AF6)), "", AF6*AE6) | AJ6: FALSE | AK6: =IF(ISBLANK(AI6), "", IF(AJ6, AI6, AI6*$F6 ) ) | AL6: =IF(ISBLANK(AH6), 0, VLOOKUP(AH6, 'Price Sheet'!$A$2:$B1015, 2, false)) -> 0 | AM6: =IF(OR(ISBLANK(AI6), ISBLANK(AL6)), "", AL6*AK6) | AP6: FALSE | AQ6: =IF(ISBLANK(AO6), "", IF(AP6, AO6, AO6*$F6 ) ) | AR6: =IF(ISBLANK(AN6), 0, VLOOKUP(AN6, 'Price Sheet'!$A$2:$B1015, 2, false)) -> 0 | AS6: =IF(OR(ISBLANK(AO6), ISBLANK(AR6)), "", AR6*AQ6) | AV6: FALSE | AW6: =IF(ISBLANK(AU6), "", IF(AV6, AU6, AU6*$F6 ) ) | AX6: =IF(ISBLANK(AT6), 0, VLOOKUP(AT6, 'Price Sheet'!$A$2:$B1015, 2, false)) -> 0 | AY6: =IF(OR(ISBLANK(AU6), ISBLANK(AX6)), "", AX6*AW6) | BB6: FALSE | BC6: =IF(ISBLANK(BA6), "", IF(BB6, BA6, BA6*$F6 ) ) | BD6: =IF(ISBLANK(AZ6), 0, VLOOKUP(AZ6, 'Price Sheet'!$A$2:$B1015, 2, false)) -> 0 | BE6: =IF(OR(ISBLANK(BA6), ISBLANK(BD6)), "", BD6*BC6) | BH6: FALSE | BI6: =IF(ISBLANK(BG6), "", IF(BH6, BG6, BG6*$F6 ) ) | BJ6: =IF(ISBLANK(BF6), 0, VLOOKUP(BF6, 'Price Sheet'!$A$2:$B1015, 2, false)) -> 0 | BK6: =IF(OR(ISBLANK(BG6), ISBLANK(BJ6)), "", BJ6*BI6) | BN6: FALSE | BO6: =IF(ISBLANK(BM6), "", IF(BN6, BM6, BM6*$F6 ) ) | BP6: =IF(ISBLANK(BL6), 0, VLOOKUP(BL6, 'Price Sheet'!$A$2:$B1015, 2, false)) -> 0 | BQ6: =IF(OR(ISBLANK(BM6), ISBLANK(BP6)), "", BP6*BO6)
A7: Board (Carpentry Table) | B7: =H7+U7+AA7+AG7+AM7+AS7+AY7+BE7+BK7+J7+BQ7 -> 1.275 | C7: Logging | D7: Carpentry Table | E7: =IF(ISBLANK(D7), "", VLOOKUP(D7,'Crafting Tables'!$A$2:$B1015, 2, false)) -> Basic | F7: =IFERROR(IF(E7 = "None", 1, VLOOKUP(C7,General!$A$5:$L$35, SWITCH(E7, "Basic", 8, "Advanced", 10, "Modern", 12), false)),"") -> 0.55 | G7: 25 | H7: =IFERROR(VLOOKUP(C7, General!$A$5:$L$35, 6, false) * G7 / 1000, 0) -> 1 | J7: =IFERROR(I7*VLOOKUP(D7,'Crafting Tables'!$1:$1000, 4, false)*F7,"") -> 0 | K7: TRUE | L7: Board | M7: 1 | N7: =IF(ISBLANK(M7), "", $B7 / M7) -> 1.275 | P7: Wood (Tag) | Q7: 1 | R7: FALSE | S7: =IF(ISBLANK(Q7), "", IF(R7, Q7, Q7*$F7 ) ) -> 0.55 | T7: =IF(ISBLANK(P7), 0, VLOOKUP(P7, 'Price Sheet'!$A$2:$B1015, 2, false)) -> 0.5 | U7: =IF(OR(ISBLANK(Q7), ISBLANK(T7)), "", T7*S7) -> 0.275 | X7: FALSE | Y7: =IF(ISBLANK(W7), "", IF(X7, W7, W7*$F7 ) ) | Z7: =IF(ISBLANK(V7), 0, VLOOKUP(V7, 'Price Sheet'!$A$2:$B1015, 2, false)) -> 0 | AA7: =IF(OR(ISBLANK(W7), ISBLANK(Z7)), "", Z7*Y7) | AD7: FALSE | AE7: =IF(ISBLANK(AC7), "", IF(AD7, AC7, AC7*$F7 ) ) | AF7: =IF(ISBLANK(AB7), 0, VLOOKUP(AB7, 'Price Sheet'!$A$2:$B1015, 2, false)) -> 0 | AG7: =IF(OR(ISBLANK(AC7), ISBLANK(AF7)), "", AF7*AE7) | AJ7: FALSE | AK7: =IF(ISBLANK(AI7), "", IF(AJ7, AI7, AI7*$F7 ) ) | AL7: =IF(ISBLANK(AH7), 0, VLOOKUP(AH7, 'Price Sheet'!$A$2:$B1015, 2, false)) -> 0 | AM7: =IF(OR(ISBLANK(AI7), ISBLANK(AL7)), "", AL7*AK7) | AP7: FALSE | AQ7: =IF(ISBLANK(AO7), "", IF(AP7, AO7, AO7*$F7 ) ) | AR7: =IF(ISBLANK(AN7), 0, VLOOKUP(AN7, 'Price Sheet'!$A$2:$B1015, 2, false)) -> 0 | AS7: =IF(OR(ISBLANK(AO7), ISBLANK(AR7)), "", AR7*AQ7) | AV7: FALSE | AW7: =IF(ISBLANK(AU7), "", IF(AV7, AU7, AU7*$F7 ) ) | AX7: =IF(ISBLANK(AT7), 0, VLOOKUP(AT7, 'Price Sheet'!$A$2:$B1015, 2, false)) -> 0 | AY7: =IF(OR(ISBLANK(AU7), ISBLANK(AX7)), "", AX7*AW7) | BB7: FALSE | BC7: =IF(ISBLANK(BA7), "", IF(BB7, BA7, BA7*$F7 ) ) | BD7: =IF(ISBLANK(AZ7), 0, VLOOKUP(AZ7, 'Price Sheet'!$A$2:$B1015, 2, false)) -> 0 | BE7: =IF(OR(ISBLANK(BA7), ISBLANK(BD7)), "", BD7*BC7) | BH7: FALSE | BI7: =IF(ISBLANK(BG7), "", IF(BH7, BG7, BG7*$F7 ) ) | BJ7: =IF(ISBLANK(BF7), 0, VLOOKUP(BF7, 'Price Sheet'!$A$2:$B1015, 2, false)) -> 0 | BK7: =IF(OR(ISBLANK(BG7), ISBLANK(BJ7)), "", BJ7*BI7) | BN7: FALSE | BO7: =IF(ISBLANK(BM7), "", IF(BN7, BM7, BM7*$F7 ) ) | BP7: =IF(ISBLANK(BL7), 0, VLOOKUP(BL7, 'Price Sheet'!$A$2:$B1015, 2, false)) -> 0 | BQ7: =IF(OR(ISBLANK(BM7), ISBLANK(BP7)), "", BP7*BO7)
A8: Particle Boards | B8: =H8+U8+AA8+AG8+AM8+AS8+AY8+BE8+BK8+J8+BQ8 -> 1.05 | C8: Logging | D8: Sawmill | E8: =IF(ISBLANK(D8), "", VLOOKUP(D8,'Crafting Tables'!$A$2:$B1015, 2, false)) -> Advanced | F8: =IFERROR(IF(E8 = "None", 1, VLOOKUP(C8,General!$A$5:$L$35, SWITCH(E8, "Basic", 8, "Advanced", 10, "Modern", 12), false)),"") -> 1 | G8: 20 | H8: =IFERROR(VLOOKUP(C8, General!$A$5:$L$35, 6, false) * G8 / 1000, 0) -> 0.8 | J8: =IFERROR(I8*VLOOKUP(D8,'Crafting Tables'!$1:$1000, 4, false)*F8,"") -> 0 | K8: FALSE | L8: Board | M8: 1 | N8: =IF(ISBLANK(M8), "", $B8 / M8) -> 1.05 | P8: Wood Pulp | Q8: 5 | R8: FALSE | S8: =IF(ISBLANK(Q8), "", IF(R8, Q8, Q8*$F8 ) ) -> 5 | T8: =IF(ISBLANK(P8), 0, VLOOKUP(P8, 'Price Sheet'!$A$2:$B1015, 2, false)) -> 0.05 | U8: =IF(OR(ISBLANK(Q8), ISBLANK(T8)), "", T8*S8) -> 0.25 | X8: FALSE | Y8: =IF(ISBLANK(W8), "", IF(X8, W8, W8*$F8 ) ) | Z8: =IF(ISBLANK(V8), 0, VLOOKUP(V8, 'Price Sheet'!$A$2:$B1015, 2, false)) -> 0 | AA8: =IF(OR(ISBLANK(W8), ISBLANK(Z8)), "", Z8*Y8) | AD8: FALSE | AE8: =IF(ISBLANK(AC8), "", IF(AD8, AC8, AC8*$F8 ) ) | AF8: =IF(ISBLANK(AB8), 0, VLOOKUP(AB8, 'Price Sheet'!$A$2:$B1015, 2, false)) -> 0 | AG8: =IF(OR(ISBLANK(AC8), ISBLANK(AF8)), "", AF8*AE8) | AJ8: FALSE | AK8: =IF(ISBLANK(AI8), "", IF(AJ8, AI8, AI8*$F8 ) ) | AL8: =IF(ISBLANK(AH8), 0, VLOOKUP(AH8, 'Price Sheet'!$A$2:$B1015, 2, false)) -> 0 | AM8: =IF(OR(ISBLANK(AI8), ISBLANK(AL8)), "", AL8*AK8) | AP8: FALSE | AQ8: =IF(ISBLANK(AO8), "", IF(AP8, AO8, AO8*$F8 ) ) | AR8: =IF(ISBLANK(AN8), 0, VLOOKUP(AN8, 'Price Sheet'!$A$2:$B1015, 2, false)) -> 0 | AS8: =IF(OR(ISBLANK(AO8), ISBLANK(AR8)), "", AR8*AQ8) | AV8: FALSE | AW8: =IF(ISBLANK(AU8), "", IF(AV8, AU8, AU8*$F8 ) ) | AX8: =IF(ISBLANK(AT8), 0, VLOOKUP(AT8, 'Price Sheet'!$A$2:$B1015, 2, false)) -> 0 | AY8: =IF(OR(ISBLANK(AU8), ISBLANK(AX8)), "", AX8*AW8) | BB8: FALSE | BC8: =IF(ISBLANK(BA8), "", IF(BB8, BA8, BA8*$F8 ) ) | BD8: =IF(ISBLANK(AZ8), 0, VLOOKUP(AZ8, 'Price Sheet'!$A$2:$B1015, 2, false)) -> 0 | BE8: =IF(OR(ISBLANK(BA8), ISBLANK(BD8)), "", BD8*BC8) | BH8: FALSE | BI8: =IF(ISBLANK(BG8), "", IF(BH8, BG8, BG8*$F8 ) ) | BJ8: =IF(ISBLANK(BF8), 0, VLOOKUP(BF8, 'Price Sheet'!$A$2:$B1015, 2, false)) -> 0 | BK8: =IF(OR(ISBLANK(BG8), ISBLANK(BJ8)), "", BJ8*BI8) | BN8: FALSE | BO8: =IF(ISBLANK(BM8), "", IF(BN8, BM8, BM8*$F8 ) ) | BP8: =IF(ISBLANK(BL8), 0, VLOOKUP(BL8, 'Price Sheet'!$A$2:$B1015, 2, false)) -> 0 | BQ8: =IF(OR(ISBLANK(BM8), ISBLANK(BP8)), "", BP8*BO8)
A9: Saw Boards | B9: =H9+U9+AA9+AG9+AM9+AS9+AY9+BE9+BK9+J9+BQ9 -> 1.8 | C9: Logging | D9: Sawmill | E9: =IF(ISBLANK(D9), "", VLOOKUP(D9,'Crafting Tables'!$A$2:$B1015, 2, false)) -> Advanced | F9: =IFERROR(IF(E9 = "None", 1, VLOOKUP(C9,General!$A$5:$L$35, SWITCH(E9, "Basic", 8, "Advanced", 10, "Modern", 12), false)),"") -> 1 | G9: 20 | H9: =IFERROR(VLOOKUP(C9, General!$A$5:$L$35, 6, false) * G9 / 1000, 0) -> 0.8 | J9: =IFERROR(I9*VLOOKUP(D9,'Crafting Tables'!$1:$1000, 4, false)*F9,"") -> 0 | K9: TRUE | L9: Board | M9: 3 | N9: =IF(ISBLANK(M9), "", $B9 / M9) -> 0.6 | P9: Wood (Tag) | Q9: 2 | R9: FALSE | S9: =IF(ISBLANK(Q9), "", IF(R9, Q9, Q9*$F9 ) ) -> 2 | T9: =IF(ISBLANK(P9), 0, VLOOKUP(P9, 'Price Sheet'!$A$2:$B1015, 2, false)) -> 0.5 | U9: =IF(OR(ISBLANK(Q9), ISBLANK(T9)), "", T9*S9) -> 1 | X9: FALSE | Y9: =IF(ISBLANK(W9), "", IF(X9, W9, W9*$F9 ) ) | Z9: =IF(ISBLANK(V9), 0, VLOOKUP(V9, 'Price Sheet'!$A$2:$B1015, 2, false)) -> 0 | AA9: =IF(OR(ISBLANK(W9), ISBLANK(Z9)), "", Z9*Y9) | AD9: FALSE | AE9: =IF(ISBLANK(AC9), "", IF(AD9, AC9, AC9*$F9 ) ) | AF9: =IF(ISBLANK(AB9), 0, VLOOKUP(AB9, 'Price Sheet'!$A$2:$B1015, 2, false)) -> 0 | AG9: =IF(OR(ISBLANK(AC9), ISBLANK(AF9)), "", AF9*AE9) | AJ9: FALSE | AK9: =IF(ISBLANK(AI9), "", IF(AJ9, AI9, AI9*$F9 ) ) | AL9: =IF(ISBLANK(AH9), 0, VLOOKUP(AH9, 'Price Sheet'!$A$2:$B1015, 2, false)) -> 0 | AM9: =IF(OR(ISBLANK(AI9), ISBLANK(AL9)), "", AL9*AK9) | AP9: FALSE | AQ9: =IF(ISBLANK(AO9), "", IF(AP9, AO9, AO9*$F9 ) ) | AR9: =IF(ISBLANK(AN9), 0, VLOOKUP(AN9, 'Price Sheet'!$A$2:$B1015, 2, false)) -> 0 | AS9: =IF(OR(ISBLANK(AO9), ISBLANK(AR9)), "", AR9*AQ9) | AV9: FALSE | AW9: =IF(ISBLANK(AU9), "", IF(AV9, AU9, AU9*$F9 ) ) | AX9: =IF(ISBLANK(AT9), 0, VLOOKUP(AT9, 'Price Sheet'!$A$2:$B1015, 2, false)) -> 0 | AY9: =IF(OR(ISBLANK(AU9), ISBLANK(AX9)), "", AX9*AW9) | BB9: FALSE | BC9: =IF(ISBLANK(BA9), "", IF(BB9, BA9, BA9*$F9 ) ) | BD9: =IF(ISBLANK(AZ9), 0, VLOOKUP(AZ9, 'Price Sheet'!$A$2:$B1015, 2, false)) -> 0 | BE9: =IF(OR(ISBLANK(BA9), ISBLANK(BD9)), "", BD9*BC9) | BH9: FALSE | BI9: =IF(ISBLANK(BG9), "", IF(BH9, BG9, BG9*$F9 ) ) | BJ9: =IF(ISBLANK(BF9), 0, VLOOKUP(BF9, 'Price Sheet'!$A$2:$B1015, 2, false)) -> 0 | BK9: =IF(OR(ISBLANK(BG9), ISBLANK(BJ9)), "", BJ9*BI9) | BN9: FALSE | BO9: =IF(ISBLANK(BM9), "", IF(BN9, BM9, BM9*$F9 ) ) | BP9: =IF(ISBLANK(BL9), 0, VLOOKUP(BL9, 'Price Sheet'!$A$2:$B1015, 2, false)) -> 0 | BQ9: =IF(OR(ISBLANK(BM9), ISBLANK(BP9)), "", BP9*BO9)
A10: Butchery Table | B10: =H10+U10+AA10+AG10+AM10+AS10+AY10+BE10+BK10+J10+BQ10 -> 21.35 | C10: Logging | D10: Carpentry Table | E10: =IF(ISBLANK(D10), "", VLOOKUP(D10,'Crafting Tables'!$A$2:$B1015, 2, false)) -> Basic | F10: =IFERROR(IF(E10 = "None", 1, VLOOKUP(C10,General!$A$5:$L$35, SWITCH(E10, "Basic", 8, "Advanced", 10, "Modern", 12), false)),"") -> 0.55 | G10: 300 | H10: =IFERROR(VLOOKUP(C10, General!$A$5:$L$35, 6, false) * G10 / 1000, 0) -> 12 | J10: =IFERROR(I10*VLOOKUP(D10,'Crafting Tables'!$1:$1000, 4, false)*F10,"") -> 0 | K10: TRUE | L10: Butchery Table | M10: 1 | N10: =IF(ISBLANK(M10), "", $B10 / M10) -> 21.35 | P10: Hewn Log | Q10: 10 | R10: FALSE | S10: =IF(ISBLANK(Q10), "", IF(R10, Q10, Q10*$F10 ) ) -> 5.5 | T10: =IF(ISBLANK(P10), 0, VLOOKUP(P10, 'Price Sheet'!$A$2:$B1015, 2, false)) -> 0.8 | U10: =IF(OR(ISBLANK(Q10), ISBLANK(T10)), "", T10*S10) -> 4.4 | V10: Board | W10: 20 | X10: FALSE | Y10: =IF(ISBLANK(W10), "", IF(X10, W10, W10*$F10 ) ) -> 11 | Z10: =IF(ISBLANK(V10), 0, VLOOKUP(V10, 'Price Sheet'!$A$2:$B1015, 2, false)) -> 0.45 | AA10: =IF(OR(ISBLANK(W10), ISBLANK(Z10)), "", Z10*Y10) -> 4.95 | AD10: FALSE | AE10: =IF(ISBLANK(AC10), "", IF(AD10, AC10, AC10*$F10 ) ) | AF10: =IF(ISBLANK(AB10), 0, VLOOKUP(AB10, 'Price Sheet'!$A$2:$B1015, 2, false)) -> 0 | AG10: =IF(OR(ISBLANK(AC10), ISBLANK(AF10)), "", AF10*AE10) | AJ10: FALSE | AK10: =IF(ISBLANK(AI10), "", IF(AJ10, AI10, AI10*$F10 ) ) | AL10: =IF(ISBLANK(AH10), 0, VLOOKUP(AH10, 'Price Sheet'!$A$2:$B1015, 2, false)) -> 0 | AM10: =IF(OR(ISBLANK(AI10), ISBLANK(AL10)), "", AL10*AK10) | AP10: FALSE | AQ10: =IF(ISBLANK(AO10), "", IF(AP10, AO10, AO10*$F10 ) ) | AR10: =IF(ISBLANK(AN10), 0, VLOOKUP(AN10, 'Price Sheet'!$A$2:$B1015, 2, false)) -> 0 | AS10: =IF(OR(ISBLANK(AO10), ISBLANK(AR10)), "", AR10*AQ10) | AV10: FALSE | AW10: =IF(ISBLANK(AU10), "", IF(AV10, AU10, AU10*$F10 ) ) | AX10: =IF(ISBLANK(AT10), 0, VLOOKUP(AT10, 'Price Sheet'!$A$2:$B1015, 2, false)) -> 0 | AY10: =IF(OR(ISBLANK(AU10), ISBLANK(AX10)), "", AX10*AW10) | BB10: FALSE | BC10: =IF(ISBLANK(BA10), "", IF(BB10, BA10, BA10*$F10 ) ) | BD10: =IF(ISBLANK(AZ10), 0, VLOOKUP(AZ10, 'Price Sheet'!$A$2:$B1015, 2, false)) -> 0 | BE10: =IF(OR(ISBLANK(BA10), ISBLANK(BD10)), "", BD10*BC10) | BH10: FALSE | BI10: =IF(ISBLANK(BG10), "", IF(BH10, BG10, BG10*$F10 ) ) | BJ10: =IF(ISBLANK(BF10), 0, VLOOKUP(BF10, 'Price Sheet'!$A$2:$B1015, 2, false)) -> 0 | BK10: =IF(OR(ISBLANK(BG10), ISBLANK(BJ10)), "", BJ10*BI10) | BN10: FALSE | BO10: =IF(ISBLANK(BM10), "", IF(BN10, BM10, BM10*$F10 ) ) | BP10: =IF(ISBLANK(BL10), 0, VLOOKUP(BL10, 'Price Sheet'!$A$2:$B1015, 2, false)) -> 0 | BQ10: =IF(OR(ISBLANK(BM10), ISBLANK(BP10)), "", BP10*BO10)
A11: Fiber Scutching Station | B11: =H11+U11+AA11+AG11+AM11+AS11+AY11+BE11+BK11+J11+BQ11 -> 21.35 | C11: Logging | D11: Carpentry Table | E11: =IF(ISBLANK(D11), "", VLOOKUP(D11,'Crafting Tables'!$A$2:$B1015, 2, false)) -> Basic | F11: =IFERROR(IF(E11 = "None", 1, VLOOKUP(C11,General!$A$5:$L$35, SWITCH(E11, "Basic", 8, "Advanced", 10, "Modern", 12), false)),"") -> 0.55 | G11: 300 | H11: =IFERROR(VLOOKUP(C11, General!$A$5:$L$35, 6, false) * G11 / 1000, 0) -> 12 | J11: =IFERROR(I11*VLOOKUP(D11,'Crafting Tables'!$1:$1000, 4, false)*F11,"") -> 0 | K11: TRUE | L11: Fiber Scutching Station | M11: 1 | N11: =IF(ISBLANK(M11), "", $B11 / M11) -> 21.35 | P11: Hewn Log | Q11: 10 | R11: FALSE | S11: =IF(ISBLANK(Q11), "", IF(R11, Q11, Q11*$F11 ) ) -> 5.5 | T11: =IF(ISBLANK(P11), 0, VLOOKUP(P11, 'Price Sheet'!$A$2:$B1015, 2, false)) -> 0.8 | U11: =IF(OR(ISBLANK(Q11), ISBLANK(T11)), "", T11*S11) -> 4.4 | V11: Board | W11: 20 | X11: FALSE | Y11: =IF(ISBLANK(W11), "", IF(X11, W11, W11*$F11 ) ) -> 11 | Z11: =IF(ISBLANK(V11), 0, VLOOKUP(V11, 'Price Sheet'!$A$2:$B1015, 2, false)) -> 0.45 | AA11: =IF(OR(ISBLANK(W11), ISBLANK(Z11)), "", Z11*Y11) -> 4.95 | AD11: FALSE | AE11: =IF(ISBLANK(AC11), "", IF(AD11, AC11, AC11*$F11 ) ) | AF11: =IF(ISBLANK(AB11), 0, VLOOKUP(AB11, 'Price Sheet'!$A$2:$B1015, 2, false)) -> 0 | AG11: =IF(OR(ISBLANK(AC11), ISBLANK(AF11)), "", AF11*AE11) | AJ11: FALSE | AK11: =IF(ISBLANK(AI11), "", IF(AJ11, AI11, AI11*$F11 ) ) | AL11: =IF(ISBLANK(AH11), 0, VLOOKUP(AH11, 'Price Sheet'!$A$2:$B1015, 2, false)) -> 0 | AM11: =IF(OR(ISBLANK(AI11), ISBLANK(AL11)), "", AL11*AK11) | AP11: FALSE | AQ11: =IF(ISBLANK(AO11), "", IF(AP11, AO11, AO11*$F11 ) ) | AR11: =IF(ISBLANK(AN11), 0, VLOOKUP(AN11, 'Price Sheet'!$A$2:$B1015, 2, false)) -> 0 | AS11: =IF(OR(ISBLANK(AO11), ISBLANK(AR11)), "", AR11*AQ11) | AV11: FALSE | AW11: =IF(ISBLANK(AU11), "", IF(AV11, AU11, AU11*$F11 ) ) | AX11: =IF(ISBLANK(AT11), 0, VLOOKUP(AT11, 'Price Sheet'!$A$2:$B1015, 2, false)) -> 0 | AY11: =IF(OR(ISBLANK(AU11), ISBLANK(AX11)), "", AX11*AW11) | BB11: FALSE | BC11: =IF(ISBLANK(BA11), "", IF(BB11, BA11, BA11*$F11 ) ) | BD11: =IF(ISBLANK(AZ11), 0, VLOOKUP(AZ11, 'Price Sheet'!$A$2:$B1015, 2, false)) -> 0 | BE11: =IF(OR(ISBLANK(BA11), ISBLANK(BD11)), "", BD11*BC11) | BH11: FALSE | BI11: =IF(ISBLANK(BG11), "", IF(BH11, BG11, BG11*$F11 ) ) | BJ11: =IF(ISBLANK(BF11), 0, VLOOKUP(BF11, 'Price Sheet'!$A$2:$B1015, 2, false)) -> 0 | BK11: =IF(OR(ISBLANK(BG11), ISBLANK(BJ11)), "", BJ11*BI11) | BN11: FALSE | BO11: =IF(ISBLANK(BM11), "", IF(BN11, BM11, BM11*$F11 ) ) | BP11: =IF(ISBLANK(BL11), 0, VLOOKUP(BL11, 'Price Sheet'!$A$2:$B1015, 2, false)) -> 0 | BQ11: =IF(OR(ISBLANK(BM11), ISBLANK(BP11)), "", BP11*BO11)
A12: Hewn Bench | B12: =H12+U12+AA12+AG12+AM12+AS12+AY12+BE12+BK12+J12+BQ12 -> 11.805 | C12: Logging | D12: Carpentry Table | E12: =IF(ISBLANK(D12), "", VLOOKUP(D12,'Crafting Tables'!$A$2:$B1015, 2, false)) -> Basic | F12: =IFERROR(IF(E12 = "None", 1, VLOOKUP(C12,General!$A$5:$L$35, SWITCH(E12, "Basic", 8, "Advanced", 10, "Modern", 12), false)),"") -> 0.55 | G12: 60 | H12: =IFERROR(VLOOKUP(C12, General!$A$5:$L$35, 6, false) * G12 / 1000, 0) -> 2.4 | J12: =IFERROR(I12*VLOOKUP(D12,'Crafting Tables'!$1:$1000, 4, false)*F12,"") -> 0 | K12: TRUE | L12: Hewn Bench | M12: 1 | N12: =IF(ISBLANK(M12), "", $B12 / M12) -> 11.805 | P12: Hewn Log | Q12: 18 | R12: FALSE | S12: =IF(ISBLANK(Q12), "", IF(R12, Q12, Q12*$F12 ) ) -> 9.9 | T12: =IF(ISBLANK(P12), 0, VLOOKUP(P12, 'Price Sheet'!$A$2:$B1015, 2, false)) -> 0.8 | U12: =IF(OR(ISBLANK(Q12), ISBLANK(T12)), "", T12*S12) -> 7.92 | V12: Board | W12: 6 | X12: FALSE | Y12: =IF(ISBLANK(W12), "", IF(X12, W12, W12*$F12 ) ) -> 3.3 | Z12: =IF(ISBLANK(V12), 0, VLOOKUP(V12, 'Price Sheet'!$A$2:$B1015, 2, false)) -> 0.45 | AA12: =IF(OR(ISBLANK(W12), ISBLANK(Z12)), "", Z12*Y12) -> 1.485 | AD12: FALSE | AE12: =IF(ISBLANK(AC12), "", IF(AD12, AC12, AC12*$F12 ) ) | AF12: =IF(ISBLANK(AB12), 0, VLOOKUP(AB12, 'Price Sheet'!$A$2:$B1015, 2, false)) -> 0 | AG12: =IF(OR(ISBLANK(AC12), ISBLANK(AF12)), "", AF12*AE12) | AJ12: FALSE | AK12: =IF(ISBLANK(AI12), "", IF(AJ12, AI12, AI12*$F12 ) ) | AL12: =IF(ISBLANK(AH12), 0, VLOOKUP(AH12, 'Price Sheet'!$A$2:$B1015, 2, false)) -> 0 | AM12: =IF(OR(ISBLANK(AI12), ISBLANK(AL12)), "", AL12*AK12) | AP12: FALSE | AQ12: =IF(ISBLANK(AO12), "", IF(AP12, AO12, AO12*$F12 ) ) | AR12: =IF(ISBLANK(AN12), 0, VLOOKUP(AN12, 'Price Sheet'!$A$2:$B1015, 2, false)) -> 0 | AS12: =IF(OR(ISBLANK(AO12), ISBLANK(AR12)), "", AR12*AQ12) | AV12: FALSE | AW12: =IF(ISBLANK(AU12), "", IF(AV12, AU12, AU12*$F12 ) ) | AX12: =IF(ISBLANK(AT12), 0, VLOOKUP(AT12, 'Price Sheet'!$A$2:$B1015, 2, false)) -> 0 | AY12: =IF(OR(ISBLANK(AU12), ISBLANK(AX12)), "", AX12*AW12) | BB12: FALSE | BC12: =IF(ISBLANK(BA12), "", IF(BB12, BA12, BA12*$F12 ) ) | BD12: =IF(ISBLANK(AZ12), 0, VLOOKUP(AZ12, 'Price Sheet'!$A$2:$B1015, 2, false)) -> 0 | BE12: =IF(OR(ISBLANK(BA12), ISBLANK(BD12)), "", BD12*BC12) | BH12: FALSE | BI12: =IF(ISBLANK(BG12), "", IF(BH12, BG12, BG12*$F12 ) ) | BJ12: =IF(ISBLANK(BF12), 0, VLOOKUP(BF12, 'Price Sheet'!$A$2:$B1015, 2, false)) -> 0 | BK12: =IF(OR(ISBLANK(BG12), ISBLANK(BJ12)), "", BJ12*BI12) | BN12: FALSE | BO12: =IF(ISBLANK(BM12), "", IF(BN12, BM12, BM12*$F12 ) ) | BP12: =IF(ISBLANK(BL12), 0, VLOOKUP(BL12, 'Price Sheet'!$A$2:$B1015, 2, false)) -> 0 | BQ12: =IF(OR(ISBLANK(BM12), ISBLANK(BP12)), "", BP12*BO12)
A13: Hewn Chair | B13: =H13+U13+AA13+AG13+AM13+AS13+AY13+BE13+BK13+J13+BQ13 -> 10.65 | C13: Logging | D13: Carpentry Table | E13: =IF(ISBLANK(D13), "", VLOOKUP(D13,'Crafting Tables'!$A$2:$B1015, 2, false)) -> Basic | F13: =IFERROR(IF(E13 = "None", 1, VLOOKUP(C13,General!$A$5:$L$35, SWITCH(E13, "Basic", 8, "Advanced", 10, "Modern", 12), false)),"") -> 0.55 | G13: 60 | H13: =IFERROR(VLOOKUP(C13, General!$A$5:$L$35, 6, false) * G13 / 1000, 0) -> 2.4 | J13: =IFERROR(I13*VLOOKUP(D13,'Crafting Tables'!$1:$1000, 4, false)*F13,"") -> 0 | K13: TRUE | L13: Hewn Chair | M13: 1 | N13: =IF(ISBLANK(M13), "", $B13 / M13) -> 10.65 | P13: Hewn Log | Q13: 12 | R13: FALSE | S13: =IF(ISBLANK(Q13), "", IF(R13, Q13, Q13*$F13 ) ) -> 6.6 | T13: =IF(ISBLANK(P13), 0, VLOOKUP(P13, 'Price Sheet'!$A$2:$B1015, 2, false)) -> 0.8 | U13: =IF(OR(ISBLANK(Q13), ISBLANK(T13)), "", T13*S13) -> 5.28 | V13: Board | W13: 12 | X13: FALSE | Y13: =IF(ISBLANK(W13), "", IF(X13, W13, W13*$F13 ) ) -> 6.6 | Z13: =IF(ISBLANK(V13), 0, VLOOKUP(V13, 'Price Sheet'!$A$2:$B1015, 2, false)) -> 0.45 | AA13: =IF(OR(ISBLANK(W13), ISBLANK(Z13)), "", Z13*Y13) -> 2.97 | AD13: FALSE | AE13: =IF(ISBLANK(AC13), "", IF(AD13, AC13, AC13*$F13 ) ) | AF13: =IF(ISBLANK(AB13), 0, VLOOKUP(AB13, 'Price Sheet'!$A$2:$B1015, 2, false)) -> 0 | AG13: =IF(OR(ISBLANK(AC13), ISBLANK(AF13)), "", AF13*AE13) | AJ13: FALSE | AK13: =IF(ISBLANK(AI13), "", IF(AJ13, AI13, AI13*$F13 ) ) | AL13: =IF(ISBLANK(AH13), 0, VLOOKUP(AH13, 'Price Sheet'!$A$2:$B1015, 2, false)) -> 0 | AM13: =IF(OR(ISBLANK(AI13), ISBLANK(AL13)), "", AL13*AK13) | AP13: FALSE | AQ13: =IF(ISBLANK(AO13), "", IF(AP13, AO13, AO13*$F13 ) ) | AR13: =IF(ISBLANK(AN13), 0, VLOOKUP(AN13, 'Price Sheet'!$A$2:$B1015, 2, false)) -> 0 | AS13: =IF(OR(ISBLANK(AO13), ISBLANK(AR13)), "", AR13*AQ13) | AV13: FALSE | AW13: =IF(ISBLANK(AU13), "", IF(AV13, AU13, AU13*$F13 ) ) | AX13: =IF(ISBLANK(AT13), 0, VLOOKUP(AT13, 'Price Sheet'!$A$2:$B1015, 2, false)) -> 0 | AY13: =IF(OR(ISBLANK(AU13), ISBLANK(AX13)), "", AX13*AW13) | BB13: FALSE | BC13: =IF(ISBLANK(BA13), "", IF(BB13, BA13, BA13*$F13 ) ) | BD13: =IF(ISBLANK(AZ13), 0, VLOOKUP(AZ13, 'Price Sheet'!$A$2:$B1015, 2, false)) -> 0 | BE13: =IF(OR(ISBLANK(BA13), ISBLANK(BD13)), "", BD13*BC13) | BH13: FALSE | BI13: =IF(ISBLANK(BG13), "", IF(BH13, BG13, BG13*$F13 ) ) | BJ13: =IF(ISBLANK(BF13), 0, VLOOKUP(BF13, 'Price Sheet'!$A$2:$B1015, 2, false)) -> 0 | BK13: =IF(OR(ISBLANK(BG13), ISBLANK(BJ13)), "", BJ13*BI13) | BN13: FALSE | BO13: =IF(ISBLANK(BM13), "", IF(BN13, BM13, BM13*$F13 ) ) | BP13: =IF(ISBLANK(BL13), 0, VLOOKUP(BL13, 'Price Sheet'!$A$2:$B1015, 2, false)) -> 0 | BQ13: =IF(OR(ISBLANK(BM13), ISBLANK(BP13)), "", BP13*BO13)
A14: Hewn Door | B14: =H14+U14+AA14+AG14+AM14+AS14+AY14+BE14+BK14+J14+BQ14 -> 3.28 | C14: Logging | D14: Carpentry Table | E14: =IF(ISBLANK(D14), "", VLOOKUP(D14,'Crafting Tables'!$A$2:$B1015, 2, false)) -> Basic | F14: =IFERROR(IF(E14 = "None", 1, VLOOKUP(C14,General!$A$5:$L$35, SWITCH(E14, "Basic", 8, "Advanced", 10, "Modern", 12), false)),"") -> 0.55 | G14: 60 | H14: =IFERROR(VLOOKUP(C14, General!$A$5:$L$35, 6, false) * G14 / 1000, 0) -> 2.4 | J14: =IFERROR(I14*VLOOKUP(D14,'Crafting Tables'!$1:$1000, 4, false)*F14,"") -> 0 | K14: TRUE | L14: Hewn Door | M14: 1 | N14: =IF(ISBLANK(M14), "", $B14 / M14) -> 3.28 | P14: Hewn Log | Q14: 2 | R14: FALSE | S14: =IF(ISBLANK(Q14), "", IF(R14, Q14, Q14*$F14 ) ) -> 1.1 | T14: =IF(ISBLANK(P14), 0, VLOOKUP(P14, 'Price Sheet'!$A$2:$B1015, 2, false)) -> 0.8 | U14: =IF(OR(ISBLANK(Q14), ISBLANK(T14)), "", T14*S14) -> 0.88 | X14: FALSE | Y14: =IF(ISBLANK(W14), "", IF(X14, W14, W14*$F14 ) ) | Z14: =IF(ISBLANK(V14), 0, VLOOKUP(V14, 'Price Sheet'!$A$2:$B1015, 2, false)) -> 0 | AA14: =IF(OR(ISBLANK(W14), ISBLANK(Z14)), "", Z14*Y14) | AD14: FALSE | AE14: =IF(ISBLANK(AC14), "", IF(AD14, AC14, AC14*$F14 ) ) | AF14: =IF(ISBLANK(AB14), 0, VLOOKUP(AB14, 'Price Sheet'!$A$2:$B1015, 2, false)) -> 0 | AG14: =IF(OR(ISBLANK(AC14), ISBLANK(AF14)), "", AF14*AE14) | AJ14: FALSE | AK14: =IF(ISBLANK(AI14), "", IF(AJ14, AI14, AI14*$F14 ) ) | AL14: =IF(ISBLANK(AH14), 0, VLOOKUP(AH14, 'Price Sheet'!$A$2:$B1015, 2, false)) -> 0 | AM14: =IF(OR(ISBLANK(AI14), ISBLANK(AL14)), "", AL14*AK14) | AP14: FALSE | AQ14: =IF(ISBLANK(AO14), "", IF(AP14, AO14, AO14*$F14 ) ) | AR14: =IF(ISBLANK(AN14), 0, VLOOKUP(AN14, 'Price Sheet'!$A$2:$B1015, 2, false)) -> 0 | AS14: =IF(OR(ISBLANK(AO14), ISBLANK(AR14)), "", AR14*AQ14) | AV14: FALSE | AW14: =IF(ISBLANK(AU14), "", IF(AV14, AU14, AU14*$F14 ) ) | AX14: =IF(ISBLANK(AT14), 0, VLOOKUP(AT14, 'Price Sheet'!$A$2:$B1015, 2, false)) -> 0 | AY14: =IF(OR(ISBLANK(AU14), ISBLANK(AX14)), "", AX14*AW14) | BB14: FALSE | BC14: =IF(ISBLANK(BA14), "", IF(BB14, BA14, BA14*$F14 ) ) | BD14: =IF(ISBLANK(AZ14), 0, VLOOKUP(AZ14, 'Price Sheet'!$A$2:$B1015, 2, false)) -> 0 | BE14: =IF(OR(ISBLANK(BA14), ISBLANK(BD14)), "", BD14*BC14) | BH14: FALSE | BI14: =IF(ISBLANK(BG14), "", IF(BH14, BG14, BG14*$F14 ) ) | BJ14: =IF(ISBLANK(BF14), 0, VLOOKUP(BF14, 'Price Sheet'!$A$2:$B1015, 2, false)) -> 0 | BK14: =IF(OR(ISBLANK(BG14), ISBLANK(BJ14)), "", BJ14*BI14) | BN14: FALSE | BO14: =IF(ISBLANK(BM14), "", IF(BN14, BM14, BM14*$F14 ) ) | BP14: =IF(ISBLANK(BL14), 0, VLOOKUP(BL14, 'Price Sheet'!$A$2:$B1015, 2, false)) -> 0 | BQ14: =IF(OR(ISBLANK(BM14), ISBLANK(BP14)), "", BP14*BO14)
A15: Hewn Dresser | B15: =H15+U15+AA15+AG15+AM15+AS15+AY15+BE15+BK15+J15+BQ15 -> 11.805 | C15: Logging | D15: Carpentry Table | E15: =IF(ISBLANK(D15), "", VLOOKUP(D15,'Crafting Tables'!$A$2:$B1015, 2, false)) -> Basic | F15: =IFERROR(IF(E15 = "None", 1, VLOOKUP(C15,General!$A$5:$L$35, SWITCH(E15, "Basic", 8, "Advanced", 10, "Modern", 12), false)),"") -> 0.55 | G15: 60 | H15: =IFERROR(VLOOKUP(C15, General!$A$5:$L$35, 6, false) * G15 / 1000, 0) -> 2.4 | J15: =IFERROR(I15*VLOOKUP(D15,'Crafting Tables'!$1:$1000, 4, false)*F15,"") -> 0 | K15: TRUE | L15: Hewn Dresser | M15: 1 | N15: =IF(ISBLANK(M15), "", $B15 / M15) -> 11.805 | P15: Hewn Log | Q15: 18 | R15: FALSE | S15: =IF(ISBLANK(Q15), "", IF(R15, Q15, Q15*$F15 ) ) -> 9.9 | T15: =IF(ISBLANK(P15), 0, VLOOKUP(P15, 'Price Sheet'!$A$2:$B1015, 2, false)) -> 0.8 | U15: =IF(OR(ISBLANK(Q15), ISBLANK(T15)), "", T15*S15) -> 7.92 | V15: Board | W15: 6 | X15: FALSE | Y15: =IF(ISBLANK(W15), "", IF(X15, W15, W15*$F15 ) ) -> 3.3 | Z15: =IF(ISBLANK(V15), 0, VLOOKUP(V15, 'Price Sheet'!$A$2:$B1015, 2, false)) -> 0.45 | AA15: =IF(OR(ISBLANK(W15), ISBLANK(Z15)), "", Z15*Y15) -> 1.485 | AD15: FALSE | AE15: =IF(ISBLANK(AC15), "", IF(AD15, AC15, AC15*$F15 ) ) | AF15: =IF(ISBLANK(AB15), 0, VLOOKUP(AB15, 'Price Sheet'!$A$2:$B1015, 2, false)) -> 0 | AG15: =IF(OR(ISBLANK(AC15), ISBLANK(AF15)), "", AF15*AE15) | AJ15: FALSE | AK15: =IF(ISBLANK(AI15), "", IF(AJ15, AI15, AI15*$F15 ) ) | AL15: =IF(ISBLANK(AH15), 0, VLOOKUP(AH15, 'Price Sheet'!$A$2:$B1015, 2, false)) -> 0 | AM15: =IF(OR(ISBLANK(AI15), ISBLANK(AL15)), "", AL15*AK15) | AP15: FALSE | AQ15: =IF(ISBLANK(AO15), "", IF(AP15, AO15, AO15*$F15 ) ) | AR15: =IF(ISBLANK(AN15), 0, VLOOKUP(AN15, 'Price Sheet'!$A$2:$B1015, 2, false)) -> 0 | AS15: =IF(OR(ISBLANK(AO15), ISBLANK(AR15)), "", AR15*AQ15) | AV15: FALSE | AW15: =IF(ISBLANK(AU15), "", IF(AV15, AU15, AU15*$F15 ) ) | AX15: =IF(ISBLANK(AT15), 0, VLOOKUP(AT15, 'Price Sheet'!$A$2:$B1015, 2, false)) -> 0 | AY15: =IF(OR(ISBLANK(AU15), ISBLANK(AX15)), "", AX15*AW15) | BB15: FALSE | BC15: =IF(ISBLANK(BA15), "", IF(BB15, BA15, BA15*$F15 ) ) | BD15: =IF(ISBLANK(AZ15), 0, VLOOKUP(AZ15, 'Price Sheet'!$A$2:$B1015, 2, false)) -> 0 | BE15: =IF(OR(ISBLANK(BA15), ISBLANK(BD15)), "", BD15*BC15) | BH15: FALSE | BI15: =IF(ISBLANK(BG15), "", IF(BH15, BG15, BG15*$F15 ) ) | BJ15: =IF(ISBLANK(BF15), 0, VLOOKUP(BF15, 'Price Sheet'!$A$2:$B1015, 2, false)) -> 0 | BK15: =IF(OR(ISBLANK(BG15), ISBLANK(BJ15)), "", BJ15*BI15) | BN15: FALSE | BO15: =IF(ISBLANK(BM15), "", IF(BN15, BM15, BM15*$F15 ) ) | BP15: =IF(ISBLANK(BL15), 0, VLOOKUP(BL15, 'Price Sheet'!$A$2:$B1015, 2, false)) -> 0 | BQ15: =IF(OR(ISBLANK(BM15), ISBLANK(BP15)), "", BP15*BO15)
A16: Hewn Nightstand | B16: =H16+U16+AA16+AG16+AM16+AS16+AY16+BE16+BK16+J16+BQ16 -> 10.54 | C16: Logging | D16: Carpentry Table | E16: =IF(ISBLANK(D16), "", VLOOKUP(D16,'Crafting Tables'!$A$2:$B1015, 2, false)) -> Basic | F16: =IFERROR(IF(E16 = "None", 1, VLOOKUP(C16,General!$A$5:$L$35, SWITCH(E16, "Basic", 8, "Advanced", 10, "Modern", 12), false)),"") -> 0.55 | G16: 60 | H16: =IFERROR(VLOOKUP(C16, General!$A$5:$L$35, 6, false) * G16 / 1000, 0) -> 2.4 | I16: 240 | J16: =IFERROR(I16*VLOOKUP(D16,'Crafting Tables'!$1:$1000, 4, false)*F16,"") -> 0 | K16: TRUE | L16: Hewn Nightstand | M16: 1 | N16: =IF(ISBLANK(M16), "", $B16 / M16) -> 10.54 | P16: Hewn Log | Q16: 14 | R16: FALSE | S16: =IF(ISBLANK(Q16), "", IF(R16, Q16, Q16*$F16 ) ) -> 7.7 | T16: =IF(ISBLANK(P16), 0, VLOOKUP(P16, 'Price Sheet'!$A$2:$B1015, 2, false)) -> 0.8 | U16: =IF(OR(ISBLANK(Q16), ISBLANK(T16)), "", T16*S16) -> 6.16 | V16: Board | W16: 8 | X16: FALSE | Y16: =IF(ISBLANK(W16), "", IF(X16, W16, W16*$F16 ) ) -> 4.4 | Z16: =IF(ISBLANK(V16), 0, VLOOKUP(V16, 'Price Sheet'!$A$2:$B1015, 2, false)) -> 0.45 | AA16: =IF(OR(ISBLANK(W16), ISBLANK(Z16)), "", Z16*Y16) -> 1.98 | AD16: FALSE | AE16: =IF(ISBLANK(AC16), "", IF(AD16, AC16, AC16*$F16 ) ) | AF16: =IF(ISBLANK(AB16), 0, VLOOKUP(AB16, 'Price Sheet'!$A$2:$B1015, 2, false)) -> 0 | AG16: =IF(OR(ISBLANK(AC16), ISBLANK(AF16)), "", AF16*AE16) | AJ16: FALSE | AK16: =IF(ISBLANK(AI16), "", IF(AJ16, AI16, AI16*$F16 ) ) | AL16: =IF(ISBLANK(AH16), 0, VLOOKUP(AH16, 'Price Sheet'!$A$2:$B1015, 2, false)) -> 0 | AM16: =IF(OR(ISBLANK(AI16), ISBLANK(AL16)), "", AL16*AK16) | AP16: FALSE | AQ16: =IF(ISBLANK(AO16), "", IF(AP16, AO16, AO16*$F16 ) ) | AR16: =IF(ISBLANK(AN16), 0, VLOOKUP(AN16, 'Price Sheet'!$A$2:$B1015, 2, false)) -> 0 | AS16: =IF(OR(ISBLANK(AO16), ISBLANK(AR16)), "", AR16*AQ16) | AV16: FALSE | AW16: =IF(ISBLANK(AU16), "", IF(AV16, AU16, AU16*$F16 ) ) | AX16: =IF(ISBLANK(AT16), 0, VLOOKUP(AT16, 'Price Sheet'!$A$2:$B1015, 2, false)) -> 0 | AY16: =IF(OR(ISBLANK(AU16), ISBLANK(AX16)), "", AX16*AW16) | BB16: FALSE | BC16: =IF(ISBLANK(BA16), "", IF(BB16, BA16, BA16*$F16 ) ) | BD16: =IF(ISBLANK(AZ16), 0, VLOOKUP(AZ16, 'Price Sheet'!$A$2:$B1015, 2, false)) -> 0 | BE16: =IF(OR(ISBLANK(BA16), ISBLANK(BD16)), "", BD16*BC16) | BH16: FALSE | BI16: =IF(ISBLANK(BG16), "", IF(BH16, BG16, BG16*$F16 ) ) | BJ16: =IF(ISBLANK(BF16), 0, VLOOKUP(BF16, 'Price Sheet'!$A$2:$B1015, 2, false)) -> 0 | BK16: =IF(OR(ISBLANK(BG16), ISBLANK(BJ16)), "", BJ16*BI16) | BN16: FALSE | BO16: =IF(ISBLANK(BM16), "", IF(BN16, BM16, BM16*$F16 ) ) | BP16: =IF(ISBLANK(BL16), 0, VLOOKUP(BL16, 'Price Sheet'!$A$2:$B1015, 2, false)) -> 0 | BQ16: =IF(OR(ISBLANK(BM16), ISBLANK(BP16)), "", BP16*BO16)
A17: Hewn Table | B17: =H17+U17+AA17+AG17+AM17+AS17+AY17+BE17+BK17+J17+BQ17 -> 10.485 | C17: Logging | D17: Carpentry Table | E17: =IF(ISBLANK(D17), "", VLOOKUP(D17,'Crafting Tables'!$A$2:$B1015, 2, false)) -> Basic | F17: =IFERROR(IF(E17 = "None", 1, VLOOKUP(C17,General!$A$5:$L$35, SWITCH(E17, "Basic", 8, "Advanced", 10, "Modern", 12), false)),"") -> 0.55 | G17: 60 | H17: =IFERROR(VLOOKUP(C17, General!$A$5:$L$35, 6, false) * G17 / 1000, 0) -> 2.4 | J17: =IFERROR(I17*VLOOKUP(D17,'Crafting Tables'!$1:$1000, 4, false)*F17,"") -> 0 | K17: TRUE | L17: Hewn Table | M17: 1 | N17: =IF(ISBLANK(M17), "", $B17 / M17) -> 10.485 | P17: Hewn Log | Q17: 15 | R17: FALSE | S17: =IF(ISBLANK(Q17), "", IF(R17, Q17, Q17*$F17 ) ) -> 8.25 | T17: =IF(ISBLANK(P17), 0, VLOOKUP(P17, 'Price Sheet'!$A$2:$B1015, 2, false)) -> 0.8 | U17: =IF(OR(ISBLANK(Q17), ISBLANK(T17)), "", T17*S17) -> 6.6 | V17: Board | W17: 6 | X17: FALSE | Y17: =IF(ISBLANK(W17), "", IF(X17, W17, W17*$F17 ) ) -> 3.3 | Z17: =IF(ISBLANK(V17), 0, VLOOKUP(V17, 'Price Sheet'!$A$2:$B1015, 2, false)) -> 0.45 | AA17: =IF(OR(ISBLANK(W17), ISBLANK(Z17)), "", Z17*Y17) -> 1.485 | AD17: FALSE | AE17: =IF(ISBLANK(AC17), "", IF(AD17, AC17, AC17*$F17 ) ) | AF17: =IF(ISBLANK(AB17), 0, VLOOKUP(AB17, 'Price Sheet'!$A$2:$B1015, 2, false)) -> 0 | AG17: =IF(OR(ISBLANK(AC17), ISBLANK(AF17)), "", AF17*AE17) | AJ17: FALSE | AK17: =IF(ISBLANK(AI17), "", IF(AJ17, AI17, AI17*$F17 ) ) | AL17: =IF(ISBLANK(AH17), 0, VLOOKUP(AH17, 'Price Sheet'!$A$2:$B1015, 2, false)) -> 0 | AM17: =IF(OR(ISBLANK(AI17), ISBLANK(AL17)), "", AL17*AK17) | AP17: FALSE | AQ17: =IF(ISBLANK(AO17), "", IF(AP17, AO17, AO17*$F17 ) ) | AR17: =IF(ISBLANK(AN17), 0, VLOOKUP(AN17, 'Price Sheet'!$A$2:$B1015, 2, false)) -> 0 | AS17: =IF(OR(ISBLANK(AO17), ISBLANK(AR17)), "", AR17*AQ17) | AV17: FALSE | AW17: =IF(ISBLANK(AU17), "", IF(AV17, AU17, AU17*$F17 ) ) | AX17: =IF(ISBLANK(AT17), 0, VLOOKUP(AT17, 'Price Sheet'!$A$2:$B1015, 2, false)) -> 0 | AY17: =IF(OR(ISBLANK(AU17), ISBLANK(AX17)), "", AX17*AW17) | BB17: FALSE | BC17: =IF(ISBLANK(BA17), "", IF(BB17, BA17, BA17*$F17 ) ) | BD17: =IF(ISBLANK(AZ17), 0, VLOOKUP(AZ17, 'Price Sheet'!$A$2:$B1015, 2, false)) -> 0 | BE17: =IF(OR(ISBLANK(BA17), ISBLANK(BD17)), "", BD17*BC17) | BH17: FALSE | BI17: =IF(ISBLANK(BG17), "", IF(BH17, BG17, BG17*$F17 ) ) | BJ17: =IF(ISBLANK(BF17), 0, VLOOKUP(BF17, 'Price Sheet'!$A$2:$B1015, 2, false)) -> 0 | BK17: =IF(OR(ISBLANK(BG17), ISBLANK(BJ17)), "", BJ17*BI17) | BN17: FALSE | BO17: =IF(ISBLANK(BM17), "", IF(BN17, BM17, BM17*$F17 ) ) | BP17: =IF(ISBLANK(BL17), 0, VLOOKUP(BL17, 'Price Sheet'!$A$2:$B1015, 2, false)) -> 0 | BQ17: =IF(OR(ISBLANK(BM17), ISBLANK(BP17)), "", BP17*BO17)
A18: Wooden Mold | B18: =H18+U18+AA18+AG18+AM18+AS18+AY18+BE18+BK18+J18+BQ18 -> 7 | C18: Logging | D18: Carpentry Table | E18: =IF(ISBLANK(D18), "", VLOOKUP(D18,'Crafting Tables'!$A$2:$B1015, 2, false)) -> Basic | F18: =IFERROR(IF(E18 = "None", 1, VLOOKUP(C18,General!$A$5:$L$35, SWITCH(E18, "Basic", 8, "Advanced", 10, "Modern", 12), false)),"") -> 0.55 | G18: 120 | H18: =IFERROR(VLOOKUP(C18, General!$A$5:$L$35, 6, false) * G18 / 1000, 0) -> 4.8 | J18: =IFERROR(I18*VLOOKUP(D18,'Crafting Tables'!$1:$1000, 4, false)*F18,"") -> 0 | K18: TRUE | L18: Wooden Mold | M18: 4 | N18: =IF(ISBLANK(M18), "", $B18 / M18) -> 1.75 | P18: Nails | Q18: 2 | R18: FALSE | S18: =IF(ISBLANK(Q18), "", IF(R18, Q18, Q18*$F18 ) ) -> 1.1 | T18: =IF(ISBLANK(P18), 0, VLOOKUP(P18, 'Price Sheet'!$A$2:$B1015, 2, false)) -> 0.2 | U18: =IF(OR(ISBLANK(Q18), ISBLANK(T18)), "", T18*S18) -> 0.22 | V18: Board | W18: 8 | X18: FALSE | Y18: =IF(ISBLANK(W18), "", IF(X18, W18, W18*$F18 ) ) -> 4.4 | Z18: =IF(ISBLANK(V18), 0, VLOOKUP(V18, 'Price Sheet'!$A$2:$B1015, 2, false)) -> 0.45 | AA18: =IF(OR(ISBLANK(W18), ISBLANK(Z18)), "", Z18*Y18) -> 1.98 | AD18: FALSE | AE18: =IF(ISBLANK(AC18), "", IF(AD18, AC18, AC18*$F18 ) ) | AF18: =IF(ISBLANK(AB18), 0, VLOOKUP(AB18, 'Price Sheet'!$A$2:$B1015, 2, false)) -> 0 | AG18: =IF(OR(ISBLANK(AC18), ISBLANK(AF18)), "", AF18*AE18) | AJ18: FALSE | AK18: =IF(ISBLANK(AI18), "", IF(AJ18, AI18, AI18*$F18 ) ) | AL18: =IF(ISBLANK(AH18), 0, VLOOKUP(AH18, 'Price Sheet'!$A$2:$B1015, 2, false)) -> 0 | AM18: =IF(OR(ISBLANK(AI18), ISBLANK(AL18)), "", AL18*AK18) | AP18: FALSE | AQ18: =IF(ISBLANK(AO18), "", IF(AP18, AO18, AO18*$F18 ) ) | AR18: =IF(ISBLANK(AN18), 0, VLOOKUP(AN18, 'Price Sheet'!$A$2:$B1015, 2, false)) -> 0 | AS18: =IF(OR(ISBLANK(AO18), ISBLANK(AR18)), "", AR18*AQ18) | AV18: FALSE | AW18: =IF(ISBLANK(AU18), "", IF(AV18, AU18, AU18*$F18 ) ) | AX18: =IF(ISBLANK(AT18), 0, VLOOKUP(AT18, 'Price Sheet'!$A$2:$B1015, 2, false)) -> 0 | AY18: =IF(OR(ISBLANK(AU18), ISBLANK(AX18)), "", AX18*AW18) | BB18: FALSE | BC18: =IF(ISBLANK(BA18), "", IF(BB18, BA18, BA18*$F18 ) ) | BD18: =IF(ISBLANK(AZ18), 0, VLOOKUP(AZ18, 'Price Sheet'!$A$2:$B1015, 2, false)) -> 0 | BE18: =IF(OR(ISBLANK(BA18), ISBLANK(BD18)), "", BD18*BC18) | BH18: FALSE | BI18: =IF(ISBLANK(BG18), "", IF(BH18, BG18, BG18*$F18 ) ) | BJ18: =IF(ISBLANK(BF18), 0, VLOOKUP(BF18, 'Price Sheet'!$A$2:$B1015, 2, false)) -> 0 | BK18: =IF(OR(ISBLANK(BG18), ISBLANK(BJ18)), "", BJ18*BI18) | BN18: FALSE | BO18: =IF(ISBLANK(BM18), "", IF(BN18, BM18, BM18*$F18 ) ) | BP18: =IF(ISBLANK(BL18), 0, VLOOKUP(BL18, 'Price Sheet'!$A$2:$B1015, 2, false)) -> 0 | BQ18: =IF(OR(ISBLANK(BM18), ISBLANK(BP18)), "", BP18*BO18)
A19: Wooden Keel | B19: =H19+U19+AA19+AG19+AM19+AS19+AY19+BE19+BK19+J19+BQ19 -> 4.6 | C19: Logging | D19: Carpentry Table | E19: =IF(ISBLANK(D19), "", VLOOKUP(D19,'Crafting Tables'!$A$2:$B1015, 2, false)) -> Basic | F19: =IFERROR(IF(E19 = "None", 1, VLOOKUP(C19,General!$A$5:$L$35, SWITCH(E19, "Basic", 8, "Advanced", 10, "Modern", 12), false)),"") -> 0.55 | G19: 60 | H19: =IFERROR(VLOOKUP(C19, General!$A$5:$L$35, 6, false) * G19 / 1000, 0) -> 2.4 | J19: =IFERROR(I19*VLOOKUP(D19,'Crafting Tables'!$1:$1000, 4, false)*F19,"") -> 0 | K19: TRUE | L19: Wooden Keel | M19: 1 | N19: =IF(ISBLANK(M19), "", $B19 / M19) -> 4.6 | P19: Wood (Tag) | Q19: 8 | R19: FALSE | S19: =IF(ISBLANK(Q19), "", IF(R19, Q19, Q19*$F19 ) ) -> 4.4 | T19: =IF(ISBLANK(P19), 0, VLOOKUP(P19, 'Price Sheet'!$A$2:$B1015, 2, false)) -> 0.5 | U19: =IF(OR(ISBLANK(Q19), ISBLANK(T19)), "", T19*S19) -> 2.2 | X19: FALSE | Y19: =IF(ISBLANK(W19), "", IF(X19, W19, W19*$F19 ) ) | Z19: =IF(ISBLANK(V19), 0, VLOOKUP(V19, 'Price Sheet'!$A$2:$B1015, 2, false)) -> 0 | AA19: =IF(OR(ISBLANK(W19), ISBLANK(Z19)), "", Z19*Y19) | AD19: FALSE | AE19: =IF(ISBLANK(AC19), "", IF(AD19, AC19, AC19*$F19 ) ) | AF19: =IF(ISBLANK(AB19), 0, VLOOKUP(AB19, 'Price Sheet'!$A$2:$B1015, 2, false)) -> 0 | AG19: =IF(OR(ISBLANK(AC19), ISBLANK(AF19)), "", AF19*AE19) | AJ19: FALSE | AK19: =IF(ISBLANK(AI19), "", IF(AJ19, AI19, AI19*$F19 ) ) | AL19: =IF(ISBLANK(AH19), 0, VLOOKUP(AH19, 'Price Sheet'!$A$2:$B1015, 2, false)) -> 0 | AM19: =IF(OR(ISBLANK(AI19), ISBLANK(AL19)), "", AL19*AK19) | AP19: FALSE | AQ19: =IF(ISBLANK(AO19), "", IF(AP19, AO19, AO19*$F19 ) ) | AR19: =IF(ISBLANK(AN19), 0, VLOOKUP(AN19, 'Price Sheet'!$A$2:$B1015, 2, false)) -> 0 | AS19: =IF(OR(ISBLANK(AO19), ISBLANK(AR19)), "", AR19*AQ19) | AV19: FALSE | AW19: =IF(ISBLANK(AU19), "", IF(AV19, AU19, AU19*$F19 ) ) | AX19: =IF(ISBLANK(AT19), 0, VLOOKUP(AT19, 'Price Sheet'!$A$2:$B1015, 2, false)) -> 0 | AY19: =IF(OR(ISBLANK(AU19), ISBLANK(AX19)), "", AX19*AW19) | BB19: FALSE | BC19: =IF(ISBLANK(BA19), "", IF(BB19, BA19, BA19*$F19 ) ) | BD19: =IF(ISBLANK(AZ19), 0, VLOOKUP(AZ19, 'Price Sheet'!$A$2:$B1015, 2, false)) -> 0 | BE19: =IF(OR(ISBLANK(BA19), ISBLANK(BD19)), "", BD19*BC19) | BH19: FALSE | BI19: =IF(ISBLANK(BG19), "", IF(BH19, BG19, BG19*$F19 ) ) | BJ19: =IF(ISBLANK(BF19), 0, VLOOKUP(BF19, 'Price Sheet'!$A$2:$B1015, 2, false)) -> 0 | BK19: =IF(OR(ISBLANK(BG19), ISBLANK(BJ19)), "", BJ19*BI19) | BN19: FALSE | BO19: =IF(ISBLANK(BM19), "", IF(BN19, BM19, BM19*$F19 ) ) | BP19: =IF(ISBLANK(BL19), 0, VLOOKUP(BL19, 'Price Sheet'!$A$2:$B1015, 2, false)) -> 0 | BQ19: =IF(OR(ISBLANK(BM19), ISBLANK(BP19)), "", BP19*BO19)
A20: Wooden Oar | B20: =H20+U20+AA20+AG20+AM20+AS20+AY20+BE20+BK20+J20+BQ20 -> 4.16 | C20: Logging | D20: Carpentry Table | E20: =IF(ISBLANK(D20), "", VLOOKUP(D20,'Crafting Tables'!$A$2:$B1015, 2, false)) -> Basic | F20: =IFERROR(IF(E20 = "None", 1, VLOOKUP(C20,General!$A$5:$L$35, SWITCH(E20, "Basic", 8, "Advanced", 10, "Modern", 12), false)),"") -> 0.55 | G20: 60 | H20: =IFERROR(VLOOKUP(C20, General!$A$5:$L$35, 6, false) * G20 / 1000, 0) -> 2.4 | J20: =IFERROR(I20*VLOOKUP(D20,'Crafting Tables'!$1:$1000, 4, false)*F20,"") -> 0 | K20: TRUE | L20: Wooden Oar | M20: 1 | N20: =IF(ISBLANK(M20), "", $B20 / M20) -> 4.16 | P20: Hewn Log | Q20: 4 | R20: FALSE | S20: =IF(ISBLANK(Q20), "", IF(R20, Q20, Q20*$F20 ) ) -> 2.2 | T20: =IF(ISBLANK(P20), 0, VLOOKUP(P20, 'Price Sheet'!$A$2:$B1015, 2, false)) -> 0.8 | U20: =IF(OR(ISBLANK(Q20), ISBLANK(T20)), "", T20*S20) -> 1.76 | X20: FALSE | Y20: =IF(ISBLANK(W20), "", IF(X20, W20, W20*$F20 ) ) | Z20: =IF(ISBLANK(V20), 0, VLOOKUP(V20, 'Price Sheet'!$A$2:$B1015, 2, false)) -> 0 | AA20: =IF(OR(ISBLANK(W20), ISBLANK(Z20)), "", Z20*Y20) | AD20: FALSE | AE20: =IF(ISBLANK(AC20), "", IF(AD20, AC20, AC20*$F20 ) ) | AF20: =IF(ISBLANK(AB20), 0, VLOOKUP(AB20, 'Price Sheet'!$A$2:$B1015, 2, false)) -> 0 | AG20: =IF(OR(ISBLANK(AC20), ISBLANK(AF20)), "", AF20*AE20) | AJ20: FALSE | AK20: =IF(ISBLANK(AI20), "", IF(AJ20, AI20, AI20*$F20 ) ) | AL20: =IF(ISBLANK(AH20), 0, VLOOKUP(AH20, 'Price Sheet'!$A$2:$B1015, 2, false)) -> 0 | AM20: =IF(OR(ISBLANK(AI20), ISBLANK(AL20)), "", AL20*AK20) | AP20: FALSE | AQ20: =IF(ISBLANK(AO20), "", IF(AP20, AO20, AO20*$F20 ) ) | AR20: =IF(ISBLANK(AN20), 0, VLOOKUP(AN20, 'Price Sheet'!$A$2:$B1015, 2, false)) -> 0 | AS20: =IF(OR(ISBLANK(AO20), ISBLANK(AR20)), "", AR20*AQ20) | AV20: FALSE | AW20: =IF(ISBLANK(AU20), "", IF(AV20, AU20, AU20*$F20 ) ) | AX20: =IF(ISBLANK(AT20), 0, VLOOKUP(AT20, 'Price Sheet'!$A$2:$B1015, 2, false)) -> 0 | AY20: =IF(OR(ISBLANK(AU20), ISBLANK(AX20)), "", AX20*AW20) | BB20: FALSE | BC20: =IF(ISBLANK(BA20), "", IF(BB20, BA20, BA20*$F20 ) ) | BD20: =IF(ISBLANK(AZ20), 0, VLOOKUP(AZ20, 'Price Sheet'!$A$2:$B1015, 2, false)) -> 0 | BE20: =IF(OR(ISBLANK(BA20), ISBLANK(BD20)), "", BD20*BC20) | BH20: FALSE | BI20: =IF(ISBLANK(BG20), "", IF(BH20, BG20, BG20*$F20 ) ) | BJ20: =IF(ISBLANK(BF20), 0, VLOOKUP(BF20, 'Price Sheet'!$A$2:$B1015, 2, false)) -> 0 | BK20: =IF(OR(ISBLANK(BG20), ISBLANK(BJ20)), "", BJ20*BI20) | BN20: FALSE | BO20: =IF(ISBLANK(BM20), "", IF(BN20, BM20, BM20*$F20 ) ) | BP20: =IF(ISBLANK(BL20), 0, VLOOKUP(BL20, 'Price Sheet'!$A$2:$B1015, 2, false)) -> 0 | BQ20: =IF(OR(ISBLANK(BM20), ISBLANK(BP20)), "", BP20*BO20)
A21: Small Shipyard | B21: =H21+U21+AA21+AG21+AM21+AS21+AY21+BE21+BK21+J21+BQ21 -> 20.78 | C21: Logging | D21: Carpentry Table | E21: =IF(ISBLANK(D21), "", VLOOKUP(D21,'Crafting Tables'!$A$2:$B1015, 2, false)) -> Basic | F21: =IFERROR(IF(E21 = "None", 1, VLOOKUP(C21,General!$A$5:$L$35, SWITCH(E21, "Basic", 8, "Advanced", 10, "Modern", 12), false)),"") -> 0.55 | G21: 360 | H21: =IFERROR(VLOOKUP(C21, General!$A$5:$L$35, 6, false) * G21 / 1000, 0) -> 14.4 | J21: =IFERROR(I21*VLOOKUP(D21,'Crafting Tables'!$1:$1000, 4, false)*F21,"") -> 0 | K21: TRUE | L21: Small Shipyard | M21: 1 | N21: =IF(ISBLANK(M21), "", $B21 / M21) -> 20.78 | P21: Hewn Log | Q21: 10 | R21: FALSE | S21: =IF(ISBLANK(Q21), "", IF(R21, Q21, Q21*$F21 ) ) -> 5.5 | T21: =IF(ISBLANK(P21), 0, VLOOKUP(P21, 'Price Sheet'!$A$2:$B1015, 2, false)) -> 0.8 | U21: =IF(OR(ISBLANK(Q21), ISBLANK(T21)), "", T21*S21) -> 4.4 | V21: Board | W21: 8 | X21: FALSE | Y21: =IF(ISBLANK(W21), "", IF(X21, W21, W21*$F21 ) ) -> 4.4 | Z21: =IF(ISBLANK(V21), 0, VLOOKUP(V21, 'Price Sheet'!$A$2:$B1015, 2, false)) -> 0.45 | AA21: =IF(OR(ISBLANK(W21), ISBLANK(Z21)), "", Z21*Y21) -> 1.98 | AD21: FALSE | AE21: =IF(ISBLANK(AC21), "", IF(AD21, AC21, AC21*$F21 ) ) | AF21: =IF(ISBLANK(AB21), 0, VLOOKUP(AB21, 'Price Sheet'!$A$2:$B1015, 2, false)) -> 0 | AG21: =IF(OR(ISBLANK(AC21), ISBLANK(AF21)), "", AF21*AE21) | AJ21: FALSE | AK21: =IF(ISBLANK(AI21), "", IF(AJ21, AI21, AI21*$F21 ) ) | AL21: =IF(ISBLANK(AH21), 0, VLOOKUP(AH21, 'Price Sheet'!$A$2:$B1015, 2, false)) -> 0 | AM21: =IF(OR(ISBLANK(AI21), ISBLANK(AL21)), "", AL21*AK21) | AP21: FALSE | AQ21: =IF(ISBLANK(AO21), "", IF(AP21, AO21, AO21*$F21 ) ) | AR21: =IF(ISBLANK(AN21), 0, VLOOKUP(AN21, 'Price Sheet'!$A$2:$B1015, 2, false)) -> 0 | AS21: =IF(OR(ISBLANK(AO21), ISBLANK(AR21)), "", AR21*AQ21) | AV21: FALSE | AW21: =IF(ISBLANK(AU21), "", IF(AV21, AU21, AU21*$F21 ) ) | AX21: =IF(ISBLANK(AT21), 0, VLOOKUP(AT21, 'Price Sheet'!$A$2:$B1015, 2, false)) -> 0 | AY21: =IF(OR(ISBLANK(AU21), ISBLANK(AX21)), "", AX21*AW21) | BB21: FALSE | BC21: =IF(ISBLANK(BA21), "", IF(BB21, BA21, BA21*$F21 ) ) | BD21: =IF(ISBLANK(AZ21), 0, VLOOKUP(AZ21, 'Price Sheet'!$A$2:$B1015, 2, false)) -> 0 | BE21: =IF(OR(ISBLANK(BA21), ISBLANK(BD21)), "", BD21*BC21) | BH21: FALSE | BI21: =IF(ISBLANK(BG21), "", IF(BH21, BG21, BG21*$F21 ) ) | BJ21: =IF(ISBLANK(BF21), 0, VLOOKUP(BF21, 'Price Sheet'!$A$2:$B1015, 2, false)) -> 0 | BK21: =IF(OR(ISBLANK(BG21), ISBLANK(BJ21)), "", BJ21*BI21) | BN21: FALSE | BO21: =IF(ISBLANK(BM21), "", IF(BN21, BM21, BM21*$F21 ) ) | BP21: =IF(ISBLANK(BL21), 0, VLOOKUP(BL21, 'Price Sheet'!$A$2:$B1015, 2, false)) -> 0 | BQ21: =IF(OR(ISBLANK(BM21), ISBLANK(BP21)), "", BP21*BO21)
A22: Small Wooden Ship Frame | B22: =H22+U22+AA22+AG22+AM22+AS22+AY22+BE22+BK22+J22+BQ22 -> 10.52 | C22: Shipwright | D22: Small Shipyard | E22: =IF(ISBLANK(D22), "", VLOOKUP(D22,'Crafting Tables'!$A$2:$B1015, 2, false)) -> Basic | F22: =IFERROR(IF(E22 = "None", 1, VLOOKUP(C22,General!$A$5:$L$35, SWITCH(E22, "Basic", 8, "Advanced", 10, "Modern", 12), false)),"") -> 0.55 | G22: 60 | H22: =IFERROR(VLOOKUP(C22, General!$A$5:$L$35, 6, false) * G22 / 1000, 0) -> 2.4 | J22: =IFERROR(I22*VLOOKUP(D22,'Crafting Tables'!$1:$1000, 4, false)*F22,"") -> 0 | K22: TRUE | L22: Small Wooden Ship Frame | M22: 1 | N22: =IF(ISBLANK(M22), "", $B22 / M22) -> 10.52 | P22: Hewn Log | Q22: 8 | R22: FALSE | S22: =IF(ISBLANK(Q22), "", IF(R22, Q22, Q22*$F22 ) ) -> 4.4 | T22: =IF(ISBLANK(P22), 0, VLOOKUP(P22, 'Price Sheet'!$A$2:$B1015, 2, false)) -> 0.8 | U22: =IF(OR(ISBLANK(Q22), ISBLANK(T22)), "", T22*S22) -> 3.52 | V22: Wooden Keel | W22: 1 | X22: TRUE | Y22: =IF(ISBLANK(W22), "", IF(X22, W22, W22*$F22 ) ) -> 1 | Z22: =IF(ISBLANK(V22), 0, VLOOKUP(V22, 'Price Sheet'!$A$2:$B1015, 2, false)) -> 4.6 | AA22: =IF(OR(ISBLANK(W22), ISBLANK(Z22)), "", Z22*Y22) -> 4.6 | AD22: FALSE | AE22: =IF(ISBLANK(AC22), "", IF(AD22, AC22, AC22*$F22 ) ) | AF22: =IF(ISBLANK(AB22), 0, VLOOKUP(AB22, 'Price Sheet'!$A$2:$B1015, 2, false)) -> 0 | AG22: =IF(OR(ISBLANK(AC22), ISBLANK(AF22)), "", AF22*AE22) | AJ22: FALSE | AK22: =IF(ISBLANK(AI22), "", IF(AJ22, AI22, AI22*$F22 ) ) | AL22: =IF(ISBLANK(AH22), 0, VLOOKUP(AH22, 'Price Sheet'!$A$2:$B1015, 2, false)) -> 0 | AM22: =IF(OR(ISBLANK(AI22), ISBLANK(AL22)), "", AL22*AK22) | AP22: FALSE | AQ22: =IF(ISBLANK(AO22), "", IF(AP22, AO22, AO22*$F22 ) ) | AR22: =IF(ISBLANK(AN22), 0, VLOOKUP(AN22, 'Price Sheet'!$A$2:$B1015, 2, false)) -> 0 | AS22: =IF(OR(ISBLANK(AO22), ISBLANK(AR22)), "", AR22*AQ22) | AV22: FALSE | AW22: =IF(ISBLANK(AU22), "", IF(AV22, AU22, AU22*$F22 ) ) | AX22: =IF(ISBLANK(AT22), 0, VLOOKUP(AT22, 'Price Sheet'!$A$2:$B1015, 2, false)) -> 0 | AY22: =IF(OR(ISBLANK(AU22), ISBLANK(AX22)), "", AX22*AW22) | BB22: FALSE | BC22: =IF(ISBLANK(BA22), "", IF(BB22, BA22, BA22*$F22 ) ) | BD22: =IF(ISBLANK(AZ22), 0, VLOOKUP(AZ22, 'Price Sheet'!$A$2:$B1015, 2, false)) -> 0 | BE22: =IF(OR(ISBLANK(BA22), ISBLANK(BD22)), "", BD22*BC22) | BH22: FALSE | BI22: =IF(ISBLANK(BG22), "", IF(BH22, BG22, BG22*$F22 ) ) | BJ22: =IF(ISBLANK(BF22), 0, VLOOKUP(BF22, 'Price Sheet'!$A$2:$B1015, 2, false)) -> 0 | BK22: =IF(OR(ISBLANK(BG22), ISBLANK(BJ22)), "", BJ22*BI22) | BN22: FALSE | BO22: =IF(ISBLANK(BM22), "", IF(BN22, BM22, BM22*$F22 ) ) | BP22: =IF(ISBLANK(BL22), 0, VLOOKUP(BL22, 'Price Sheet'!$A$2:$B1015, 2, false)) -> 0 | BQ22: =IF(OR(ISBLANK(BM22), ISBLANK(BP22)), "", BP22*BO22)
A23: Wooden Hull Planks | B23: =H23+U23+AA23+AG23+AM23+AS23+AY23+BE23+BK23+J23+BQ23 -> 4.16 | C23: Shipwright | D23: Small Shipyard | E23: =IF(ISBLANK(D23), "", VLOOKUP(D23,'Crafting Tables'!$A$2:$B1015, 2, false)) -> Basic | F23: =IFERROR(IF(E23 = "None", 1, VLOOKUP(C23,General!$A$5:$L$35, SWITCH(E23, "Basic", 8, "Advanced", 10, "Modern", 12), false)),"") -> 0.55 | G23: 60 | H23: =IFERROR(VLOOKUP(C23, General!$A$5:$L$35, 6, false) * G23 / 1000, 0) -> 2.4 | J23: =IFERROR(I23*VLOOKUP(D23,'Crafting Tables'!$1:$1000, 4, false)*F23,"") -> 0 | K23: TRUE | L23: Wooden Hull Planks | M23: 1 | N23: =IF(ISBLANK(M23), "", $B23 / M23) -> 4.16 | P23: Hewn Log | Q23: 4 | R23: FALSE | S23: =IF(ISBLANK(Q23), "", IF(R23, Q23, Q23*$F23 ) ) -> 2.2 | T23: =IF(ISBLANK(P23), 0, VLOOKUP(P23, 'Price Sheet'!$A$2:$B1015, 2, false)) -> 0.8 | U23: =IF(OR(ISBLANK(Q23), ISBLANK(T23)), "", T23*S23) -> 1.76 | X23: FALSE | Y23: =IF(ISBLANK(W23), "", IF(X23, W23, W23*$F23 ) ) | Z23: =IF(ISBLANK(V23), 0, VLOOKUP(V23, 'Price Sheet'!$A$2:$B1015, 2, false)) -> 0 | AA23: =IF(OR(ISBLANK(W23), ISBLANK(Z23)), "", Z23*Y23) | AD23: FALSE | AE23: =IF(ISBLANK(AC23), "", IF(AD23, AC23, AC23*$F23 ) ) | AF23: =IF(ISBLANK(AB23), 0, VLOOKUP(AB23, 'Price Sheet'!$A$2:$B1015, 2, false)) -> 0 | AG23: =IF(OR(ISBLANK(AC23), ISBLANK(AF23)), "", AF23*AE23) | AJ23: FALSE | AK23: =IF(ISBLANK(AI23), "", IF(AJ23, AI23, AI23*$F23 ) ) | AL23: =IF(ISBLANK(AH23), 0, VLOOKUP(AH23, 'Price Sheet'!$A$2:$B1015, 2, false)) -> 0 | AM23: =IF(OR(ISBLANK(AI23), ISBLANK(AL23)), "", AL23*AK23) | AP23: FALSE | AQ23: =IF(ISBLANK(AO23), "", IF(AP23, AO23, AO23*$F23 ) ) | AR23: =IF(ISBLANK(AN23), 0, VLOOKUP(AN23, 'Price Sheet'!$A$2:$B1015, 2, false)) -> 0 | AS23: =IF(OR(ISBLANK(AO23), ISBLANK(AR23)), "", AR23*AQ23) | AV23: FALSE | AW23: =IF(ISBLANK(AU23), "", IF(AV23, AU23, AU23*$F23 ) ) | AX23: =IF(ISBLANK(AT23), 0, VLOOKUP(AT23, 'Price Sheet'!$A$2:$B1015, 2, false)) -> 0 | AY23: =IF(OR(ISBLANK(AU23), ISBLANK(AX23)), "", AX23*AW23) | BB23: FALSE | BC23: =IF(ISBLANK(BA23), "", IF(BB23, BA23, BA23*$F23 ) ) | BD23: =IF(ISBLANK(AZ23), 0, VLOOKUP(AZ23, 'Price Sheet'!$A$2:$B1015, 2, false)) -> 0 | BE23: =IF(OR(ISBLANK(BA23), ISBLANK(BD23)), "", BD23*BC23) | BH23: FALSE | BI23: =IF(ISBLANK(BG23), "", IF(BH23, BG23, BG23*$F23 ) ) | BJ23: =IF(ISBLANK(BF23), 0, VLOOKUP(BF23, 'Price Sheet'!$A$2:$B1015, 2, false)) -> 0 | BK23: =IF(OR(ISBLANK(BG23), ISBLANK(BJ23)), "", BJ23*BI23) | BN23: FALSE | BO23: =IF(ISBLANK(BM23), "", IF(BN23, BM23, BM23*$F23 ) ) | BP23: =IF(ISBLANK(BL23), 0, VLOOKUP(BL23, 'Price Sheet'!$A$2:$B1015, 2, false)) -> 0 | BQ23: =IF(OR(ISBLANK(BM23), ISBLANK(BP23)), "", BP23*BO23)
A24: Small Canoe | B24: =H24+U24+AA24+AG24+AM24+AS24+AY24+BE24+BK24+J24+BQ24 -> 30.48 | C24: Shipwright | D24: Small Shipyard | E24: =IF(ISBLANK(D24), "", VLOOKUP(D24,'Crafting Tables'!$A$2:$B1015, 2, false)) -> Basic | F24: =IFERROR(IF(E24 = "None", 1, VLOOKUP(C24,General!$A$5:$L$35, SWITCH(E24, "Basic", 8, "Advanced", 10, "Modern", 12), false)),"") -> 0.55 | G24: 120 | H24: =IFERROR(VLOOKUP(C24, General!$A$5:$L$35, 6, false) * G24 / 1000, 0) -> 4.8 | J24: =IFERROR(I24*VLOOKUP(D24,'Crafting Tables'!$1:$1000, 4, false)*F24,"") -> 0 | K24: TRUE | L24: Small Canoe | M24: 1 | N24: =IF(ISBLANK(M24), "", $B24 / M24) -> 30.48 | P24: Wooden Hull Planks | Q24: 4 | R24: FALSE | S24: =IF(ISBLANK(Q24), "", IF(R24, Q24, Q24*$F24 ) ) -> 2.2 | T24: =IF(ISBLANK(P24), 0, VLOOKUP(P24, 'Price Sheet'!$A$2:$B1015, 2, false)) -> 5 | U24: =IF(OR(ISBLANK(Q24), ISBLANK(T24)), "", T24*S24) -> 11 | V24: Wooden Oar | W24: 1 | X24: TRUE | Y24: =IF(ISBLANK(W24), "", IF(X24, W24, W24*$F24 ) ) -> 1 | Z24: =IF(ISBLANK(V24), 0, VLOOKUP(V24, 'Price Sheet'!$A$2:$B1015, 2, false)) -> 4.16 | AA24: =IF(OR(ISBLANK(W24), ISBLANK(Z24)), "", Z24*Y24) -> 4.16 | AB24: Small Wooden Ship Frame | AC24: 1 | AD24: TRUE | AE24: =IF(ISBLANK(AC24), "", IF(AD24, AC24, AC24*$F24 ) ) -> 1 | AF24: =IF(ISBLANK(AB24), 0, VLOOKUP(AB24, 'Price Sheet'!$A$2:$B1015, 2, false)) -> 10.52 | AG24: =IF(OR(ISBLANK(AC24), ISBLANK(AF24)), "", AF24*AE24) -> 10.52 | AJ24: FALSE | AK24: =IF(ISBLANK(AI24), "", IF(AJ24, AI24, AI24*$F24 ) ) | AL24: =IF(ISBLANK(AH24), 0, VLOOKUP(AH24, 'Price Sheet'!$A$2:$B1015, 2, false)) -> 0 | AM24: =IF(OR(ISBLANK(AI24), ISBLANK(AL24)), "", AL24*AK24) | AP24: FALSE | AQ24: =IF(ISBLANK(AO24), "", IF(AP24, AO24, AO24*$F24 ) ) | AR24: =IF(ISBLANK(AN24), 0, VLOOKUP(AN24, 'Price Sheet'!$A$2:$B1015, 2, false)) -> 0 | AS24: =IF(OR(ISBLANK(AO24), ISBLANK(AR24)), "", AR24*AQ24) | AV24: FALSE | AW24: =IF(ISBLANK(AU24), "", IF(AV24, AU24, AU24*$F24 ) ) | AX24: =IF(ISBLANK(AT24), 0, VLOOKUP(AT24, 'Price Sheet'!$A$2:$B1015, 2, false)) -> 0 | AY24: =IF(OR(ISBLANK(AU24), ISBLANK(AX24)), "", AX24*AW24) | BB24: FALSE | BC24: =IF(ISBLANK(BA24), "", IF(BB24, BA24, BA24*$F24 ) ) | BD24: =IF(ISBLANK(AZ24), 0, VLOOKUP(AZ24, 'Price Sheet'!$A$2:$B1015, 2, false)) -> 0 | BE24: =IF(OR(ISBLANK(BA24), ISBLANK(BD24)), "", BD24*BC24) | BH24: FALSE | BI24: =IF(ISBLANK(BG24), "", IF(BH24, BG24, BG24*$F24 ) ) | BJ24: =IF(ISBLANK(BF24), 0, VLOOKUP(BF24, 'Price Sheet'!$A$2:$B1015, 2, false)) -> 0 | BK24: =IF(OR(ISBLANK(BG24), ISBLANK(BJ24)), "", BJ24*BI24) | BN24: FALSE | BO24: =IF(ISBLANK(BM24), "", IF(BN24, BM24, BM24*$F24 ) ) | BP24: =IF(ISBLANK(BL24), 0, VLOOKUP(BL24, 'Price Sheet'!$A$2:$B1015, 2, false)) -> 0 | BQ24: =IF(OR(ISBLANK(BM24), ISBLANK(BP24)), "", BP24*BO24)
A25: Large Canoe | B25: =H25+U25+AA25+AG25+AM25+AS25+AY25+BE25+BK25+J25+BQ25 -> 51.08 | C25: Shipwright | D25: Small Shipyard | E25: =IF(ISBLANK(D25), "", VLOOKUP(D25,'Crafting Tables'!$A$2:$B1015, 2, false)) -> Basic | F25: =IFERROR(IF(E25 = "None", 1, VLOOKUP(C25,General!$A$5:$L$35, SWITCH(E25, "Basic", 8, "Advanced", 10, "Modern", 12), false)),"") -> 0.55 | G25: 360 | H25: =IFERROR(VLOOKUP(C25, General!$A$5:$L$35, 6, false) * G25 / 1000, 0) -> 14.4 | J25: =IFERROR(I25*VLOOKUP(D25,'Crafting Tables'!$1:$1000, 4, false)*F25,"") -> 0 | K25: TRUE | L25: Large Canoe | M25: 1 | N25: =IF(ISBLANK(M25), "", $B25 / M25) -> 51.08 | P25: Wooden Hull Planks | Q25: 8 | R25: FALSE | S25: =IF(ISBLANK(Q25), "", IF(R25, Q25, Q25*$F25 ) ) -> 4.4 | T25: =IF(ISBLANK(P25), 0, VLOOKUP(P25, 'Price Sheet'!$A$2:$B1015, 2, false)) -> 5 | U25: =IF(OR(ISBLANK(Q25), ISBLANK(T25)), "", T25*S25) -> 22 | V25: Wooden Oar | W25: 1 | X25: TRUE | Y25: =IF(ISBLANK(W25), "", IF(X25, W25, W25*$F25 ) ) -> 1 | Z25: =IF(ISBLANK(V25), 0, VLOOKUP(V25, 'Price Sheet'!$A$2:$B1015, 2, false)) -> 4.16 | AA25: =IF(OR(ISBLANK(W25), ISBLANK(Z25)), "", Z25*Y25) -> 4.16 | AB25: Small Wooden Ship Frame | AC25: 1 | AD25: TRUE | AE25: =IF(ISBLANK(AC25), "", IF(AD25, AC25, AC25*$F25 ) ) -> 1 | AF25: =IF(ISBLANK(AB25), 0, VLOOKUP(AB25, 'Price Sheet'!$A$2:$B1015, 2, false)) -> 10.52 | AG25: =IF(OR(ISBLANK(AC25), ISBLANK(AF25)), "", AF25*AE25) -> 10.52 | AJ25: FALSE | AK25: =IF(ISBLANK(AI25), "", IF(AJ25, AI25, AI25*$F25 ) ) | AL25: =IF(ISBLANK(AH25), 0, VLOOKUP(AH25, 'Price Sheet'!$A$2:$B1015, 2, false)) -> 0 | AM25: =IF(OR(ISBLANK(AI25), ISBLANK(AL25)), "", AL25*AK25) | AP25: FALSE | AQ25: =IF(ISBLANK(AO25), "", IF(AP25, AO25, AO25*$F25 ) ) | AR25: =IF(ISBLANK(AN25), 0, VLOOKUP(AN25, 'Price Sheet'!$A$2:$B1015, 2, false)) -> 0 | AS25: =IF(OR(ISBLANK(AO25), ISBLANK(AR25)), "", AR25*AQ25) | AV25: FALSE | AW25: =IF(ISBLANK(AU25), "", IF(AV25, AU25, AU25*$F25 ) ) | AX25: =IF(ISBLANK(AT25), 0, VLOOKUP(AT25, 'Price Sheet'!$A$2:$B1015, 2, false)) -> 0 | AY25: =IF(OR(ISBLANK(AU25), ISBLANK(AX25)), "", AX25*AW25) | BB25: FALSE | BC25: =IF(ISBLANK(BA25), "", IF(BB25, BA25, BA25*$F25 ) ) | BD25: =IF(ISBLANK(AZ25), 0, VLOOKUP(AZ25, 'Price Sheet'!$A$2:$B1015, 2, false)) -> 0 | BE25: =IF(OR(ISBLANK(BA25), ISBLANK(BD25)), "", BD25*BC25) | BH25: FALSE | BI25: =IF(ISBLANK(BG25), "", IF(BH25, BG25, BG25*$F25 ) ) | BJ25: =IF(ISBLANK(BF25), 0, VLOOKUP(BF25, 'Price Sheet'!$A$2:$B1015, 2, false)) -> 0 | BK25: =IF(OR(ISBLANK(BG25), ISBLANK(BJ25)), "", BJ25*BI25) | BN25: FALSE | BO25: =IF(ISBLANK(BM25), "", IF(BN25, BM25, BM25*$F25 ) ) | BP25: =IF(ISBLANK(BL25), 0, VLOOKUP(BL25, 'Price Sheet'!$A$2:$B1015, 2, false)) -> 0 | BQ25: =IF(OR(ISBLANK(BM25), ISBLANK(BP25)), "", BP25*BO25)
A26: Outpost Netting | B26: =H26+U26+AA26+AG26+AM26+AS26+AY26+BE26+BK26+J26+BQ26 -> 43.72 | C26: Shipwright | D26: Small Shipyard | E26: =IF(ISBLANK(D26), "", VLOOKUP(D26,'Crafting Tables'!$A$2:$B1015, 2, false)) -> Basic | F26: =IFERROR(IF(E26 = "None", 1, VLOOKUP(C26,General!$A$5:$L$35, SWITCH(E26, "Basic", 8, "Advanced", 10, "Modern", 12), false)),"") -> 0.55 | G26: 180 | H26: =IFERROR(VLOOKUP(C26, General!$A$5:$L$35, 6, false) * G26 / 1000, 0) -> 7.2 | J26: =IFERROR(I26*VLOOKUP(D26,'Crafting Tables'!$1:$1000, 4, false)*F26,"") -> 0 | K26: TRUE | L26: Outpost Netting | M26: 1 | N26: =IF(ISBLANK(M26), "", $B26 / M26) -> 43.72 | P26: Hemp Mooring Rope | Q26: 6 | R26: FALSE | S26: =IF(ISBLANK(Q26), "", IF(R26, Q26, Q26*$F26 ) ) -> 3.3 | T26: =IF(ISBLANK(P26), 0, VLOOKUP(P26, 'Price Sheet'!$A$2:$B1015, 2, false)) -> 10 | U26: =IF(OR(ISBLANK(Q26), ISBLANK(T26)), "", T26*S26) -> 33 | V26: Hewn Log | W26: 8 | X26: FALSE | Y26: =IF(ISBLANK(W26), "", IF(X26, W26, W26*$F26 ) ) -> 4.4 | Z26: =IF(ISBLANK(V26), 0, VLOOKUP(V26, 'Price Sheet'!$A$2:$B1015, 2, false)) -> 0.8 | AA26: =IF(OR(ISBLANK(W26), ISBLANK(Z26)), "", Z26*Y26) -> 3.52 | AD26: FALSE | AE26: =IF(ISBLANK(AC26), "", IF(AD26, AC26, AC26*$F26 ) ) | AF26: =IF(ISBLANK(AB26), 0, VLOOKUP(AB26, 'Price Sheet'!$A$2:$B1015, 2, false)) -> 0 | AG26: =IF(OR(ISBLANK(AC26), ISBLANK(AF26)), "", AF26*AE26) | AJ26: FALSE | AK26: =IF(ISBLANK(AI26), "", IF(AJ26, AI26, AI26*$F26 ) ) | AL26: =IF(ISBLANK(AH26), 0, VLOOKUP(AH26, 'Price Sheet'!$A$2:$B1015, 2, false)) -> 0 | AM26: =IF(OR(ISBLANK(AI26), ISBLANK(AL26)), "", AL26*AK26) | AP26: FALSE | AQ26: =IF(ISBLANK(AO26), "", IF(AP26, AO26, AO26*$F26 ) ) | AR26: =IF(ISBLANK(AN26), 0, VLOOKUP(AN26, 'Price Sheet'!$A$2:$B1015, 2, false)) -> 0 | AS26: =IF(OR(ISBLANK(AO26), ISBLANK(AR26)), "", AR26*AQ26) | AV26: FALSE | AW26: =IF(ISBLANK(AU26), "", IF(AV26, AU26, AU26*$F26 ) ) | AX26: =IF(ISBLANK(AT26), 0, VLOOKUP(AT26, 'Price Sheet'!$A$2:$B1015, 2, false)) -> 0 | AY26: =IF(OR(ISBLANK(AU26), ISBLANK(AX26)), "", AX26*AW26) | BB26: FALSE | BC26: =IF(ISBLANK(BA26), "", IF(BB26, BA26, BA26*$F26 ) ) | BD26: =IF(ISBLANK(AZ26), 0, VLOOKUP(AZ26, 'Price Sheet'!$A$2:$B1015, 2, false)) -> 0 | BE26: =IF(OR(ISBLANK(BA26), ISBLANK(BD26)), "", BD26*BC26) | BH26: FALSE | BI26: =IF(ISBLANK(BG26), "", IF(BH26, BG26, BG26*$F26 ) ) | BJ26: =IF(ISBLANK(BF26), 0, VLOOKUP(BF26, 'Price Sheet'!$A$2:$B1015, 2, false)) -> 0 | BK26: =IF(OR(ISBLANK(BG26), ISBLANK(BJ26)), "", BJ26*BI26) | BN26: FALSE | BO26: =IF(ISBLANK(BM26), "", IF(BN26, BM26, BM26*$F26 ) ) | BP26: =IF(ISBLANK(BL26), 0, VLOOKUP(BL26, 'Price Sheet'!$A$2:$B1015, 2, false)) -> 0 | BQ26: =IF(OR(ISBLANK(BM26), ISBLANK(BP26)), "", BP26*BO26)
A27: Wooden Moorage Post | B27: =H27+U27+AA27+AG27+AM27+AS27+AY27+BE27+BK27+J27+BQ27 -> 30.67 | C27: Shipwright | D27: Small Shipyard | E27: =IF(ISBLANK(D27), "", VLOOKUP(D27,'Crafting Tables'!$A$2:$B1015, 2, false)) -> Basic | F27: =IFERROR(IF(E27 = "None", 1, VLOOKUP(C27,General!$A$5:$L$35, SWITCH(E27, "Basic", 8, "Advanced", 10, "Modern", 12), false)),"") -> 0.55 | G27: 60 | H27: =IFERROR(VLOOKUP(C27, General!$A$5:$L$35, 6, false) * G27 / 1000, 0) -> 2.4 | J27: =IFERROR(I27*VLOOKUP(D27,'Crafting Tables'!$1:$1000, 4, false)*F27,"") -> 0 | K27: TRUE | L27: Wooden Moorage Post | M27: 1 | N27: =IF(ISBLANK(M27), "", $B27 / M27) -> 30.67 | P27: Hewn Log | Q27: 12 | R27: FALSE | S27: =IF(ISBLANK(Q27), "", IF(R27, Q27, Q27*$F27 ) ) -> 6.6 | T27: =IF(ISBLANK(P27), 0, VLOOKUP(P27, 'Price Sheet'!$A$2:$B1015, 2, false)) -> 0.8 | U27: =IF(OR(ISBLANK(Q27), ISBLANK(T27)), "", T27*S27) -> 5.28 | V27: Board | W27: 4 | X27: FALSE | Y27: =IF(ISBLANK(W27), "", IF(X27, W27, W27*$F27 ) ) -> 2.2 | Z27: =IF(ISBLANK(V27), 0, VLOOKUP(V27, 'Price Sheet'!$A$2:$B1015, 2, false)) -> 0.45 | AA27: =IF(OR(ISBLANK(W27), ISBLANK(Z27)), "", Z27*Y27) -> 0.99 | AB27: Hemp Mooring Rope | AC27: 4 | AD27: FALSE | AE27: =IF(ISBLANK(AC27), "", IF(AD27, AC27, AC27*$F27 ) ) -> 2.2 | AF27: =IF(ISBLANK(AB27), 0, VLOOKUP(AB27, 'Price Sheet'!$A$2:$B1015, 2, false)) -> 10 | AG27: =IF(OR(ISBLANK(AC27), ISBLANK(AF27)), "", AF27*AE27) -> 22 | AJ27: FALSE | AK27: =IF(ISBLANK(AI27), "", IF(AJ27, AI27, AI27*$F27 ) ) | AL27: =IF(ISBLANK(AH27), 0, VLOOKUP(AH27, 'Price Sheet'!$A$2:$B1015, 2, false)) -> 0 | AM27: =IF(OR(ISBLANK(AI27), ISBLANK(AL27)), "", AL27*AK27) | AP27: FALSE | AQ27: =IF(ISBLANK(AO27), "", IF(AP27, AO27, AO27*$F27 ) ) | AR27: =IF(ISBLANK(AN27), 0, VLOOKUP(AN27, 'Price Sheet'!$A$2:$B1015, 2, false)) -> 0 | AS27: =IF(OR(ISBLANK(AO27), ISBLANK(AR27)), "", AR27*AQ27) | AV27: FALSE | AW27: =IF(ISBLANK(AU27), "", IF(AV27, AU27, AU27*$F27 ) ) | AX27: =IF(ISBLANK(AT27), 0, VLOOKUP(AT27, 'Price Sheet'!$A$2:$B1015, 2, false)) -> 0 | AY27: =IF(OR(ISBLANK(AU27), ISBLANK(AX27)), "", AX27*AW27) | BB27: FALSE | BC27: =IF(ISBLANK(BA27), "", IF(BB27, BA27, BA27*$F27 ) ) | BD27: =IF(ISBLANK(AZ27), 0, VLOOKUP(AZ27, 'Price Sheet'!$A$2:$B1015, 2, false)) -> 0 | BE27: =IF(OR(ISBLANK(BA27), ISBLANK(BD27)), "", BD27*BC27) | BH27: FALSE | BI27: =IF(ISBLANK(BG27), "", IF(BH27, BG27, BG27*$F27 ) ) | BJ27: =IF(ISBLANK(BF27), 0, VLOOKUP(BF27, 'Price Sheet'!$A$2:$B1015, 2, false)) -> 0 | BK27: =IF(OR(ISBLANK(BG27), ISBLANK(BJ27)), "", BJ27*BI27) | BN27: FALSE | BO27: =IF(ISBLANK(BM27), "", IF(BN27, BM27, BM27*$F27 ) ) | BP27: =IF(ISBLANK(BL27), 0, VLOOKUP(BL27, 'Price Sheet'!$A$2:$B1015, 2, false)) -> 0 | BQ27: =IF(OR(ISBLANK(BM27), ISBLANK(BP27)), "", BP27*BO27)
A28: Wooden Transport Ship | B28: =H28+U28+AA28+AG28+AM28+AS28+AY28+BE28+BK28+J28+BQ28 -> 0 | C28: Shipwright | E28: =IF(ISBLANK(D28), "", VLOOKUP(D28,'Crafting Tables'!$A$2:$B1015, 2, false)) | F28: =IFERROR(IF(E28 = "None", 1, VLOOKUP(C28,General!$A$5:$L$35, SWITCH(E28, "Basic", 8, "Advanced", 10, "Modern", 12), false)),"") | H28: =IFERROR(VLOOKUP(C28, General!$A$5:$L$35, 6, false) * G28 / 1000, 0) -> 0 | J28: =IFERROR(I28*VLOOKUP(D28,'Crafting Tables'!$1:$1000, 4, false)*F28,"") | K28: TRUE | L28: Wooden Transport Ship | M28: 1 | N28: =IF(ISBLANK(M28), "", $B28 / M28) -> 0 | R28: FALSE | S28: =IF(ISBLANK(Q28), "", IF(R28, Q28, Q28*$F28 ) ) | T28: =IF(ISBLANK(P28), 0, VLOOKUP(P28, 'Price Sheet'!$A$2:$B1015, 2, false)) -> 0 | U28: =IF(OR(ISBLANK(Q28), ISBLANK(T28)), "", T28*S28) | X28: FALSE | Y28: =IF(ISBLANK(W28), "", IF(X28, W28, W28*$F28 ) ) | Z28: =IF(ISBLANK(V28), 0, VLOOKUP(V28, 'Price Sheet'!$A$2:$B1015, 2, false)) -> 0 | AA28: =IF(OR(ISBLANK(W28), ISBLANK(Z28)), "", Z28*Y28) | AD28: FALSE | AE28: =IF(ISBLANK(AC28), "", IF(AD28, AC28, AC28*$F28 ) ) | AF28: =IF(ISBLANK(AB28), 0, VLOOKUP(AB28, 'Price Sheet'!$A$2:$B1015, 2, false)) -> 0 | AG28: =IF(OR(ISBLANK(AC28), ISBLANK(AF28)), "", AF28*AE28) | AJ28: FALSE | AK28: =IF(ISBLANK(AI28), "", IF(AJ28, AI28, AI28*$F28 ) ) | AL28: =IF(ISBLANK(AH28), 0, VLOOKUP(AH28, 'Price Sheet'!$A$2:$B1015, 2, false)) -> 0 | AM28: =IF(OR(ISBLANK(AI28), ISBLANK(AL28)), "", AL28*AK28) | AP28: FALSE | AQ28: =IF(ISBLANK(AO28), "", IF(AP28, AO28, AO28*$F28 ) ) | AR28: =IF(ISBLANK(AN28), 0, VLOOKUP(AN28, 'Price Sheet'!$A$2:$B1015, 2, false)) -> 0 | AS28: =IF(OR(ISBLANK(AO28), ISBLANK(AR28)), "", AR28*AQ28) | AV28: FALSE | AW28: =IF(ISBLANK(AU28), "", IF(AV28, AU28, AU28*$F28 ) ) | AX28: =IF(ISBLANK(AT28), 0, VLOOKUP(AT28, 'Price Sheet'!$A$2:$B1015, 2, false)) -> 0 | AY28: =IF(OR(ISBLANK(AU28), ISBLANK(AX28)), "", AX28*AW28) | BB28: FALSE | BC28: =IF(ISBLANK(BA28), "", IF(BB28, BA28, BA28*$F28 ) ) | BD28: =IF(ISBLANK(AZ28), 0, VLOOKUP(AZ28, 'Price Sheet'!$A$2:$B1015, 2, false)) -> 0 | BE28: =IF(OR(ISBLANK(BA28), ISBLANK(BD28)), "", BD28*BC28) | BH28: FALSE | BI28: =IF(ISBLANK(BG28), "", IF(BH28, BG28, BG28*$F28 ) ) | BJ28: =IF(ISBLANK(BF28), 0, VLOOKUP(BF28, 'Price Sheet'!$A$2:$B1015, 2, false)) -> 0 | BK28: =IF(OR(ISBLANK(BG28), ISBLANK(BJ28)), "", BJ28*BI28) | BN28: FALSE | BO28: =IF(ISBLANK(BM28), "", IF(BN28, BM28, BM28*$F28 ) ) | BP28: =IF(ISBLANK(BL28), 0, VLOOKUP(BL28, 'Price Sheet'!$A$2:$B1015, 2, false)) -> 0 | BQ28: =IF(OR(ISBLANK(BM28), ISBLANK(BP28)), "", BP28*BO28)
A29: Basic Upgrade 1 | B29: =H29+U29+AA29+AG29+AM29+AS29+AY29+BE29+BK29+J29+BQ29 -> 69 | C29: None | D29: Workbench | E29: =IF(ISBLANK(D29), "", VLOOKUP(D29,'Crafting Tables'!$A$2:$B1015, 2, false)) -> None | F29: =IFERROR(IF(E29 = "None", 1, VLOOKUP(C29,General!$A$5:$L$35, SWITCH(E29, "Basic", 8, "Advanced", 10, "Modern", 12), false)),"") -> 1 | G29: 200 | H29: =IFERROR(VLOOKUP(C29, General!$A$5:$L$35, 6, false) * G29 / 1000, 0) -> 8 | I29: 120 | J29: =IFERROR(I29*VLOOKUP(D29,'Crafting Tables'!$1:$1000, 4, false)*F29,"") -> 0 | K29: TRUE | L29: Basic Upgrade 1 | M29: 1 | N29: =IF(ISBLANK(M29), "", $B29 / M29) -> 69 | P29: Gathering Research Paper Basic | Q29: 1 | R29: TRUE | S29: =IF(ISBLANK(Q29), "", IF(R29, Q29, Q29*$F29 ) ) -> 1 | T29: =IF(ISBLANK(P29), 0, VLOOKUP(P29, 'Price Sheet'!$A$2:$B1015, 2, false)) -> 25 | U29: =IF(OR(ISBLANK(Q29), ISBLANK(T29)), "", T29*S29) -> 25 | V29: Geology Research Paper Basic | W29: 3 | X29: TRUE | Y29: =IF(ISBLANK(W29), "", IF(X29, W29, W29*$F29 ) ) -> 3 | Z29: =IF(ISBLANK(V29), 0, VLOOKUP(V29, 'Price Sheet'!$A$2:$B1015, 2, false)) -> 8 | AA29: =IF(OR(ISBLANK(W29), ISBLANK(Z29)), "", Z29*Y29) -> 24 | AB29: Dendrology Research Paper Basic | AC29: 1 | AD29: TRUE | AE29: =IF(ISBLANK(AC29), "", IF(AD29, AC29, AC29*$F29 ) ) -> 1 | AF29: =IF(ISBLANK(AB29), 0, VLOOKUP(AB29, 'Price Sheet'!$A$2:$B1015, 2, false)) -> 12 | AG29: =IF(OR(ISBLANK(AC29), ISBLANK(AF29)), "", AF29*AE29) -> 12 | AJ29: TRUE | AK29: =IF(ISBLANK(AI29), "", IF(AJ29, AI29, AI29*$F29 ) ) | AL29: =IF(ISBLANK(AH29), 0, VLOOKUP(AH29, 'Price Sheet'!$A$2:$B1015, 2, false)) -> 0 | AM29: =IF(OR(ISBLANK(AI29), ISBLANK(AL29)), "", AL29*AK29) | AP29: FALSE | AQ29: =IF(ISBLANK(AO29), "", IF(AP29, AO29, AO29*$F29 ) ) | AR29: =IF(ISBLANK(AN29), 0, VLOOKUP(AN29, 'Price Sheet'!$A$2:$B1015, 2, false)) -> 0 | AS29: =IF(OR(ISBLANK(AO29), ISBLANK(AR29)), "", AR29*AQ29) | AV29: FALSE | AW29: =IF(ISBLANK(AU29), "", IF(AV29, AU29, AU29*$F29 ) ) | AX29: =IF(ISBLANK(AT29), 0, VLOOKUP(AT29, 'Price Sheet'!$A$2:$B1015, 2, false)) -> 0 | AY29: =IF(OR(ISBLANK(AU29), ISBLANK(AX29)), "", AX29*AW29) | BB29: FALSE | BC29: =IF(ISBLANK(BA29), "", IF(BB29, BA29, BA29*$F29 ) ) | BD29: =IF(ISBLANK(AZ29), 0, VLOOKUP(AZ29, 'Price Sheet'!$A$2:$B1015, 2, false)) -> 0 | BE29: =IF(OR(ISBLANK(BA29), ISBLANK(BD29)), "", BD29*BC29) | BH29: FALSE | BI29: =IF(ISBLANK(BG29), "", IF(BH29, BG29, BG29*$F29 ) ) | BJ29: =IF(ISBLANK(BF29), 0, VLOOKUP(BF29, 'Price Sheet'!$A$2:$B1015, 2, false)) -> 0 | BK29: =IF(OR(ISBLANK(BG29), ISBLANK(BJ29)), "", BJ29*BI29) | BN29: FALSE | BO29: =IF(ISBLANK(BM29), "", IF(BN29, BM29, BM29*$F29 ) ) | BP29: =IF(ISBLANK(BL29), 0, VLOOKUP(BL29, 'Price Sheet'!$A$2:$B1015, 2, false)) -> 0 | BQ29: =IF(OR(ISBLANK(BM29), ISBLANK(BP29)), "", BP29*BO29)
A30: Basic Upgrade 2 | B30: =H30+U30+AA30+AG30+AM30+AS30+AY30+BE30+BK30+J30+BQ30 -> 127 | C30: None | D30: Workbench | E30: =IF(ISBLANK(D30), "", VLOOKUP(D30,'Crafting Tables'!$A$2:$B1015, 2, false)) -> None | F30: =IFERROR(IF(E30 = "None", 1, VLOOKUP(C30,General!$A$5:$L$35, SWITCH(E30, "Basic", 8, "Advanced", 10, "Modern", 12), false)),"") -> 1 | G30: 200 | H30: =IFERROR(VLOOKUP(C30, General!$A$5:$L$35, 6, false) * G30 / 1000, 0) -> 8 | I30: 240 | J30: =IFERROR(I30*VLOOKUP(D30,'Crafting Tables'!$1:$1000, 4, false)*F30,"") -> 0 | K30: TRUE | L30: Basic Upgrade 2 | M30: 1 | N30: =IF(ISBLANK(M30), "", $B30 / M30) -> 127 | P30: Basic Upgrade 1 | Q30: 1 | R30: TRUE | S30: =IF(ISBLANK(Q30), "", IF(R30, Q30, Q30*$F30 ) ) -> 1 | T30: =IF(ISBLANK(P30), 0, VLOOKUP(P30, 'Price Sheet'!$A$2:$B1015, 2, false)) -> 69 | U30: =IF(OR(ISBLANK(Q30), ISBLANK(T30)), "", T30*S30) -> 69 | V30: Culinary Research Paper Basic | W30: 1 | X30: TRUE | Y30: =IF(ISBLANK(W30), "", IF(X30, W30, W30*$F30 ) ) -> 1 | Z30: =IF(ISBLANK(V30), 0, VLOOKUP(V30, 'Price Sheet'!$A$2:$B1015, 2, false)) -> 25 | AA30: =IF(OR(ISBLANK(W30), ISBLANK(Z30)), "", Z30*Y30) -> 25 | AB30: Metallurgy Research Paper Basic | AC30: 1 | AD30: TRUE | AE30: =IF(ISBLANK(AC30), "", IF(AD30, AC30, AC30*$F30 ) ) -> 1 | AF30: =IF(ISBLANK(AB30), 0, VLOOKUP(AB30, 'Price Sheet'!$A$2:$B1015, 2, false)) -> 5 | AG30: =IF(OR(ISBLANK(AC30), ISBLANK(AF30)), "", AF30*AE30) -> 5 | AH30: Wooden Hull Planks | AI30: 4 | AJ30: TRUE | AK30: =IF(ISBLANK(AI30), "", IF(AJ30, AI30, AI30*$F30 ) ) -> 4 | AL30: =IF(ISBLANK(AH30), 0, VLOOKUP(AH30, 'Price Sheet'!$A$2:$B1015, 2, false)) -> 5 | AM30: =IF(OR(ISBLANK(AI30), ISBLANK(AL30)), "", AL30*AK30) -> 20 | AN30: Geology Research Paper Advanced | AP30: TRUE | AQ30: =IF(ISBLANK(AO30), "", IF(AP30, AO30, AO30*$F30 ) ) | AR30: =IF(ISBLANK(AN30), 0, VLOOKUP(AN30, 'Price Sheet'!$A$2:$B1015, 2, false)) -> 25.95 | AS30: =IF(OR(ISBLANK(AO30), ISBLANK(AR30)), "", AR30*AQ30) | AV30: FALSE | AW30: =IF(ISBLANK(AU30), "", IF(AV30, AU30, AU30*$F30 ) ) | AX30: =IF(ISBLANK(AT30), 0, VLOOKUP(AT30, 'Price Sheet'!$A$2:$B1015, 2, false)) -> 0 | AY30: =IF(OR(ISBLANK(AU30), ISBLANK(AX30)), "", AX30*AW30) | BB30: FALSE | BC30: =IF(ISBLANK(BA30), "", IF(BB30, BA30, BA30*$F30 ) ) | BD30: =IF(ISBLANK(AZ30), 0, VLOOKUP(AZ30, 'Price Sheet'!$A$2:$B1015, 2, false)) -> 0 | BE30: =IF(OR(ISBLANK(BA30), ISBLANK(BD30)), "", BD30*BC30) | BH30: FALSE | BI30: =IF(ISBLANK(BG30), "", IF(BH30, BG30, BG30*$F30 ) ) | BJ30: =IF(ISBLANK(BF30), 0, VLOOKUP(BF30, 'Price Sheet'!$A$2:$B1015, 2, false)) -> 0 | BK30: =IF(OR(ISBLANK(BG30), ISBLANK(BJ30)), "", BJ30*BI30) | BN30: FALSE | BO30: =IF(ISBLANK(BM30), "", IF(BN30, BM30, BM30*$F30 ) ) | BP30: =IF(ISBLANK(BL30), 0, VLOOKUP(BL30, 'Price Sheet'!$A$2:$B1015, 2, false)) -> 0 | BQ30: =IF(OR(ISBLANK(BM30), ISBLANK(BP30)), "", BP30*BO30)
A31: Basic Upgrade 3 | B31: =H31+U31+AA31+AG31+AM31+AS31+AY31+BE31+BK31+J31+BQ31 -> 465 | C31: None | D31: Workbench | E31: =IF(ISBLANK(D31), "", VLOOKUP(D31,'Crafting Tables'!$A$2:$B1015, 2, false)) -> None | F31: =IFERROR(IF(E31 = "None", 1, VLOOKUP(C31,General!$A$5:$L$35, SWITCH(E31, "Basic", 8, "Advanced", 10, "Modern", 12), false)),"") -> 1 | G31: 200 | H31: =IFERROR(VLOOKUP(C31, General!$A$5:$L$35, 6, false) * G31 / 1000, 0) -> 8 | I31: 360 | J31: =IFERROR(I31*VLOOKUP(D31,'Crafting Tables'!$1:$1000, 4, false)*F31,"") -> 0 | K31: TRUE | L31: Basic Upgrade 3 | M31: 1 | N31: =IF(ISBLANK(M31), "", $B31 / M31) -> 465 | P31: Basic Upgrade 2 | Q31: 1 | R31: TRUE | S31: =IF(ISBLANK(Q31), "", IF(R31, Q31, Q31*$F31 ) ) -> 1 | T31: =IF(ISBLANK(P31), 0, VLOOKUP(P31, 'Price Sheet'!$A$2:$B1015, 2, false)) -> 127 | U31: =IF(OR(ISBLANK(Q31), ISBLANK(T31)), "", T31*S31) -> 127 | V31: Metallurgy Research Paper Advanced | W31: 1 | X31: TRUE | Y31: =IF(ISBLANK(W31), "", IF(X31, W31, W31*$F31 ) ) -> 1 | Z31: =IF(ISBLANK(V31), 0, VLOOKUP(V31, 'Price Sheet'!$A$2:$B1015, 2, false)) -> 250 | AA31: =IF(OR(ISBLANK(W31), ISBLANK(Z31)), "", Z31*Y31) -> 250 | AB31: Dendrology Research Paper Advanced | AC31: 1 | AD31: TRUE | AE31: =IF(ISBLANK(AC31), "", IF(AD31, AC31, AC31*$F31 ) ) -> 1 | AF31: =IF(ISBLANK(AB31), 0, VLOOKUP(AB31, 'Price Sheet'!$A$2:$B1015, 2, false)) -> 30 | AG31: =IF(OR(ISBLANK(AC31), ISBLANK(AF31)), "", AF31*AE31) -> 30 | AH31: Agriculture Research Paper Advanced | AI31: 1 | AJ31: TRUE | AK31: =IF(ISBLANK(AI31), "", IF(AJ31, AI31, AI31*$F31 ) ) -> 1 | AL31: =IF(ISBLANK(AH31), 0, VLOOKUP(AH31, 'Price Sheet'!$A$2:$B1015, 2, false)) -> 50 | AM31: =IF(OR(ISBLANK(AI31), ISBLANK(AL31)), "", AL31*AK31) -> 50 | AP31: FALSE | AQ31: =IF(ISBLANK(AO31), "", IF(AP31, AO31, AO31*$F31 ) ) | AR31: =IF(ISBLANK(AN31), 0, VLOOKUP(AN31, 'Price Sheet'!$A$2:$B1015, 2, false)) -> 0 | AS31: =IF(OR(ISBLANK(AO31), ISBLANK(AR31)), "", AR31*AQ31) | AV31: FALSE | AW31: =IF(ISBLANK(AU31), "", IF(AV31, AU31, AU31*$F31 ) ) | AX31: =IF(ISBLANK(AT31), 0, VLOOKUP(AT31, 'Price Sheet'!$A$2:$B1015, 2, false)) -> 0 | AY31: =IF(OR(ISBLANK(AU31), ISBLANK(AX31)), "", AX31*AW31) | BB31: FALSE | BC31: =IF(ISBLANK(BA31), "", IF(BB31, BA31, BA31*$F31 ) ) | BD31: =IF(ISBLANK(AZ31), 0, VLOOKUP(AZ31, 'Price Sheet'!$A$2:$B1015, 2, false)) -> 0 | BE31: =IF(OR(ISBLANK(BA31), ISBLANK(BD31)), "", BD31*BC31) | BH31: FALSE | BI31: =IF(ISBLANK(BG31), "", IF(BH31, BG31, BG31*$F31 ) ) | BJ31: =IF(ISBLANK(BF31), 0, VLOOKUP(BF31, 'Price Sheet'!$A$2:$B1015, 2, false)) -> 0 | BK31: =IF(OR(ISBLANK(BG31), ISBLANK(BJ31)), "", BJ31*BI31) | BN31: FALSE | BO31: =IF(ISBLANK(BM31), "", IF(BN31, BM31, BM31*$F31 ) ) | BP31: =IF(ISBLANK(BL31), 0, VLOOKUP(BL31, 'Price Sheet'!$A$2:$B1015, 2, false)) -> 0 | BQ31: =IF(OR(ISBLANK(BM31), ISBLANK(BP31)), "", BP31*BO31)
A32: Basic Upgrade 4 | B32: =H32+U32+AA32+AG32+AM32+AS32+AY32+BE32+BK32+J32+BQ32 -> 655.55 | C32: None | D32: Workbench | E32: =IF(ISBLANK(D32), "", VLOOKUP(D32,'Crafting Tables'!$A$2:$B1015, 2, false)) -> None | F32: =IFERROR(IF(E32 = "None", 1, VLOOKUP(C32,General!$A$5:$L$35, SWITCH(E32, "Basic", 8, "Advanced", 10, "Modern", 12), false)),"") -> 1 | G32: 200 | H32: =IFERROR(VLOOKUP(C32, General!$A$5:$L$35, 6, false) * G32 / 1000, 0) -> 8 | I32: =8*60 -> 480 | J32: =IFERROR(I32*VLOOKUP(D32,'Crafting Tables'!$1:$1000, 4, false)*F32,"") -> 0 | K32: TRUE | L32: Basic Upgrade 4 | M32: 1 | N32: =IF(ISBLANK(M32), "", $B32 / M32) -> 655.55 | P32: Basic Upgrade 3 | Q32: 1 | R32: TRUE | S32: =IF(ISBLANK(Q32), "", IF(R32, Q32, Q32*$F32 ) ) -> 1 | T32: =IF(ISBLANK(P32), 0, VLOOKUP(P32, 'Price Sheet'!$A$2:$B1015, 2, false)) -> 465 | U32: =IF(OR(ISBLANK(Q32), ISBLANK(T32)), "", T32*S32) -> 465 | V32: Geology Research Paper Advanced | W32: 1 | X32: TRUE | Y32: =IF(ISBLANK(W32), "", IF(X32, W32, W32*$F32 ) ) -> 1 | Z32: =IF(ISBLANK(V32), 0, VLOOKUP(V32, 'Price Sheet'!$A$2:$B1015, 2, false)) -> 25.95 | AA32: =IF(OR(ISBLANK(W32), ISBLANK(Z32)), "", Z32*Y32) -> 25.95 | AB32: Engineering Research Paper Advanced | AC32: 1 | AD32: TRUE | AE32: =IF(ISBLANK(AC32), "", IF(AD32, AC32, AC32*$F32 ) ) -> 1 | AF32: =IF(ISBLANK(AB32), 0, VLOOKUP(AB32, 'Price Sheet'!$A$2:$B1015, 2, false)) -> 132.6 | AG32: =IF(OR(ISBLANK(AC32), ISBLANK(AF32)), "", AF32*AE32) -> 132.6 | AH32: Geology Research Paper Basic | AI32: 3 | AJ32: TRUE | AK32: =IF(ISBLANK(AI32), "", IF(AJ32, AI32, AI32*$F32 ) ) -> 3 | AL32: =IF(ISBLANK(AH32), 0, VLOOKUP(AH32, 'Price Sheet'!$A$2:$B1015, 2, false)) -> 8 | AM32: =IF(OR(ISBLANK(AI32), ISBLANK(AL32)), "", AL32*AK32) -> 24 | AP32: FALSE | AQ32: =IF(ISBLANK(AO32), "", IF(AP32, AO32, AO32*$F32 ) ) | AR32: =IF(ISBLANK(AN32), 0, VLOOKUP(AN32, 'Price Sheet'!$A$2:$B1015, 2, false)) -> 0 | AS32: =IF(OR(ISBLANK(AO32), ISBLANK(AR32)), "", AR32*AQ32) | AV32: FALSE | AW32: =IF(ISBLANK(AU32), "", IF(AV32, AU32, AU32*$F32 ) ) | AX32: =IF(ISBLANK(AT32), 0, VLOOKUP(AT32, 'Price Sheet'!$A$2:$B1015, 2, false)) -> 0 | AY32: =IF(OR(ISBLANK(AU32), ISBLANK(AX32)), "", AX32*AW32) | BB32: FALSE | BC32: =IF(ISBLANK(BA32), "", IF(BB32, BA32, BA32*$F32 ) ) | BD32: =IF(ISBLANK(AZ32), 0, VLOOKUP(AZ32, 'Price Sheet'!$A$2:$B1015, 2, false)) -> 0 | BE32: =IF(OR(ISBLANK(BA32), ISBLANK(BD32)), "", BD32*BC32) | BH32: FALSE | BI32: =IF(ISBLANK(BG32), "", IF(BH32, BG32, BG32*$F32 ) ) | BJ32: =IF(ISBLANK(BF32), 0, VLOOKUP(BF32, 'Price Sheet'!$A$2:$B1015, 2, false)) -> 0 | BK32: =IF(OR(ISBLANK(BG32), ISBLANK(BJ32)), "", BJ32*BI32) | BN32: FALSE | BO32: =IF(ISBLANK(BM32), "", IF(BN32, BM32, BM32*$F32 ) ) | BP32: =IF(ISBLANK(BL32), 0, VLOOKUP(BL32, 'Price Sheet'!$A$2:$B1015, 2, false)) -> 0 | BQ32: =IF(OR(ISBLANK(BM32), ISBLANK(BP32)), "", BP32*BO32)
A33: Charcoal | B33: =H33+U33+AA33+AG33+AM33+AS33+AY33+BE33+BK33+J33+BQ33 -> 4.635 | C33: Logging | D33: Kiln | E33: =IF(ISBLANK(D33), "", VLOOKUP(D33,'Crafting Tables'!$A$2:$B1015, 2, false)) -> Advanced | F33: =IFERROR(IF(E33 = "None", 1, VLOOKUP(C33,General!$A$5:$L$35, SWITCH(E33, "Basic", 8, "Advanced", 10, "Modern", 12), false)),"") -> 1 | G33: 25 | H33: =IFERROR(VLOOKUP(C33, General!$A$5:$L$35, 6, false) * G33 / 1000, 0) -> 1 | I33: 72 | J33: =IFERROR(I33*VLOOKUP(D33,'Crafting Tables'!$1:$1000, 4, false)*F33,"") -> 0.135 | K33: TRUE | L33: Charcoal | M33: 2 | N33: =IF(ISBLANK(M33), "", $B33 / M33) -> 2.3175 | P33: Wood (Tag) | Q33: 7 | R33: FALSE | S33: =IF(ISBLANK(Q33), "", IF(R33, Q33, Q33*$F33 ) ) -> 7 | T33: =IF(ISBLANK(P33), 0, VLOOKUP(P33, 'Price Sheet'!$A$2:$B1015, 2, false)) -> 0.5 | U33: =IF(OR(ISBLANK(Q33), ISBLANK(T33)), "", T33*S33) -> 3.5 | X33: FALSE | Y33: =IF(ISBLANK(W33), "", IF(X33, W33, W33*$F33 ) ) | Z33: =IF(ISBLANK(V33), 0, VLOOKUP(V33, 'Price Sheet'!$A$2:$B1015, 2, false)) -> 0 | AA33: =IF(OR(ISBLANK(W33), ISBLANK(Z33)), "", Z33*Y33) | AD33: FALSE | AE33: =IF(ISBLANK(AC33), "", IF(AD33, AC33, AC33*$F33 ) ) | AF33: =IF(ISBLANK(AB33), 0, VLOOKUP(AB33, 'Price Sheet'!$A$2:$B1015, 2, false)) -> 0 | AG33: =IF(OR(ISBLANK(AC33), ISBLANK(AF33)), "", AF33*AE33) | AJ33: FALSE | AK33: =IF(ISBLANK(AI33), "", IF(AJ33, AI33, AI33*$F33 ) ) | AL33: =IF(ISBLANK(AH33), 0, VLOOKUP(AH33, 'Price Sheet'!$A$2:$B1015, 2, false)) -> 0 | AM33: =IF(OR(ISBLANK(AI33), ISBLANK(AL33)), "", AL33*AK33) | AP33: FALSE | AQ33: =IF(ISBLANK(AO33), "", IF(AP33, AO33, AO33*$F33 ) ) | AR33: =IF(ISBLANK(AN33), 0, VLOOKUP(AN33, 'Price Sheet'!$A$2:$B1015, 2, false)) -> 0 | AS33: =IF(OR(ISBLANK(AO33), ISBLANK(AR33)), "", AR33*AQ33) | AV33: FALSE | AW33: =IF(ISBLANK(AU33), "", IF(AV33, AU33, AU33*$F33 ) ) | AX33: =IF(ISBLANK(AT33), 0, VLOOKUP(AT33, 'Price Sheet'!$A$2:$B1015, 2, false)) -> 0 | AY33: =IF(OR(ISBLANK(AU33), ISBLANK(AX33)), "", AX33*AW33) | BB33: FALSE | BC33: =IF(ISBLANK(BA33), "", IF(BB33, BA33, BA33*$F33 ) ) | BD33: =IF(ISBLANK(AZ33), 0, VLOOKUP(AZ33, 'Price Sheet'!$A$2:$B1015, 2, false)) -> 0 | BE33: =IF(OR(ISBLANK(BA33), ISBLANK(BD33)), "", BD33*BC33) | BH33: FALSE | BI33: =IF(ISBLANK(BG33), "", IF(BH33, BG33, BG33*$F33 ) ) | BJ33: =IF(ISBLANK(BF33), 0, VLOOKUP(BF33, 'Price Sheet'!$A$2:$B1015, 2, false)) -> 0 | BK33: =IF(OR(ISBLANK(BG33), ISBLANK(BJ33)), "", BJ33*BI33) | BN33: FALSE | BO33: =IF(ISBLANK(BM33), "", IF(BN33, BM33, BM33*$F33 ) ) | BP33: =IF(ISBLANK(BL33), 0, VLOOKUP(BL33, 'Price Sheet'!$A$2:$B1015, 2, false)) -> 0 | BQ33: =IF(OR(ISBLANK(BM33), ISBLANK(BP33)), "", BP33*BO33)
A34: Wet Brick | B34: =H34+U34+AA34+AG34+AM34+AS34+AY34+BE34+BK34+J34+BQ34 -> 14.80625 | C34: Pottery | D34: Kiln | E34: =IF(ISBLANK(D34), "", VLOOKUP(D34,'Crafting Tables'!$A$2:$B1015, 2, false)) -> Advanced | F34: =IFERROR(IF(E34 = "None", 1, VLOOKUP(C34,General!$A$5:$L$35, SWITCH(E34, "Basic", 8, "Advanced", 10, "Modern", 12), false)),"") -> 1 | G34: 100 | H34: =IFERROR(VLOOKUP(C34, General!$A$5:$L$35, 6, false) * G34 / 1000, 0) -> 4 | I34: 30 | J34: =IFERROR(I34*VLOOKUP(D34,'Crafting Tables'!$1:$1000, 4, false)*F34,"") -> 0.05625 | K34: TRUE | L34: Wet Brick | M34: 4 | N34: =IF(ISBLANK(M34), "", $B34 / M34) -> 3.7015625 | P34: Sand | Q34: 3 | R34: FALSE | S34: =IF(ISBLANK(Q34), "", IF(R34, Q34, Q34*$F34 ) ) -> 3 | T34: =IF(ISBLANK(P34), 0, VLOOKUP(P34, 'Price Sheet'!$A$2:$B1015, 2, false)) -> 0.25 | U34: =IF(OR(ISBLANK(Q34), ISBLANK(T34)), "", T34*S34) -> 0.75 | V34: Clay | W34: 12 | X34: FALSE | Y34: =IF(ISBLANK(W34), "", IF(X34, W34, W34*$F34 ) ) -> 12 | Z34: =IF(ISBLANK(V34), 0, VLOOKUP(V34, 'Price Sheet'!$A$2:$B1015, 2, false)) -> 0.5 | AA34: =IF(OR(ISBLANK(W34), ISBLANK(Z34)), "", Z34*Y34) -> 6 | AB34: Wooden Mold | AC34: 4 | AD34: FALSE | AE34: =IF(ISBLANK(AC34), "", IF(AD34, AC34, AC34*$F34 ) ) -> 4 | AF34: =IF(ISBLANK(AB34), 0, VLOOKUP(AB34, 'Price Sheet'!$A$2:$B1015, 2, false)) -> 1 | AG34: =IF(OR(ISBLANK(AC34), ISBLANK(AF34)), "", AF34*AE34) -> 4 | AJ34: FALSE | AK34: =IF(ISBLANK(AI34), "", IF(AJ34, AI34, AI34*$F34 ) ) | AL34: =IF(ISBLANK(AH34), 0, VLOOKUP(AH34, 'Price Sheet'!$A$2:$B1015, 2, false)) -> 0 | AM34: =IF(OR(ISBLANK(AI34), ISBLANK(AL34)), "", AL34*AK34) | AP34: FALSE | AQ34: =IF(ISBLANK(AO34), "", IF(AP34, AO34, AO34*$F34 ) ) | AR34: =IF(ISBLANK(AN34), 0, VLOOKUP(AN34, 'Price Sheet'!$A$2:$B1015, 2, false)) -> 0 | AS34: =IF(OR(ISBLANK(AO34), ISBLANK(AR34)), "", AR34*AQ34) | AV34: FALSE | AW34: =IF(ISBLANK(AU34), "", IF(AV34, AU34, AU34*$F34 ) ) | AX34: =IF(ISBLANK(AT34), 0, VLOOKUP(AT34, 'Price Sheet'!$A$2:$B1015, 2, false)) -> 0 | AY34: =IF(OR(ISBLANK(AU34), ISBLANK(AX34)), "", AX34*AW34) | BB34: FALSE | BC34: =IF(ISBLANK(BA34), "", IF(BB34, BA34, BA34*$F34 ) ) | BD34: =IF(ISBLANK(AZ34), 0, VLOOKUP(AZ34, 'Price Sheet'!$A$2:$B1015, 2, false)) -> 0 | BE34: =IF(OR(ISBLANK(BA34), ISBLANK(BD34)), "", BD34*BC34) | BH34: FALSE | BI34: =IF(ISBLANK(BG34), "", IF(BH34, BG34, BG34*$F34 ) ) | BJ34: =IF(ISBLANK(BF34), 0, VLOOKUP(BF34, 'Price Sheet'!$A$2:$B1015, 2, false)) -> 0 | BK34: =IF(OR(ISBLANK(BG34), ISBLANK(BJ34)), "", BJ34*BI34) | BN34: FALSE | BO34: =IF(ISBLANK(BM34), "", IF(BN34, BM34, BM34*$F34 ) ) | BP34: =IF(ISBLANK(BL34), 0, VLOOKUP(BL34, 'Price Sheet'!$A$2:$B1015, 2, false)) -> 0 | BQ34: =IF(OR(ISBLANK(BM34), ISBLANK(BP34)), "", BP34*BO34)
A35: Wet Brick (Shale) | B35: =H35+U35+AA35+AG35+AM35+AS35+AY35+BE35+BK35+J35+BQ35 -> 24.0125 | C35: Pottery | D35: Kiln | E35: =IF(ISBLANK(D35), "", VLOOKUP(D35,'Crafting Tables'!$A$2:$B1015, 2, false)) -> Advanced | F35: =IFERROR(IF(E35 = "None", 1, VLOOKUP(C35,General!$A$5:$L$35, SWITCH(E35, "Basic", 8, "Advanced", 10, "Modern", 12), false)),"") -> 1 | G35: 200 | H35: =IFERROR(VLOOKUP(C35, General!$A$5:$L$35, 6, false) * G35 / 1000, 0) -> 8 | I35: 60 | J35: =IFERROR(I35*VLOOKUP(D35,'Crafting Tables'!$1:$1000, 4, false)*F35,"") -> 0.1125 | K35: TRUE | L35: Wet Brick | M35: 8 | N35: =IF(ISBLANK(M35), "", $B35 / M35) -> 3.0015625 | P35: Sand | Q35: 6 | R35: FALSE | S35: =IF(ISBLANK(Q35), "", IF(R35, Q35, Q35*$F35 ) ) -> 6 | T35: =IF(ISBLANK(P35), 0, VLOOKUP(P35, 'Price Sheet'!$A$2:$B1015, 2, false)) -> 0.25 | U35: =IF(OR(ISBLANK(Q35), ISBLANK(T35)), "", T35*S35) -> 1.5 | V35: Clay | W35: 12 | X35: FALSE | Y35: =IF(ISBLANK(W35), "", IF(X35, W35, W35*$F35 ) ) -> 12 | Z35: =IF(ISBLANK(V35), 0, VLOOKUP(V35, 'Price Sheet'!$A$2:$B1015, 2, false)) -> 0.5 | AA35: =IF(OR(ISBLANK(W35), ISBLANK(Z35)), "", Z35*Y35) -> 6 | AB35: Wooden Mold | AC35: 8 | AD35: FALSE | AE35: =IF(ISBLANK(AC35), "", IF(AD35, AC35, AC35*$F35 ) ) -> 8 | AF35: =IF(ISBLANK(AB35), 0, VLOOKUP(AB35, 'Price Sheet'!$A$2:$B1015, 2, false)) -> 1 | AG35: =IF(OR(ISBLANK(AC35), ISBLANK(AF35)), "", AF35*AE35) -> 8 | AH35: Crushed Shale | AI35: 4 | AJ35: FALSE | AK35: =IF(ISBLANK(AI35), "", IF(AJ35, AI35, AI35*$F35 ) ) -> 4 | AL35: =IF(ISBLANK(AH35), 0, VLOOKUP(AH35, 'Price Sheet'!$A$2:$B1015, 2, false)) -> 0.1 | AM35: =IF(OR(ISBLANK(AI35), ISBLANK(AL35)), "", AL35*AK35) -> 0.4 | AP35: FALSE | AQ35: =IF(ISBLANK(AO35), "", IF(AP35, AO35, AO35*$F35 ) ) | AR35: =IF(ISBLANK(AN35), 0, VLOOKUP(AN35, 'Price Sheet'!$A$2:$B1015, 2, false)) -> 0 | AS35: =IF(OR(ISBLANK(AO35), ISBLANK(AR35)), "", AR35*AQ35) | AV35: FALSE | AW35: =IF(ISBLANK(AU35), "", IF(AV35, AU35, AU35*$F35 ) ) | AX35: =IF(ISBLANK(AT35), 0, VLOOKUP(AT35, 'Price Sheet'!$A$2:$B1015, 2, false)) -> 0 | AY35: =IF(OR(ISBLANK(AU35), ISBLANK(AX35)), "", AX35*AW35) | BB35: FALSE | BC35: =IF(ISBLANK(BA35), "", IF(BB35, BA35, BA35*$F35 ) ) | BD35: =IF(ISBLANK(AZ35), 0, VLOOKUP(AZ35, 'Price Sheet'!$A$2:$B1015, 2, false)) -> 0 | BE35: =IF(OR(ISBLANK(BA35), ISBLANK(BD35)), "", BD35*BC35) | BH35: FALSE | BI35: =IF(ISBLANK(BG35), "", IF(BH35, BG35, BG35*$F35 ) ) | BJ35: =IF(ISBLANK(BF35), 0, VLOOKUP(BF35, 'Price Sheet'!$A$2:$B1015, 2, false)) -> 0 | BK35: =IF(OR(ISBLANK(BG35), ISBLANK(BJ35)), "", BJ35*BI35) | BN35: FALSE | BO35: =IF(ISBLANK(BM35), "", IF(BN35, BM35, BM35*$F35 ) ) | BP35: =IF(ISBLANK(BL35), 0, VLOOKUP(BL35, 'Price Sheet'!$A$2:$B1015, 2, false)) -> 0 | BQ35: =IF(OR(ISBLANK(BM35), ISBLANK(BP35)), "", BP35*BO35)
A36: Brick | B36: =H36+U36+AA36+AG36+AM36+AS36+AY36+BE36+BK36+J36+BQ36 -> 4.6203125 | C36: Pottery | D36: Kiln | E36: =IF(ISBLANK(D36), "", VLOOKUP(D36,'Crafting Tables'!$A$2:$B1015, 2, false)) -> Advanced | F36: =IFERROR(IF(E36 = "None", 1, VLOOKUP(C36,General!$A$5:$L$35, SWITCH(E36, "Basic", 8, "Advanced", 10, "Modern", 12), false)),"") -> 1 | G36: 15 | H36: =IFERROR(VLOOKUP(C36, General!$A$5:$L$35, 6, false) * G36 / 1000, 0) -> 0.6 | I36: 10 | J36: =IFERROR(I36*VLOOKUP(D36,'Crafting Tables'!$1:$1000, 4, false)*F36,"") -> 0.01875 | K36: TRUE | L36: Brick | M36: 1 | N36: =IF(ISBLANK(M36), "", $B36 / M36) -> 4.6203125 | P36: Wet Brick | Q36: 1 | R36: FALSE | S36: =IF(ISBLANK(Q36), "", IF(R36, Q36, Q36*$F36 ) ) -> 1 | T36: =IF(ISBLANK(P36), 0, VLOOKUP(P36, 'Price Sheet'!$A$2:$B1015, 2, false)) -> 3.0015625 | U36: =IF(OR(ISBLANK(Q36), ISBLANK(T36)), "", T36*S36) -> 3.0015625 | V36: Mortar | W36: 4 | X36: FALSE | Y36: =IF(ISBLANK(W36), "", IF(X36, W36, W36*$F36 ) ) -> 4 | Z36: =IF(ISBLANK(V36), 0, VLOOKUP(V36, 'Price Sheet'!$A$2:$B1015, 2, false)) -> 0.25 | AA36: =IF(OR(ISBLANK(W36), ISBLANK(Z36)), "", Z36*Y36) -> 1 | AD36: FALSE | AE36: =IF(ISBLANK(AC36), "", IF(AD36, AC36, AC36*$F36 ) ) | AF36: =IF(ISBLANK(AB36), 0, VLOOKUP(AB36, 'Price Sheet'!$A$2:$B1015, 2, false)) -> 0 | AG36: =IF(OR(ISBLANK(AC36), ISBLANK(AF36)), "", AF36*AE36) | AJ36: FALSE | AK36: =IF(ISBLANK(AI36), "", IF(AJ36, AI36, AI36*$F36 ) ) | AL36: =IF(ISBLANK(AH36), 0, VLOOKUP(AH36, 'Price Sheet'!$A$2:$B1015, 2, false)) -> 0 | AM36: =IF(OR(ISBLANK(AI36), ISBLANK(AL36)), "", AL36*AK36) | AP36: FALSE | AQ36: =IF(ISBLANK(AO36), "", IF(AP36, AO36, AO36*$F36 ) ) | AR36: =IF(ISBLANK(AN36), 0, VLOOKUP(AN36, 'Price Sheet'!$A$2:$B1015, 2, false)) -> 0 | AS36: =IF(OR(ISBLANK(AO36), ISBLANK(AR36)), "", AR36*AQ36) | AV36: FALSE | AW36: =IF(ISBLANK(AU36), "", IF(AV36, AU36, AU36*$F36 ) ) | AX36: =IF(ISBLANK(AT36), 0, VLOOKUP(AT36, 'Price Sheet'!$A$2:$B1015, 2, false)) -> 0 | AY36: =IF(OR(ISBLANK(AU36), ISBLANK(AX36)), "", AX36*AW36) | BB36: FALSE | BC36: =IF(ISBLANK(BA36), "", IF(BB36, BA36, BA36*$F36 ) ) | BD36: =IF(ISBLANK(AZ36), 0, VLOOKUP(AZ36, 'Price Sheet'!$A$2:$B1015, 2, false)) -> 0 | BE36: =IF(OR(ISBLANK(BA36), ISBLANK(BD36)), "", BD36*BC36) | BH36: FALSE | BI36: =IF(ISBLANK(BG36), "", IF(BH36, BG36, BG36*$F36 ) ) | BJ36: =IF(ISBLANK(BF36), 0, VLOOKUP(BF36, 'Price Sheet'!$A$2:$B1015, 2, false)) -> 0 | BK36: =IF(OR(ISBLANK(BG36), ISBLANK(BJ36)), "", BJ36*BI36) | BN36: FALSE | BO36: =IF(ISBLANK(BM36), "", IF(BN36, BM36, BM36*$F36 ) ) | BP36: =IF(ISBLANK(BL36), 0, VLOOKUP(BL36, 'Price Sheet'!$A$2:$B1015, 2, false)) -> 0 | BQ36: =IF(OR(ISBLANK(BM36), ISBLANK(BP36)), "", BP36*BO36)
A37: Mortar (Campfire) | B37: =H37+U37+AA37+AG37+AM37+AS37+AY37+BE37+BK37+J37+BQ37 -> 0.85 | C37: None | D37: Campfire | E37: =IF(ISBLANK(D37), "", VLOOKUP(D37,'Crafting Tables'!$A$2:$B1015, 2, false)) -> Basic | F37: =IFERROR(IF(E37 = "None", 1, VLOOKUP(C37,General!$A$5:$L$35, SWITCH(E37, "Basic", 8, "Advanced", 10, "Modern", 12), false)),"") -> 0.55 | G37: 15 | H37: =IFERROR(VLOOKUP(C37, General!$A$5:$L$35, 6, false) * G37 / 1000, 0) -> 0.6 | J37: =IFERROR(I37*VLOOKUP(D37,'Crafting Tables'!$1:$1000, 4, false)*F37,"") -> 0 | K37: TRUE | L37: Mortar | M37: 1 | N37: =IF(ISBLANK(M37), "", $B37 / M37) -> 0.85 | P37: Fiber (Tag) | Q37: 5 | R37: TRUE | S37: =IF(ISBLANK(Q37), "", IF(R37, Q37, Q37*$F37 ) ) -> 5 | T37: =IF(ISBLANK(P37), 0, VLOOKUP(P37, 'Price Sheet'!$A$2:$B1015, 2, false)) -> 0.05 | U37: =IF(OR(ISBLANK(Q37), ISBLANK(T37)), "", T37*S37) -> 0.25 | X37: FALSE | Y37: =IF(ISBLANK(W37), "", IF(X37, W37, W37*$F37 ) ) | Z37: =IF(ISBLANK(V37), 0, VLOOKUP(V37, 'Price Sheet'!$A$2:$B1015, 2, false)) -> 0 | AA37: =IF(OR(ISBLANK(W37), ISBLANK(Z37)), "", Z37*Y37) | AD37: FALSE | AE37: =IF(ISBLANK(AC37), "", IF(AD37, AC37, AC37*$F37 ) ) | AF37: =IF(ISBLANK(AB37), 0, VLOOKUP(AB37, 'Price Sheet'!$A$2:$B1015, 2, false)) -> 0 | AG37: =IF(OR(ISBLANK(AC37), ISBLANK(AF37)), "", AF37*AE37) | AJ37: FALSE | AK37: =IF(ISBLANK(AI37), "", IF(AJ37, AI37, AI37*$F37 ) ) | AL37: =IF(ISBLANK(AH37), 0, VLOOKUP(AH37, 'Price Sheet'!$A$2:$B1015, 2, false)) -> 0 | AM37: =IF(OR(ISBLANK(AI37), ISBLANK(AL37)), "", AL37*AK37) | AP37: FALSE | AQ37: =IF(ISBLANK(AO37), "", IF(AP37, AO37, AO37*$F37 ) ) | AR37: =IF(ISBLANK(AN37), 0, VLOOKUP(AN37, 'Price Sheet'!$A$2:$B1015, 2, false)) -> 0 | AS37: =IF(OR(ISBLANK(AO37), ISBLANK(AR37)), "", AR37*AQ37) | AV37: FALSE | AW37: =IF(ISBLANK(AU37), "", IF(AV37, AU37, AU37*$F37 ) ) | AX37: =IF(ISBLANK(AT37), 0, VLOOKUP(AT37, 'Price Sheet'!$A$2:$B1015, 2, false)) -> 0 | AY37: =IF(OR(ISBLANK(AU37), ISBLANK(AX37)), "", AX37*AW37) | BB37: FALSE | BC37: =IF(ISBLANK(BA37), "", IF(BB37, BA37, BA37*$F37 ) ) | BD37: =IF(ISBLANK(AZ37), 0, VLOOKUP(AZ37, 'Price Sheet'!$A$2:$B1015, 2, false)) -> 0 | BE37: =IF(OR(ISBLANK(BA37), ISBLANK(BD37)), "", BD37*BC37) | BH37: FALSE | BI37: =IF(ISBLANK(BG37), "", IF(BH37, BG37, BG37*$F37 ) ) | BJ37: =IF(ISBLANK(BF37), 0, VLOOKUP(BF37, 'Price Sheet'!$A$2:$B1015, 2, false)) -> 0 | BK37: =IF(OR(ISBLANK(BG37), ISBLANK(BJ37)), "", BJ37*BI37) | BN37: FALSE | BO37: =IF(ISBLANK(BM37), "", IF(BN37, BM37, BM37*$F37 ) ) | BP37: =IF(ISBLANK(BL37), 0, VLOOKUP(BL37, 'Price Sheet'!$A$2:$B1015, 2, false)) -> 0 | BQ37: =IF(OR(ISBLANK(BM37), ISBLANK(BP37)), "", BP37*BO37)
A38: Mortar (Masonry) | B38: =H38+U38+AA38+AG38+AM38+AS38+AY38+BE38+BK38+J38+BQ38 -> 1.1375 | C38: Masonry | D38: Masonry Table | E38: =IF(ISBLANK(D38), "", VLOOKUP(D38,'Crafting Tables'!$A$2:$B1015, 2, false)) -> Basic | F38: =IFERROR(IF(E38 = "None", 1, VLOOKUP(C38,General!$A$5:$L$35, SWITCH(E38, "Basic", 8, "Advanced", 10, "Modern", 12), false)),"") -> 0.55 | G38: 25 | H38: =IFERROR(VLOOKUP(C38, General!$A$5:$L$35, 6, false) * G38 / 1000, 0) -> 1 | J38: =IFERROR(I38*VLOOKUP(D38,'Crafting Tables'!$1:$1000, 4, false)*F38,"") -> 0 | K38: TRUE | L38: Mortar | M38: 3 | N38: =IF(ISBLANK(M38), "", $B38 / M38) -> 0.37916667 | P38: Sand | Q38: 1 | R38: FALSE | S38: =IF(ISBLANK(Q38), "", IF(R38, Q38, Q38*$F38 ) ) -> 0.55 | T38: =IF(ISBLANK(P38), 0, VLOOKUP(P38, 'Price Sheet'!$A$2:$B1015, 2, false)) -> 0.25 | U38: =IF(OR(ISBLANK(Q38), ISBLANK(T38)), "", T38*S38) -> 0.1375 | X38: FALSE | Y38: =IF(ISBLANK(W38), "", IF(X38, W38, W38*$F38 ) ) | Z38: =IF(ISBLANK(V38), 0, VLOOKUP(V38, 'Price Sheet'!$A$2:$B1015, 2, false)) -> 0 | AA38: =IF(OR(ISBLANK(W38), ISBLANK(Z38)), "", Z38*Y38) | AD38: FALSE | AE38: =IF(ISBLANK(AC38), "", IF(AD38, AC38, AC38*$F38 ) ) | AF38: =IF(ISBLANK(AB38), 0, VLOOKUP(AB38, 'Price Sheet'!$A$2:$B1015, 2, false)) -> 0 | AG38: =IF(OR(ISBLANK(AC38), ISBLANK(AF38)), "", AF38*AE38) | AJ38: FALSE | AK38: =IF(ISBLANK(AI38), "", IF(AJ38, AI38, AI38*$F38 ) ) | AL38: =IF(ISBLANK(AH38), 0, VLOOKUP(AH38, 'Price Sheet'!$A$2:$B1015, 2, false)) -> 0 | AM38: =IF(OR(ISBLANK(AI38), ISBLANK(AL38)), "", AL38*AK38) | AP38: FALSE | AQ38: =IF(ISBLANK(AO38), "", IF(AP38, AO38, AO38*$F38 ) ) | AR38: =IF(ISBLANK(AN38), 0, VLOOKUP(AN38, 'Price Sheet'!$A$2:$B1015, 2, false)) -> 0 | AS38: =IF(OR(ISBLANK(AO38), ISBLANK(AR38)), "", AR38*AQ38) | AV38: FALSE | AW38: =IF(ISBLANK(AU38), "", IF(AV38, AU38, AU38*$F38 ) ) | AX38: =IF(ISBLANK(AT38), 0, VLOOKUP(AT38, 'Price Sheet'!$A$2:$B1015, 2, false)) -> 0 | AY38: =IF(OR(ISBLANK(AU38), ISBLANK(AX38)), "", AX38*AW38) | BB38: FALSE | BC38: =IF(ISBLANK(BA38), "", IF(BB38, BA38, BA38*$F38 ) ) | BD38: =IF(ISBLANK(AZ38), 0, VLOOKUP(AZ38, 'Price Sheet'!$A$2:$B1015, 2, false)) -> 0 | BE38: =IF(OR(ISBLANK(BA38), ISBLANK(BD38)), "", BD38*BC38) | BH38: FALSE | BI38: =IF(ISBLANK(BG38), "", IF(BH38, BG38, BG38*$F38 ) ) | BJ38: =IF(ISBLANK(BF38), 0, VLOOKUP(BF38, 'Price Sheet'!$A$2:$B1015, 2, false)) -> 0 | BK38: =IF(OR(ISBLANK(BG38), ISBLANK(BJ38)), "", BJ38*BI38) | BN38: FALSE | BO38: =IF(ISBLANK(BM38), "", IF(BN38, BM38, BM38*$F38 ) ) | BP38: =IF(ISBLANK(BL38), 0, VLOOKUP(BL38, 'Price Sheet'!$A$2:$B1015, 2, false)) -> 0 | BQ38: =IF(OR(ISBLANK(BM38), ISBLANK(BP38)), "", BP38*BO38)
A39: Advanced Upgrade 1 | B39: =H39+U39+AA39+AG39+AM39+AS39+AY39+BE39+BK39+J39+BQ39 -> 89.9375 | C39: Pottery | D39: Kiln | E39: =IF(ISBLANK(D39), "", VLOOKUP(D39,'Crafting Tables'!$A$2:$B1015, 2, false)) -> Advanced | F39: =IFERROR(IF(E39 = "None", 1, VLOOKUP(C39,General!$A$5:$L$35, SWITCH(E39, "Basic", 8, "Advanced", 10, "Modern", 12), false)),"") -> 1 | G39: 90 | H39: =IFERROR(VLOOKUP(C39, General!$A$5:$L$35, 6, false) * G39 / 1000, 0) -> 3.6 | I39: =60*3 -> 180 | J39: =IFERROR(I39*VLOOKUP(D39,'Crafting Tables'!$1:$1000, 4, false)*F39,"") -> 0.3375 | K39: TRUE | L39: Advanced Upgrade 1 | M39: 1 | N39: =IF(ISBLANK(M39), "", $B39 / M39) -> 89.9375 | P39: Clay | Q39: 12 | R39: FALSE | S39: =IF(ISBLANK(Q39), "", IF(R39, Q39, Q39*$F39 ) ) -> 12 | T39: =IF(ISBLANK(P39), 0, VLOOKUP(P39, 'Price Sheet'!$A$2:$B1015, 2, false)) -> 0.5 | U39: =IF(OR(ISBLANK(Q39), ISBLANK(T39)), "", T39*S39) -> 6 | V39: Brick | W39: 20 | X39: FALSE | Y39: =IF(ISBLANK(W39), "", IF(X39, W39, W39*$F39 ) ) -> 20 | Z39: =IF(ISBLANK(V39), 0, VLOOKUP(V39, 'Price Sheet'!$A$2:$B1015, 2, false)) -> 4 | AA39: =IF(OR(ISBLANK(W39), ISBLANK(Z39)), "", Z39*Y39) -> 80 | AD39: FALSE | AE39: =IF(ISBLANK(AC39), "", IF(AD39, AC39, AC39*$F39 ) ) | AF39: =IF(ISBLANK(AB39), 0, VLOOKUP(AB39, 'Price Sheet'!$A$2:$B1015, 2, false)) -> 0 | AG39: =IF(OR(ISBLANK(AC39), ISBLANK(AF39)), "", AF39*AE39) | AJ39: FALSE | AK39: =IF(ISBLANK(AI39), "", IF(AJ39, AI39, AI39*$F39 ) ) | AL39: =IF(ISBLANK(AH39), 0, VLOOKUP(AH39, 'Price Sheet'!$A$2:$B1015, 2, false)) -> 0 | AM39: =IF(OR(ISBLANK(AI39), ISBLANK(AL39)), "", AL39*AK39) | AP39: FALSE | AQ39: =IF(ISBLANK(AO39), "", IF(AP39, AO39, AO39*$F39 ) ) | AR39: =IF(ISBLANK(AN39), 0, VLOOKUP(AN39, 'Price Sheet'!$A$2:$B1015, 2, false)) -> 0 | AS39: =IF(OR(ISBLANK(AO39), ISBLANK(AR39)), "", AR39*AQ39) | AV39: FALSE | AW39: =IF(ISBLANK(AU39), "", IF(AV39, AU39, AU39*$F39 ) ) | AX39: =IF(ISBLANK(AT39), 0, VLOOKUP(AT39, 'Price Sheet'!$A$2:$B1015, 2, false)) -> 0 | AY39: =IF(OR(ISBLANK(AU39), ISBLANK(AX39)), "", AX39*AW39) | BB39: FALSE | BC39: =IF(ISBLANK(BA39), "", IF(BB39, BA39, BA39*$F39 ) ) | BD39: =IF(ISBLANK(AZ39), 0, VLOOKUP(AZ39, 'Price Sheet'!$A$2:$B1015, 2, false)) -> 0 | BE39: =IF(OR(ISBLANK(BA39), ISBLANK(BD39)), "", BD39*BC39) | BH39: FALSE | BI39: =IF(ISBLANK(BG39), "", IF(BH39, BG39, BG39*$F39 ) ) | BJ39: =IF(ISBLANK(BF39), 0, VLOOKUP(BF39, 'Price Sheet'!$A$2:$B1015, 2, false)) -> 0 | BK39: =IF(OR(ISBLANK(BG39), ISBLANK(BJ39)), "", BJ39*BI39) | BN39: FALSE | BO39: =IF(ISBLANK(BM39), "", IF(BN39, BM39, BM39*$F39 ) ) | BP39: =IF(ISBLANK(BL39), 0, VLOOKUP(BL39, 'Price Sheet'!$A$2:$B1015, 2, false)) -> 0 | BQ39: =IF(OR(ISBLANK(BM39), ISBLANK(BP39)), "", BP39*BO39)
A40: Recycle Hewn Log | B40: =H40+U40+AA40+AG40+AM40+AS40+AY40+BE40+BK40+J40+BQ40 -> 1.68 | C40: Logging | D40: Carpentry Table | E40: =IF(ISBLANK(D40), "", VLOOKUP(D40,'Crafting Tables'!$A$2:$B1015, 2, false)) -> Basic | F40: =IFERROR(IF(E40 = "None", 1, VLOOKUP(C40,General!$A$5:$L$35, SWITCH(E40, "Basic", 8, "Advanced", 10, "Modern", 12), false)),"") -> 0.55 | G40: 20 | H40: =IFERROR(VLOOKUP(C40, General!$A$5:$L$35, 6, false) * G40 / 1000, 0) -> 0.8 | J40: =IFERROR(I40*VLOOKUP(D40,'Crafting Tables'!$1:$1000, 4, false)*F40,"") -> 0 | K40: TRUE | L40: Wood Pulp | M40: 10 | N40: =IF(ISBLANK(M40), "", $B40 / M40) -> 0.168 | P40: Hewn Log | Q40: 2 | R40: FALSE | S40: =IF(ISBLANK(Q40), "", IF(R40, Q40, Q40*$F40 ) ) -> 1.1 | T40: =IF(ISBLANK(P40), 0, VLOOKUP(P40, 'Price Sheet'!$A$2:$B1015, 2, false)) -> 0.8 | U40: =IF(OR(ISBLANK(Q40), ISBLANK(T40)), "", T40*S40) -> 0.88 | X40: FALSE | Y40: =IF(ISBLANK(W40), "", IF(X40, W40, W40*$F40 ) ) | Z40: =IF(ISBLANK(V40), 0, VLOOKUP(V40, 'Price Sheet'!$A$2:$B1015, 2, false)) -> 0 | AA40: =IF(OR(ISBLANK(W40), ISBLANK(Z40)), "", Z40*Y40) | AD40: FALSE | AE40: =IF(ISBLANK(AC40), "", IF(AD40, AC40, AC40*$F40 ) ) | AF40: =IF(ISBLANK(AB40), 0, VLOOKUP(AB40, 'Price Sheet'!$A$2:$B1015, 2, false)) -> 0 | AG40: =IF(OR(ISBLANK(AC40), ISBLANK(AF40)), "", AF40*AE40) | AJ40: FALSE | AK40: =IF(ISBLANK(AI40), "", IF(AJ40, AI40, AI40*$F40 ) ) | AL40: =IF(ISBLANK(AH40), 0, VLOOKUP(AH40, 'Price Sheet'!$A$2:$B1015, 2, false)) -> 0 | AM40: =IF(OR(ISBLANK(AI40), ISBLANK(AL40)), "", AL40*AK40) | AP40: FALSE | AQ40: =IF(ISBLANK(AO40), "", IF(AP40, AO40, AO40*$F40 ) ) | AR40: =IF(ISBLANK(AN40), 0, VLOOKUP(AN40, 'Price Sheet'!$A$2:$B1015, 2, false)) -> 0 | AS40: =IF(OR(ISBLANK(AO40), ISBLANK(AR40)), "", AR40*AQ40) | AV40: FALSE | AW40: =IF(ISBLANK(AU40), "", IF(AV40, AU40, AU40*$F40 ) ) | AX40: =IF(ISBLANK(AT40), 0, VLOOKUP(AT40, 'Price Sheet'!$A$2:$B1015, 2, false)) -> 0 | AY40: =IF(OR(ISBLANK(AU40), ISBLANK(AX40)), "", AX40*AW40) | BB40: FALSE | BC40: =IF(ISBLANK(BA40), "", IF(BB40, BA40, BA40*$F40 ) ) | BD40: =IF(ISBLANK(AZ40), 0, VLOOKUP(AZ40, 'Price Sheet'!$A$2:$B1015, 2, false)) -> 0 | BE40: =IF(OR(ISBLANK(BA40), ISBLANK(BD40)), "", BD40*BC40) | BH40: FALSE | BI40: =IF(ISBLANK(BG40), "", IF(BH40, BG40, BG40*$F40 ) ) | BJ40: =IF(ISBLANK(BF40), 0, VLOOKUP(BF40, 'Price Sheet'!$A$2:$B1015, 2, false)) -> 0 | BK40: =IF(OR(ISBLANK(BG40), ISBLANK(BJ40)), "", BJ40*BI40) | BN40: FALSE | BO40: =IF(ISBLANK(BM40), "", IF(BN40, BM40, BM40*$F40 ) ) | BP40: =IF(ISBLANK(BL40), 0, VLOOKUP(BL40, 'Price Sheet'!$A$2:$B1015, 2, false)) -> 0 | BQ40: =IF(OR(ISBLANK(BM40), ISBLANK(BP40)), "", BP40*BO40)
A41: Glassworks | B41: =H41+U41+AA41+AG41+AM41+AS41+AY41+BE41+BK41+J41+BQ41 -> 111.5625 | C41: Pottery | D41: Kiln | E41: =IF(ISBLANK(D41), "", VLOOKUP(D41,'Crafting Tables'!$A$2:$B1015, 2, false)) -> Advanced | F41: =IFERROR(IF(E41 = "None", 1, VLOOKUP(C41,General!$A$5:$L$35, SWITCH(E41, "Basic", 8, "Advanced", 10, "Modern", 12), false)),"") -> 1 | G41: 150 | H41: =IFERROR(VLOOKUP(C41, General!$A$5:$L$35, 6, false) * G41 / 1000, 0) -> 6 | I41: =5*60 -> 300 | J41: =IFERROR(I41*VLOOKUP(D41,'Crafting Tables'!$1:$1000, 4, false)*F41,"") -> 0.5625 | K41: TRUE | L41: Glassworks | M41: 1 | N41: =IF(ISBLANK(M41), "", $B41 / M41) -> 111.5625 | P41: Brick | Q41: 16 | R41: FALSE | S41: =IF(ISBLANK(Q41), "", IF(R41, Q41, Q41*$F41 ) ) -> 16 | T41: =IF(ISBLANK(P41), 0, VLOOKUP(P41, 'Price Sheet'!$A$2:$B1015, 2, false)) -> 4 | U41: =IF(OR(ISBLANK(Q41), ISBLANK(T41)), "", T41*S41) -> 64 | V41: Board | W41: 20 | X41: FALSE | Y41: =IF(ISBLANK(W41), "", IF(X41, W41, W41*$F41 ) ) -> 20 | Z41: =IF(ISBLANK(V41), 0, VLOOKUP(V41, 'Price Sheet'!$A$2:$B1015, 2, false)) -> 0.45 | AA41: =IF(OR(ISBLANK(W41), ISBLANK(Z41)), "", Z41*Y41) -> 9 | AB41: Iron Bar | AC41: 8 | AD41: FALSE | AE41: =IF(ISBLANK(AC41), "", IF(AD41, AC41, AC41*$F41 ) ) -> 8 | AF41: =IF(ISBLANK(AB41), 0, VLOOKUP(AB41, 'Price Sheet'!$A$2:$B1015, 2, false)) -> 4 | AG41: =IF(OR(ISBLANK(AC41), ISBLANK(AF41)), "", AF41*AE41) -> 32 | AJ41: FALSE | AK41: =IF(ISBLANK(AI41), "", IF(AJ41, AI41, AI41*$F41 ) ) | AL41: =IF(ISBLANK(AH41), 0, VLOOKUP(AH41, 'Price Sheet'!$A$2:$B1015, 2, false)) -> 0 | AM41: =IF(OR(ISBLANK(AI41), ISBLANK(AL41)), "", AL41*AK41) | AP41: FALSE | AQ41: =IF(ISBLANK(AO41), "", IF(AP41, AO41, AO41*$F41 ) ) | AR41: =IF(ISBLANK(AN41), 0, VLOOKUP(AN41, 'Price Sheet'!$A$2:$B1015, 2, false)) -> 0 | AS41: =IF(OR(ISBLANK(AO41), ISBLANK(AR41)), "", AR41*AQ41) | AV41: FALSE | AW41: =IF(ISBLANK(AU41), "", IF(AV41, AU41, AU41*$F41 ) ) | AX41: =IF(ISBLANK(AT41), 0, VLOOKUP(AT41, 'Price Sheet'!$A$2:$B1015, 2, false)) -> 0 | AY41: =IF(OR(ISBLANK(AU41), ISBLANK(AX41)), "", AX41*AW41) | BB41: FALSE | BC41: =IF(ISBLANK(BA41), "", IF(BB41, BA41, BA41*$F41 ) ) | BD41: =IF(ISBLANK(AZ41), 0, VLOOKUP(AZ41, 'Price Sheet'!$A$2:$B1015, 2, false)) -> 0 | BE41: =IF(OR(ISBLANK(BA41), ISBLANK(BD41)), "", BD41*BC41) | BH41: FALSE | BI41: =IF(ISBLANK(BG41), "", IF(BH41, BG41, BG41*$F41 ) ) | BJ41: =IF(ISBLANK(BF41), 0, VLOOKUP(BF41, 'Price Sheet'!$A$2:$B1015, 2, false)) -> 0 | BK41: =IF(OR(ISBLANK(BG41), ISBLANK(BJ41)), "", BJ41*BI41) | BN41: FALSE | BO41: =IF(ISBLANK(BM41), "", IF(BN41, BM41, BM41*$F41 ) ) | BP41: =IF(ISBLANK(BL41), 0, VLOOKUP(BL41, 'Price Sheet'!$A$2:$B1015, 2, false)) -> 0 | BQ41: =IF(OR(ISBLANK(BM41), ISBLANK(BP41)), "", BP41*BO41)
A42: Bakery Oven | B42: =H42+U42+AA42+AG42+AM42+AS42+AY42+BE42+BK42+J42+BQ42 -> 128.1 | C42: Pottery | D42: Kiln | E42: =IF(ISBLANK(D42), "", VLOOKUP(D42,'Crafting Tables'!$A$2:$B1015, 2, false)) -> Advanced | F42: =IFERROR(IF(E42 = "None", 1, VLOOKUP(C42,General!$A$5:$L$35, SWITCH(E42, "Basic", 8, "Advanced", 10, "Modern", 12), false)),"") -> 1 | G42: 180 | H42: =IFERROR(VLOOKUP(C42, General!$A$5:$L$35, 6, false) * G42 / 1000, 0) -> 7.2 | I42: =8*60 -> 480 | J42: =IFERROR(I42*VLOOKUP(D42,'Crafting Tables'!$1:$1000, 4, false)*F42,"") -> 0.9 | K42: TRUE | L42: Bakery Oven | M42: 1 | N42: =IF(ISBLANK(M42), "", $B42 / M42) -> 128.1 | P42: Iron Bar | Q42: 10 | R42: FALSE | S42: =IF(ISBLANK(Q42), "", IF(R42, Q42, Q42*$F42 ) ) -> 10 | T42: =IF(ISBLANK(P42), 0, VLOOKUP(P42, 'Price Sheet'!$A$2:$B1015, 2, false)) -> 4 | U42: =IF(OR(ISBLANK(Q42), ISBLANK(T42)), "", T42*S42) -> 40 | V42: Brick | W42: 20 | X42: FALSE | Y42: =IF(ISBLANK(W42), "", IF(X42, W42, W42*$F42 ) ) -> 20 | Z42: =IF(ISBLANK(V42), 0, VLOOKUP(V42, 'Price Sheet'!$A$2:$B1015, 2, false)) -> 4 | AA42: =IF(OR(ISBLANK(W42), ISBLANK(Z42)), "", Z42*Y42) -> 80 | AD42: FALSE | AE42: =IF(ISBLANK(AC42), "", IF(AD42, AC42, AC42*$F42 ) ) | AF42: =IF(ISBLANK(AB42), 0, VLOOKUP(AB42, 'Price Sheet'!$A$2:$B1015, 2, false)) -> 0 | AG42: =IF(OR(ISBLANK(AC42), ISBLANK(AF42)), "", AF42*AE42) | AJ42: FALSE | AK42: =IF(ISBLANK(AI42), "", IF(AJ42, AI42, AI42*$F42 ) ) | AL42: =IF(ISBLANK(AH42), 0, VLOOKUP(AH42, 'Price Sheet'!$A$2:$B1015, 2, false)) -> 0 | AM42: =IF(OR(ISBLANK(AI42), ISBLANK(AL42)), "", AL42*AK42) | AP42: FALSE | AQ42: =IF(ISBLANK(AO42), "", IF(AP42, AO42, AO42*$F42 ) ) | AR42: =IF(ISBLANK(AN42), 0, VLOOKUP(AN42, 'Price Sheet'!$A$2:$B1015, 2, false)) -> 0 | AS42: =IF(OR(ISBLANK(AO42), ISBLANK(AR42)), "", AR42*AQ42) | AV42: FALSE | AW42: =IF(ISBLANK(AU42), "", IF(AV42, AU42, AU42*$F42 ) ) | AX42: =IF(ISBLANK(AT42), 0, VLOOKUP(AT42, 'Price Sheet'!$A$2:$B1015, 2, false)) -> 0 | AY42: =IF(OR(ISBLANK(AU42), ISBLANK(AX42)), "", AX42*AW42) | BB42: FALSE | BC42: =IF(ISBLANK(BA42), "", IF(BB42, BA42, BA42*$F42 ) ) | BD42: =IF(ISBLANK(AZ42), 0, VLOOKUP(AZ42, 'Price Sheet'!$A$2:$B1015, 2, false)) -> 0 | BE42: =IF(OR(ISBLANK(BA42), ISBLANK(BD42)), "", BD42*BC42) | BH42: FALSE | BI42: =IF(ISBLANK(BG42), "", IF(BH42, BG42, BG42*$F42 ) ) | BJ42: =IF(ISBLANK(BF42), 0, VLOOKUP(BF42, 'Price Sheet'!$A$2:$B1015, 2, false)) -> 0 | BK42: =IF(OR(ISBLANK(BG42), ISBLANK(BJ42)), "", BJ42*BI42) | BN42: FALSE | BO42: =IF(ISBLANK(BM42), "", IF(BN42, BM42, BM42*$F42 ) ) | BP42: =IF(ISBLANK(BL42), 0, VLOOKUP(BL42, 'Price Sheet'!$A$2:$B1015, 2, false)) -> 0 | BQ42: =IF(OR(ISBLANK(BM42), ISBLANK(BP42)), "", BP42*BO42)
A43: Small Sink | B43: =H43+U43+AA43+AG43+AM43+AS43+AY43+BE43+BK43+J43+BQ43 -> 60.025 | C43: Pottery | D43: Kiln | E43: =IF(ISBLANK(D43), "", VLOOKUP(D43,'Crafting Tables'!$A$2:$B1015, 2, false)) -> Advanced | F43: =IFERROR(IF(E43 = "None", 1, VLOOKUP(C43,General!$A$5:$L$35, SWITCH(E43, "Basic", 8, "Advanced", 10, "Modern", 12), false)),"") -> 1 | G43: 120 | H43: =IFERROR(VLOOKUP(C43, General!$A$5:$L$35, 6, false) * G43 / 1000, 0) -> 4.8 | I43: 120 | J43: =IFERROR(I43*VLOOKUP(D43,'Crafting Tables'!$1:$1000, 4, false)*F43,"") -> 0.225 | K43: TRUE | L43: Small Sink | M43: 1 | N43: =IF(ISBLANK(M43), "", $B43 / M43) -> 60.025 | P43: Clay | Q43: 30 | R43: FALSE | S43: =IF(ISBLANK(Q43), "", IF(R43, Q43, Q43*$F43 ) ) -> 30 | T43: =IF(ISBLANK(P43), 0, VLOOKUP(P43, 'Price Sheet'!$A$2:$B1015, 2, false)) -> 0.5 | U43: =IF(OR(ISBLANK(Q43), ISBLANK(T43)), "", T43*S43) -> 15 | V43: Iron Bar | W43: 10 | X43: FALSE | Y43: =IF(ISBLANK(W43), "", IF(X43, W43, W43*$F43 ) ) -> 10 | Z43: =IF(ISBLANK(V43), 0, VLOOKUP(V43, 'Price Sheet'!$A$2:$B1015, 2, false)) -> 4 | AA43: =IF(OR(ISBLANK(W43), ISBLANK(Z43)), "", Z43*Y43) -> 40 | AD43: FALSE | AE43: =IF(ISBLANK(AC43), "", IF(AD43, AC43, AC43*$F43 ) ) | AF43: =IF(ISBLANK(AB43), 0, VLOOKUP(AB43, 'Price Sheet'!$A$2:$B1015, 2, false)) -> 0 | AG43: =IF(OR(ISBLANK(AC43), ISBLANK(AF43)), "", AF43*AE43) | AJ43: FALSE | AK43: =IF(ISBLANK(AI43), "", IF(AJ43, AI43, AI43*$F43 ) ) | AL43: =IF(ISBLANK(AH43), 0, VLOOKUP(AH43, 'Price Sheet'!$A$2:$B1015, 2, false)) -> 0 | AM43: =IF(OR(ISBLANK(AI43), ISBLANK(AL43)), "", AL43*AK43) | AP43: FALSE | AQ43: =IF(ISBLANK(AO43), "", IF(AP43, AO43, AO43*$F43 ) ) | AR43: =IF(ISBLANK(AN43), 0, VLOOKUP(AN43, 'Price Sheet'!$A$2:$B1015, 2, false)) -> 0 | AS43: =IF(OR(ISBLANK(AO43), ISBLANK(AR43)), "", AR43*AQ43) | AV43: FALSE | AW43: =IF(ISBLANK(AU43), "", IF(AV43, AU43, AU43*$F43 ) ) | AX43: =IF(ISBLANK(AT43), 0, VLOOKUP(AT43, 'Price Sheet'!$A$2:$B1015, 2, false)) -> 0 | AY43: =IF(OR(ISBLANK(AU43), ISBLANK(AX43)), "", AX43*AW43) | BB43: FALSE | BC43: =IF(ISBLANK(BA43), "", IF(BB43, BA43, BA43*$F43 ) ) | BD43: =IF(ISBLANK(AZ43), 0, VLOOKUP(AZ43, 'Price Sheet'!$A$2:$B1015, 2, false)) -> 0 | BE43: =IF(OR(ISBLANK(BA43), ISBLANK(BD43)), "", BD43*BC43) | BH43: FALSE | BI43: =IF(ISBLANK(BG43), "", IF(BH43, BG43, BG43*$F43 ) ) | BJ43: =IF(ISBLANK(BF43), 0, VLOOKUP(BF43, 'Price Sheet'!$A$2:$B1015, 2, false)) -> 0 | BK43: =IF(OR(ISBLANK(BG43), ISBLANK(BJ43)), "", BJ43*BI43) | BN43: FALSE | BO43: =IF(ISBLANK(BM43), "", IF(BN43, BM43, BM43*$F43 ) ) | BP43: =IF(ISBLANK(BL43), 0, VLOOKUP(BL43, 'Price Sheet'!$A$2:$B1015, 2, false)) -> 0 | BQ43: =IF(OR(ISBLANK(BM43), ISBLANK(BP43)), "", BP43*BO43)
A44: Toilet | B44: =H44+U44+AA44+AG44+AM44+AS44+AY44+BE44+BK44+J44+BQ44 -> 60.025 | C44: Pottery | D44: Kiln | E44: =IF(ISBLANK(D44), "", VLOOKUP(D44,'Crafting Tables'!$A$2:$B1015, 2, false)) -> Advanced | F44: =IFERROR(IF(E44 = "None", 1, VLOOKUP(C44,General!$A$5:$L$35, SWITCH(E44, "Basic", 8, "Advanced", 10, "Modern", 12), false)),"") -> 1 | G44: 120 | H44: =IFERROR(VLOOKUP(C44, General!$A$5:$L$35, 6, false) * G44 / 1000, 0) -> 4.8 | I44: 120 | J44: =IFERROR(I44*VLOOKUP(D44,'Crafting Tables'!$1:$1000, 4, false)*F44,"") -> 0.225 | K44: TRUE | L44: Toilet | M44: 1 | N44: =IF(ISBLANK(M44), "", $B44 / M44) -> 60.025 | P44: Clay | Q44: 30 | R44: FALSE | S44: =IF(ISBLANK(Q44), "", IF(R44, Q44, Q44*$F44 ) ) -> 30 | T44: =IF(ISBLANK(P44), 0, VLOOKUP(P44, 'Price Sheet'!$A$2:$B1015, 2, false)) -> 0.5 | U44: =IF(OR(ISBLANK(Q44), ISBLANK(T44)), "", T44*S44) -> 15 | V44: Iron Bar | W44: 10 | X44: FALSE | Y44: =IF(ISBLANK(W44), "", IF(X44, W44, W44*$F44 ) ) -> 10 | Z44: =IF(ISBLANK(V44), 0, VLOOKUP(V44, 'Price Sheet'!$A$2:$B1015, 2, false)) -> 4 | AA44: =IF(OR(ISBLANK(W44), ISBLANK(Z44)), "", Z44*Y44) -> 40 | AD44: FALSE | AE44: =IF(ISBLANK(AC44), "", IF(AD44, AC44, AC44*$F44 ) ) | AF44: =IF(ISBLANK(AB44), 0, VLOOKUP(AB44, 'Price Sheet'!$A$2:$B1015, 2, false)) -> 0 | AG44: =IF(OR(ISBLANK(AC44), ISBLANK(AF44)), "", AF44*AE44) | AJ44: FALSE | AK44: =IF(ISBLANK(AI44), "", IF(AJ44, AI44, AI44*$F44 ) ) | AL44: =IF(ISBLANK(AH44), 0, VLOOKUP(AH44, 'Price Sheet'!$A$2:$B1015, 2, false)) -> 0 | AM44: =IF(OR(ISBLANK(AI44), ISBLANK(AL44)), "", AL44*AK44) | AP44: FALSE | AQ44: =IF(ISBLANK(AO44), "", IF(AP44, AO44, AO44*$F44 ) ) | AR44: =IF(ISBLANK(AN44), 0, VLOOKUP(AN44, 'Price Sheet'!$A$2:$B1015, 2, false)) -> 0 | AS44: =IF(OR(ISBLANK(AO44), ISBLANK(AR44)), "", AR44*AQ44) | AV44: FALSE | AW44: =IF(ISBLANK(AU44), "", IF(AV44, AU44, AU44*$F44 ) ) | AX44: =IF(ISBLANK(AT44), 0, VLOOKUP(AT44, 'Price Sheet'!$A$2:$B1015, 2, false)) -> 0 | AY44: =IF(OR(ISBLANK(AU44), ISBLANK(AX44)), "", AX44*AW44) | BB44: FALSE | BC44: =IF(ISBLANK(BA44), "", IF(BB44, BA44, BA44*$F44 ) ) | BD44: =IF(ISBLANK(AZ44), 0, VLOOKUP(AZ44, 'Price Sheet'!$A$2:$B1015, 2, false)) -> 0 | BE44: =IF(OR(ISBLANK(BA44), ISBLANK(BD44)), "", BD44*BC44) | BH44: FALSE | BI44: =IF(ISBLANK(BG44), "", IF(BH44, BG44, BG44*$F44 ) ) | BJ44: =IF(ISBLANK(BF44), 0, VLOOKUP(BF44, 'Price Sheet'!$A$2:$B1015, 2, false)) -> 0 | BK44: =IF(OR(ISBLANK(BG44), ISBLANK(BJ44)), "", BJ44*BI44) | BN44: FALSE | BO44: =IF(ISBLANK(BM44), "", IF(BN44, BM44, BM44*$F44 ) ) | BP44: =IF(ISBLANK(BL44), 0, VLOOKUP(BL44, 'Price Sheet'!$A$2:$B1015, 2, false)) -> 0 | BQ44: =IF(OR(ISBLANK(BM44), ISBLANK(BP44)), "", BP44*BO44)
A45: Round/Square Pot | B45: =H45+U45+AA45+AG45+AM45+AS45+AY45+BE45+BK45+J45+BQ45 -> 4.025 | C45: Pottery | D45: Kiln | E45: =IF(ISBLANK(D45), "", VLOOKUP(D45,'Crafting Tables'!$A$2:$B1015, 2, false)) -> Advanced | F45: =IFERROR(IF(E45 = "None", 1, VLOOKUP(C45,General!$A$5:$L$35, SWITCH(E45, "Basic", 8, "Advanced", 10, "Modern", 12), false)),"") -> 1 | G45: 45 | H45: =IFERROR(VLOOKUP(C45, General!$A$5:$L$35, 6, false) * G45 / 1000, 0) -> 1.8 | I45: 120 | J45: =IFERROR(I45*VLOOKUP(D45,'Crafting Tables'!$1:$1000, 4, false)*F45,"") -> 0.225 | K45: TRUE | L45: Round Pot | M45: 1 | N45: =IF(ISBLANK(M45), "", $B45 / M45) -> 4.025 | P45: Clay | Q45: 4 | R45: FALSE | S45: =IF(ISBLANK(Q45), "", IF(R45, Q45, Q45*$F45 ) ) -> 4 | T45: =IF(ISBLANK(P45), 0, VLOOKUP(P45, 'Price Sheet'!$A$2:$B1015, 2, false)) -> 0.5 | U45: =IF(OR(ISBLANK(Q45), ISBLANK(T45)), "", T45*S45) -> 2 | X45: FALSE | Y45: =IF(ISBLANK(W45), "", IF(X45, W45, W45*$F45 ) ) | Z45: =IF(ISBLANK(V45), 0, VLOOKUP(V45, 'Price Sheet'!$A$2:$B1015, 2, false)) -> 0 | AA45: =IF(OR(ISBLANK(W45), ISBLANK(Z45)), "", Z45*Y45) | AD45: FALSE | AE45: =IF(ISBLANK(AC45), "", IF(AD45, AC45, AC45*$F45 ) ) | AF45: =IF(ISBLANK(AB45), 0, VLOOKUP(AB45, 'Price Sheet'!$A$2:$B1015, 2, false)) -> 0 | AG45: =IF(OR(ISBLANK(AC45), ISBLANK(AF45)), "", AF45*AE45) | AJ45: FALSE | AK45: =IF(ISBLANK(AI45), "", IF(AJ45, AI45, AI45*$F45 ) ) | AL45: =IF(ISBLANK(AH45), 0, VLOOKUP(AH45, 'Price Sheet'!$A$2:$B1015, 2, false)) -> 0 | AM45: =IF(OR(ISBLANK(AI45), ISBLANK(AL45)), "", AL45*AK45) | AP45: FALSE | AQ45: =IF(ISBLANK(AO45), "", IF(AP45, AO45, AO45*$F45 ) ) | AR45: =IF(ISBLANK(AN45), 0, VLOOKUP(AN45, 'Price Sheet'!$A$2:$B1015, 2, false)) -> 0 | AS45: =IF(OR(ISBLANK(AO45), ISBLANK(AR45)), "", AR45*AQ45) | AV45: FALSE | AW45: =IF(ISBLANK(AU45), "", IF(AV45, AU45, AU45*$F45 ) ) | AX45: =IF(ISBLANK(AT45), 0, VLOOKUP(AT45, 'Price Sheet'!$A$2:$B1015, 2, false)) -> 0 | AY45: =IF(OR(ISBLANK(AU45), ISBLANK(AX45)), "", AX45*AW45) | BB45: FALSE | BC45: =IF(ISBLANK(BA45), "", IF(BB45, BA45, BA45*$F45 ) ) | BD45: =IF(ISBLANK(AZ45), 0, VLOOKUP(AZ45, 'Price Sheet'!$A$2:$B1015, 2, false)) -> 0 | BE45: =IF(OR(ISBLANK(BA45), ISBLANK(BD45)), "", BD45*BC45) | BH45: FALSE | BI45: =IF(ISBLANK(BG45), "", IF(BH45, BG45, BG45*$F45 ) ) | BJ45: =IF(ISBLANK(BF45), 0, VLOOKUP(BF45, 'Price Sheet'!$A$2:$B1015, 2, false)) -> 0 | BK45: =IF(OR(ISBLANK(BG45), ISBLANK(BJ45)), "", BJ45*BI45) | BN45: FALSE | BO45: =IF(ISBLANK(BM45), "", IF(BN45, BM45, BM45*$F45 ) ) | BP45: =IF(ISBLANK(BL45), 0, VLOOKUP(BL45, 'Price Sheet'!$A$2:$B1015, 2, false)) -> 0 | BQ45: =IF(OR(ISBLANK(BM45), ISBLANK(BP45)), "", BP45*BO45)
A46: Brick Fireplace | B46: =H46+U46+AA46+AG46+AM46+AS46+AY46+BE46+BK46+J46+BQ46 -> 292.5625 | C46: Pottery | D46: Kiln | E46: =IF(ISBLANK(D46), "", VLOOKUP(D46,'Crafting Tables'!$A$2:$B1015, 2, false)) -> Advanced | F46: =IFERROR(IF(E46 = "None", 1, VLOOKUP(C46,General!$A$5:$L$35, SWITCH(E46, "Basic", 8, "Advanced", 10, "Modern", 12), false)),"") -> 1 | G46: 300 | H46: =IFERROR(VLOOKUP(C46, General!$A$5:$L$35, 6, false) * G46 / 1000, 0) -> 12 | I46: 300 | J46: =IFERROR(I46*VLOOKUP(D46,'Crafting Tables'!$1:$1000, 4, false)*F46,"") -> 0.5625 | K46: TRUE | L46: Brick Fireplace | M46: 1 | N46: =IF(ISBLANK(M46), "", $B46 / M46) -> 292.5625 | P46: Brick | Q46: 50 | R46: FALSE | S46: =IF(ISBLANK(Q46), "", IF(R46, Q46, Q46*$F46 ) ) -> 50 | T46: =IF(ISBLANK(P46), 0, VLOOKUP(P46, 'Price Sheet'!$A$2:$B1015, 2, false)) -> 4 | U46: =IF(OR(ISBLANK(Q46), ISBLANK(T46)), "", T46*S46) -> 200 | V46: Iron Bar | W46: 20 | X46: FALSE | Y46: =IF(ISBLANK(W46), "", IF(X46, W46, W46*$F46 ) ) -> 20 | Z46: =IF(ISBLANK(V46), 0, VLOOKUP(V46, 'Price Sheet'!$A$2:$B1015, 2, false)) -> 4 | AA46: =IF(OR(ISBLANK(W46), ISBLANK(Z46)), "", Z46*Y46) -> 80 | AD46: FALSE | AE46: =IF(ISBLANK(AC46), "", IF(AD46, AC46, AC46*$F46 ) ) | AF46: =IF(ISBLANK(AB46), 0, VLOOKUP(AB46, 'Price Sheet'!$A$2:$B1015, 2, false)) -> 0 | AG46: =IF(OR(ISBLANK(AC46), ISBLANK(AF46)), "", AF46*AE46) | AJ46: FALSE | AK46: =IF(ISBLANK(AI46), "", IF(AJ46, AI46, AI46*$F46 ) ) | AL46: =IF(ISBLANK(AH46), 0, VLOOKUP(AH46, 'Price Sheet'!$A$2:$B1015, 2, false)) -> 0 | AM46: =IF(OR(ISBLANK(AI46), ISBLANK(AL46)), "", AL46*AK46) | AP46: FALSE | AQ46: =IF(ISBLANK(AO46), "", IF(AP46, AO46, AO46*$F46 ) ) | AR46: =IF(ISBLANK(AN46), 0, VLOOKUP(AN46, 'Price Sheet'!$A$2:$B1015, 2, false)) -> 0 | AS46: =IF(OR(ISBLANK(AO46), ISBLANK(AR46)), "", AR46*AQ46) | AV46: FALSE | AW46: =IF(ISBLANK(AU46), "", IF(AV46, AU46, AU46*$F46 ) ) | AX46: =IF(ISBLANK(AT46), 0, VLOOKUP(AT46, 'Price Sheet'!$A$2:$B1015, 2, false)) -> 0 | AY46: =IF(OR(ISBLANK(AU46), ISBLANK(AX46)), "", AX46*AW46) | BB46: FALSE | BC46: =IF(ISBLANK(BA46), "", IF(BB46, BA46, BA46*$F46 ) ) | BD46: =IF(ISBLANK(AZ46), 0, VLOOKUP(AZ46, 'Price Sheet'!$A$2:$B1015, 2, false)) -> 0 | BE46: =IF(OR(ISBLANK(BA46), ISBLANK(BD46)), "", BD46*BC46) | BH46: FALSE | BI46: =IF(ISBLANK(BG46), "", IF(BH46, BG46, BG46*$F46 ) ) | BJ46: =IF(ISBLANK(BF46), 0, VLOOKUP(BF46, 'Price Sheet'!$A$2:$B1015, 2, false)) -> 0 | BK46: =IF(OR(ISBLANK(BG46), ISBLANK(BJ46)), "", BJ46*BI46) | BN46: FALSE | BO46: =IF(ISBLANK(BM46), "", IF(BN46, BM46, BM46*$F46 ) ) | BP46: =IF(ISBLANK(BL46), 0, VLOOKUP(BL46, 'Price Sheet'!$A$2:$B1015, 2, false)) -> 0 | BQ46: =IF(OR(ISBLANK(BM46), ISBLANK(BP46)), "", BP46*BO46)
A47: Bathtub | B47: =H47+U47+AA47+AG47+AM47+AS47+AY47+BE47+BK47+J47+BQ47 -> 109.9375 | C47: Pottery | D47: Kiln | E47: =IF(ISBLANK(D47), "", VLOOKUP(D47,'Crafting Tables'!$A$2:$B1015, 2, false)) -> Advanced | F47: =IFERROR(IF(E47 = "None", 1, VLOOKUP(C47,General!$A$5:$L$35, SWITCH(E47, "Basic", 8, "Advanced", 10, "Modern", 12), false)),"") -> 1 | G47: 240 | H47: =IFERROR(VLOOKUP(C47, General!$A$5:$L$35, 6, false) * G47 / 1000, 0) -> 9.6 | I47: 180 | J47: =IFERROR(I47*VLOOKUP(D47,'Crafting Tables'!$1:$1000, 4, false)*F47,"") -> 0.3375 | K47: TRUE | L47: Bathtub | M47: 1 | N47: =IF(ISBLANK(M47), "", $B47 / M47) -> 109.9375 | P47: Clay | Q47: 40 | R47: FALSE | S47: =IF(ISBLANK(Q47), "", IF(R47, Q47, Q47*$F47 ) ) -> 40 | T47: =IF(ISBLANK(P47), 0, VLOOKUP(P47, 'Price Sheet'!$A$2:$B1015, 2, false)) -> 0.5 | U47: =IF(OR(ISBLANK(Q47), ISBLANK(T47)), "", T47*S47) -> 20 | V47: Iron Bar | W47: 20 | X47: FALSE | Y47: =IF(ISBLANK(W47), "", IF(X47, W47, W47*$F47 ) ) -> 20 | Z47: =IF(ISBLANK(V47), 0, VLOOKUP(V47, 'Price Sheet'!$A$2:$B1015, 2, false)) -> 4 | AA47: =IF(OR(ISBLANK(W47), ISBLANK(Z47)), "", Z47*Y47) -> 80 | AD47: FALSE | AE47: =IF(ISBLANK(AC47), "", IF(AD47, AC47, AC47*$F47 ) ) | AF47: =IF(ISBLANK(AB47), 0, VLOOKUP(AB47, 'Price Sheet'!$A$2:$B1015, 2, false)) -> 0 | AG47: =IF(OR(ISBLANK(AC47), ISBLANK(AF47)), "", AF47*AE47) | AJ47: FALSE | AK47: =IF(ISBLANK(AI47), "", IF(AJ47, AI47, AI47*$F47 ) ) | AL47: =IF(ISBLANK(AH47), 0, VLOOKUP(AH47, 'Price Sheet'!$A$2:$B1015, 2, false)) -> 0 | AM47: =IF(OR(ISBLANK(AI47), ISBLANK(AL47)), "", AL47*AK47) | AP47: FALSE | AQ47: =IF(ISBLANK(AO47), "", IF(AP47, AO47, AO47*$F47 ) ) | AR47: =IF(ISBLANK(AN47), 0, VLOOKUP(AN47, 'Price Sheet'!$A$2:$B1015, 2, false)) -> 0 | AS47: =IF(OR(ISBLANK(AO47), ISBLANK(AR47)), "", AR47*AQ47) | AV47: FALSE | AW47: =IF(ISBLANK(AU47), "", IF(AV47, AU47, AU47*$F47 ) ) | AX47: =IF(ISBLANK(AT47), 0, VLOOKUP(AT47, 'Price Sheet'!$A$2:$B1015, 2, false)) -> 0 | AY47: =IF(OR(ISBLANK(AU47), ISBLANK(AX47)), "", AX47*AW47) | BB47: FALSE | BC47: =IF(ISBLANK(BA47), "", IF(BB47, BA47, BA47*$F47 ) ) | BD47: =IF(ISBLANK(AZ47), 0, VLOOKUP(AZ47, 'Price Sheet'!$A$2:$B1015, 2, false)) -> 0 | BE47: =IF(OR(ISBLANK(BA47), ISBLANK(BD47)), "", BD47*BC47) | BH47: FALSE | BI47: =IF(ISBLANK(BG47), "", IF(BH47, BG47, BG47*$F47 ) ) | BJ47: =IF(ISBLANK(BF47), 0, VLOOKUP(BF47, 'Price Sheet'!$A$2:$B1015, 2, false)) -> 0 | BK47: =IF(OR(ISBLANK(BG47), ISBLANK(BJ47)), "", BJ47*BI47) | BN47: FALSE | BO47: =IF(ISBLANK(BM47), "", IF(BN47, BM47, BM47*$F47 ) ) | BP47: =IF(ISBLANK(BL47), 0, VLOOKUP(BL47, 'Price Sheet'!$A$2:$B1015, 2, false)) -> 0 | BQ47: =IF(OR(ISBLANK(BM47), ISBLANK(BP47)), "", BP47*BO47)
A48: Wooden Wheel | B48: =H48+U48+AA48+AG48+AM48+AS48+AY48+BE48+BK48+J48+BQ48 -> 3.36 | C48: Basic Engineering | D48: Wainwright Table | E48: =IF(ISBLANK(D48), "", VLOOKUP(D48,'Crafting Tables'!$A$2:$B1015, 2, false)) -> Basic | F48: =IFERROR(IF(E48 = "None", 1, VLOOKUP(C48,General!$A$5:$L$35, SWITCH(E48, "Basic", 8, "Advanced", 10, "Modern", 12), false)),"") -> 0.55 | G48: 40 | H48: =IFERROR(VLOOKUP(C48, General!$A$5:$L$35, 6, false) * G48 / 1000, 0) -> 1.6 | I48: 120 | J48: =IFERROR(I48*VLOOKUP(D48,'Crafting Tables'!$1:$1000, 4, false)*F48,"") -> 0 | K48: TRUE | L48: Wooden Wheel | M48: 1 | N48: =IF(ISBLANK(M48), "", $B48 / M48) -> 3.36 | P48: Hewn Log | Q48: 4 | R48: FALSE | S48: =IF(ISBLANK(Q48), "", IF(R48, Q48, Q48*$F48 ) ) -> 2.2 | T48: =IF(ISBLANK(P48), 0, VLOOKUP(P48, 'Price Sheet'!$A$2:$B1015, 2, false)) -> 0.8 | U48: =IF(OR(ISBLANK(Q48), ISBLANK(T48)), "", T48*S48) -> 1.76 | X48: FALSE | Y48: =IF(ISBLANK(W48), "", IF(X48, W48, W48*$F48 ) ) | Z48: =IF(ISBLANK(V48), 0, VLOOKUP(V48, 'Price Sheet'!$A$2:$B1015, 2, false)) -> 0 | AA48: =IF(OR(ISBLANK(W48), ISBLANK(Z48)), "", Z48*Y48) | AD48: FALSE | AE48: =IF(ISBLANK(AC48), "", IF(AD48, AC48, AC48*$F48 ) ) | AF48: =IF(ISBLANK(AB48), 0, VLOOKUP(AB48, 'Price Sheet'!$A$2:$B1015, 2, false)) -> 0 | AG48: =IF(OR(ISBLANK(AC48), ISBLANK(AF48)), "", AF48*AE48) | AJ48: FALSE | AK48: =IF(ISBLANK(AI48), "", IF(AJ48, AI48, AI48*$F48 ) ) | AL48: =IF(ISBLANK(AH48), 0, VLOOKUP(AH48, 'Price Sheet'!$A$2:$B1015, 2, false)) -> 0 | AM48: =IF(OR(ISBLANK(AI48), ISBLANK(AL48)), "", AL48*AK48) | AP48: FALSE | AQ48: =IF(ISBLANK(AO48), "", IF(AP48, AO48, AO48*$F48 ) ) | AR48: =IF(ISBLANK(AN48), 0, VLOOKUP(AN48, 'Price Sheet'!$A$2:$B1015, 2, false)) -> 0 | AS48: =IF(OR(ISBLANK(AO48), ISBLANK(AR48)), "", AR48*AQ48) | AV48: FALSE | AW48: =IF(ISBLANK(AU48), "", IF(AV48, AU48, AU48*$F48 ) ) | AX48: =IF(ISBLANK(AT48), 0, VLOOKUP(AT48, 'Price Sheet'!$A$2:$B1015, 2, false)) -> 0 | AY48: =IF(OR(ISBLANK(AU48), ISBLANK(AX48)), "", AX48*AW48) | BB48: FALSE | BC48: =IF(ISBLANK(BA48), "", IF(BB48, BA48, BA48*$F48 ) ) | BD48: =IF(ISBLANK(AZ48), 0, VLOOKUP(AZ48, 'Price Sheet'!$A$2:$B1015, 2, false)) -> 0 | BE48: =IF(OR(ISBLANK(BA48), ISBLANK(BD48)), "", BD48*BC48) | BH48: FALSE | BI48: =IF(ISBLANK(BG48), "", IF(BH48, BG48, BG48*$F48 ) ) | BJ48: =IF(ISBLANK(BF48), 0, VLOOKUP(BF48, 'Price Sheet'!$A$2:$B1015, 2, false)) -> 0 | BK48: =IF(OR(ISBLANK(BG48), ISBLANK(BJ48)), "", BJ48*BI48) | BN48: FALSE | BO48: =IF(ISBLANK(BM48), "", IF(BN48, BM48, BM48*$F48 ) ) | BP48: =IF(ISBLANK(BL48), 0, VLOOKUP(BL48, 'Price Sheet'!$A$2:$B1015, 2, false)) -> 0 | BQ48: =IF(OR(ISBLANK(BM48), ISBLANK(BP48)), "", BP48*BO48)
A49: Small Wooden Boat | B49: =H49+U49+AA49+AG49+AM49+AS49+AY49+BE49+BK49+J49+BQ49 -> 151.24 | C49: Shipwright | D49: Small Shipyard | E49: =IF(ISBLANK(D49), "", VLOOKUP(D49,'Crafting Tables'!$A$2:$B1015, 2, false)) -> Basic | F49: =IFERROR(IF(E49 = "None", 1, VLOOKUP(C49,General!$A$5:$L$35, SWITCH(E49, "Basic", 8, "Advanced", 10, "Modern", 12), false)),"") -> 0.55 | G49: 680 | H49: =IFERROR(VLOOKUP(C49, General!$A$5:$L$35, 6, false) * G49 / 1000, 0) -> 27.2 | I49: =6*60 -> 360 | J49: =IFERROR(I49*VLOOKUP(D49,'Crafting Tables'!$1:$1000, 4, false)*F49,"") -> 0 | K49: TRUE | L49: Small Wooden Boat | M49: 1 | N49: =IF(ISBLANK(M49), "", $B49 / M49) -> 151.24 | P49: Wooden Hull Planks | Q49: 8 | R49: FALSE | S49: =IF(ISBLANK(Q49), "", IF(R49, Q49, Q49*$F49 ) ) -> 4.4 | T49: =IF(ISBLANK(P49), 0, VLOOKUP(P49, 'Price Sheet'!$A$2:$B1015, 2, false)) -> 5 | U49: =IF(OR(ISBLANK(Q49), ISBLANK(T49)), "", T49*S49) -> 22 | V49: Wooden Wheel | W49: 2 | X49: TRUE | Y49: =IF(ISBLANK(W49), "", IF(X49, W49, W49*$F49 ) ) -> 2 | Z49: =IF(ISBLANK(V49), 0, VLOOKUP(V49, 'Price Sheet'!$A$2:$B1015, 2, false)) -> 5 | AA49: =IF(OR(ISBLANK(W49), ISBLANK(Z49)), "", Z49*Y49) -> 10 | AB49: Gearbox | AC49: 2 | AD49: TRUE | AE49: =IF(ISBLANK(AC49), "", IF(AD49, AC49, AC49*$F49 ) ) -> 2 | AF49: =IF(ISBLANK(AB49), 0, VLOOKUP(AB49, 'Price Sheet'!$A$2:$B1015, 2, false)) -> 37.8 | AG49: =IF(OR(ISBLANK(AC49), ISBLANK(AF49)), "", AF49*AE49) -> 75.6 | AH49: Medium Wooden Ship Frame | AI49: 1 | AJ49: TRUE | AK49: =IF(ISBLANK(AI49), "", IF(AJ49, AI49, AI49*$F49 ) ) -> 1 | AL49: =IF(ISBLANK(AH49), 0, VLOOKUP(AH49, 'Price Sheet'!$A$2:$B1015, 2, false)) -> 16.44 | AM49: =IF(OR(ISBLANK(AI49), ISBLANK(AL49)), "", AL49*AK49) -> 16.44 | AP49: FALSE | AQ49: =IF(ISBLANK(AO49), "", IF(AP49, AO49, AO49*$F49 ) ) | AR49: =IF(ISBLANK(AN49), 0, VLOOKUP(AN49, 'Price Sheet'!$A$2:$B1015, 2, false)) -> 0 | AS49: =IF(OR(ISBLANK(AO49), ISBLANK(AR49)), "", AR49*AQ49) | AV49: FALSE | AW49: =IF(ISBLANK(AU49), "", IF(AV49, AU49, AU49*$F49 ) ) | AX49: =IF(ISBLANK(AT49), 0, VLOOKUP(AT49, 'Price Sheet'!$A$2:$B1015, 2, false)) -> 0 | AY49: =IF(OR(ISBLANK(AU49), ISBLANK(AX49)), "", AX49*AW49) | BB49: FALSE | BC49: =IF(ISBLANK(BA49), "", IF(BB49, BA49, BA49*$F49 ) ) | BD49: =IF(ISBLANK(AZ49), 0, VLOOKUP(AZ49, 'Price Sheet'!$A$2:$B1015, 2, false)) -> 0 | BE49: =IF(OR(ISBLANK(BA49), ISBLANK(BD49)), "", BD49*BC49) | BH49: FALSE | BI49: =IF(ISBLANK(BG49), "", IF(BH49, BG49, BG49*$F49 ) ) | BJ49: =IF(ISBLANK(BF49), 0, VLOOKUP(BF49, 'Price Sheet'!$A$2:$B1015, 2, false)) -> 0 | BK49: =IF(OR(ISBLANK(BG49), ISBLANK(BJ49)), "", BJ49*BI49) | BN49: FALSE | BO49: =IF(ISBLANK(BM49), "", IF(BN49, BM49, BM49*$F49 ) ) | BP49: =IF(ISBLANK(BL49), 0, VLOOKUP(BL49, 'Price Sheet'!$A$2:$B1015, 2, false)) -> 0 | BQ49: =IF(OR(ISBLANK(BM49), ISBLANK(BP49)), "", BP49*BO49)
A50: Wooden Barge | B50: =H50+U50+AA50+AG50+AM50+AS50+AY50+BE50+BK50+J50+BQ50 -> 0 | E50: =IF(ISBLANK(D50), "", VLOOKUP(D50,'Crafting Tables'!$A$2:$B1015, 2, false)) | F50: =IFERROR(IF(E50 = "None", 1, VLOOKUP(C50,General!$A$5:$L$35, SWITCH(E50, "Basic", 8, "Advanced", 10, "Modern", 12), false)),"") | H50: =IFERROR(VLOOKUP(C50, General!$A$5:$L$35, 6, false) * G50 / 1000, 0) -> 0 | J50: =IFERROR(I50*VLOOKUP(D50,'Crafting Tables'!$1:$1000, 4, false)*F50,"") | K50: TRUE | N50: =IF(ISBLANK(M50), "", $B50 / M50) | R50: FALSE | S50: =IF(ISBLANK(Q50), "", IF(R50, Q50, Q50*$F50 ) ) | T50: =IF(ISBLANK(P50), 0, VLOOKUP(P50, 'Price Sheet'!$A$2:$B1015, 2, false)) -> 0 | U50: =IF(OR(ISBLANK(Q50), ISBLANK(T50)), "", T50*S50) | X50: FALSE | Y50: =IF(ISBLANK(W50), "", IF(X50, W50, W50*$F50 ) ) | Z50: =IF(ISBLANK(V50), 0, VLOOKUP(V50, 'Price Sheet'!$A$2:$B1015, 2, false)) -> 0 | AA50: =IF(OR(ISBLANK(W50), ISBLANK(Z50)), "", Z50*Y50) | AD50: FALSE | AE50: =IF(ISBLANK(AC50), "", IF(AD50, AC50, AC50*$F50 ) ) | AF50: =IF(ISBLANK(AB50), 0, VLOOKUP(AB50, 'Price Sheet'!$A$2:$B1015, 2, false)) -> 0 | AG50: =IF(OR(ISBLANK(AC50), ISBLANK(AF50)), "", AF50*AE50) | AJ50: FALSE | AK50: =IF(ISBLANK(AI50), "", IF(AJ50, AI50, AI50*$F50 ) ) | AL50: =IF(ISBLANK(AH50), 0, VLOOKUP(AH50, 'Price Sheet'!$A$2:$B1015, 2, false)) -> 0 | AM50: =IF(OR(ISBLANK(AI50), ISBLANK(AL50)), "", AL50*AK50) | AP50: FALSE | AQ50: =IF(ISBLANK(AO50), "", IF(AP50, AO50, AO50*$F50 ) ) | AR50: =IF(ISBLANK(AN50), 0, VLOOKUP(AN50, 'Price Sheet'!$A$2:$B1015, 2, false)) -> 0 | AS50: =IF(OR(ISBLANK(AO50), ISBLANK(AR50)), "", AR50*AQ50) | AV50: FALSE | AW50: =IF(ISBLANK(AU50), "", IF(AV50, AU50, AU50*$F50 ) ) | AX50: =IF(ISBLANK(AT50), 0, VLOOKUP(AT50, 'Price Sheet'!$A$2:$B1015, 2, false)) -> 0 | AY50: =IF(OR(ISBLANK(AU50), ISBLANK(AX50)), "", AX50*AW50) | BB50: FALSE | BC50: =IF(ISBLANK(BA50), "", IF(BB50, BA50, BA50*$F50 ) ) | BD50: =IF(ISBLANK(AZ50), 0, VLOOKUP(AZ50, 'Price Sheet'!$A$2:$B1015, 2, false)) -> 0 | BE50: =IF(OR(ISBLANK(BA50), ISBLANK(BD50)), "", BD50*BC50) | BH50: FALSE | BI50: =IF(ISBLANK(BG50), "", IF(BH50, BG50, BG50*$F50 ) ) | BJ50: =IF(ISBLANK(BF50), 0, VLOOKUP(BF50, 'Price Sheet'!$A$2:$B1015, 2, false)) -> 0 | BK50: =IF(OR(ISBLANK(BG50), ISBLANK(BJ50)), "", BJ50*BI50) | BN50: FALSE | BO50: =IF(ISBLANK(BM50), "", IF(BN50, BM50, BM50*$F50 ) ) | BP50: =IF(ISBLANK(BL50), 0, VLOOKUP(BL50, 'Price Sheet'!$A$2:$B1015, 2, false)) -> 0 | BQ50: =IF(OR(ISBLANK(BM50), ISBLANK(BP50)), "", BP50*BO50)
A51: Medium Wooden Ship Frame | B51: =H51+U51+AA51+AG51+AM51+AS51+AY51+BE51+BK51+J51+BQ51 -> 16.44 | C51: Shipwright | D51: Small Shipyard | E51: =IF(ISBLANK(D51), "", VLOOKUP(D51,'Crafting Tables'!$A$2:$B1015, 2, false)) -> Basic | F51: =IFERROR(IF(E51 = "None", 1, VLOOKUP(C51,General!$A$5:$L$35, SWITCH(E51, "Basic", 8, "Advanced", 10, "Modern", 12), false)),"") -> 0.55 | G51: 120 | H51: =IFERROR(VLOOKUP(C51, General!$A$5:$L$35, 6, false) * G51 / 1000, 0) -> 4.8 | J51: =IFERROR(I51*VLOOKUP(D51,'Crafting Tables'!$1:$1000, 4, false)*F51,"") -> 0 | K51: TRUE | L51: Medium Wooden Ship Frame | M51: 1 | N51: =IF(ISBLANK(M51), "", $B51 / M51) -> 16.44 | P51: Hewn Log | Q51: 16 | R51: FALSE | S51: =IF(ISBLANK(Q51), "", IF(R51, Q51, Q51*$F51 ) ) -> 8.8 | T51: =IF(ISBLANK(P51), 0, VLOOKUP(P51, 'Price Sheet'!$A$2:$B1015, 2, false)) -> 0.8 | U51: =IF(OR(ISBLANK(Q51), ISBLANK(T51)), "", T51*S51) -> 7.04 | V51: Wooden Keel | W51: 1 | X51: TRUE | Y51: =IF(ISBLANK(W51), "", IF(X51, W51, W51*$F51 ) ) -> 1 | Z51: =IF(ISBLANK(V51), 0, VLOOKUP(V51, 'Price Sheet'!$A$2:$B1015, 2, false)) -> 4.6 | AA51: =IF(OR(ISBLANK(W51), ISBLANK(Z51)), "", Z51*Y51) -> 4.6 | AD51: FALSE | AE51: =IF(ISBLANK(AC51), "", IF(AD51, AC51, AC51*$F51 ) ) | AF51: =IF(ISBLANK(AB51), 0, VLOOKUP(AB51, 'Price Sheet'!$A$2:$B1015, 2, false)) -> 0 | AG51: =IF(OR(ISBLANK(AC51), ISBLANK(AF51)), "", AF51*AE51) | AJ51: FALSE | AK51: =IF(ISBLANK(AI51), "", IF(AJ51, AI51, AI51*$F51 ) ) | AL51: =IF(ISBLANK(AH51), 0, VLOOKUP(AH51, 'Price Sheet'!$A$2:$B1015, 2, false)) -> 0 | AM51: =IF(OR(ISBLANK(AI51), ISBLANK(AL51)), "", AL51*AK51) | AP51: FALSE | AQ51: =IF(ISBLANK(AO51), "", IF(AP51, AO51, AO51*$F51 ) ) | AR51: =IF(ISBLANK(AN51), 0, VLOOKUP(AN51, 'Price Sheet'!$A$2:$B1015, 2, false)) -> 0 | AS51: =IF(OR(ISBLANK(AO51), ISBLANK(AR51)), "", AR51*AQ51) | AV51: FALSE | AW51: =IF(ISBLANK(AU51), "", IF(AV51, AU51, AU51*$F51 ) ) | AX51: =IF(ISBLANK(AT51), 0, VLOOKUP(AT51, 'Price Sheet'!$A$2:$B1015, 2, false)) -> 0 | AY51: =IF(OR(ISBLANK(AU51), ISBLANK(AX51)), "", AX51*AW51) | BB51: FALSE | BC51: =IF(ISBLANK(BA51), "", IF(BB51, BA51, BA51*$F51 ) ) | BD51: =IF(ISBLANK(AZ51), 0, VLOOKUP(AZ51, 'Price Sheet'!$A$2:$B1015, 2, false)) -> 0 | BE51: =IF(OR(ISBLANK(BA51), ISBLANK(BD51)), "", BD51*BC51) | BH51: FALSE | BI51: =IF(ISBLANK(BG51), "", IF(BH51, BG51, BG51*$F51 ) ) | BJ51: =IF(ISBLANK(BF51), 0, VLOOKUP(BF51, 'Price Sheet'!$A$2:$B1015, 2, false)) -> 0 | BK51: =IF(OR(ISBLANK(BG51), ISBLANK(BJ51)), "", BJ51*BI51) | BN51: FALSE | BO51: =IF(ISBLANK(BM51), "", IF(BN51, BM51, BM51*$F51 ) ) | BP51: =IF(ISBLANK(BL51), 0, VLOOKUP(BL51, 'Price Sheet'!$A$2:$B1015, 2, false)) -> 0 | BQ51: =IF(OR(ISBLANK(BM51), ISBLANK(BP51)), "", BP51*BO51)
A52: Lumber | B52: =H52+U52+AA52+AG52+AM52+AS52+AY52+BE52+BK52+J52+BQ52 -> #N/A | C52: Carpentry | D52: Sawmill | E52: =IF(ISBLANK(D52), "", VLOOKUP(D52,'Crafting Tables'!$A$2:$B1015, 2, false)) -> Advanced | F52: =IFERROR(IF(E52 = "None", 1, VLOOKUP(C52,General!$A$5:$L$35, SWITCH(E52, "Basic", 8, "Advanced", 10, "Modern", 12), false)),"") -> 1 | G52: 60 | H52: =IFERROR(VLOOKUP(C52, General!$A$5:$L$35, 6, false) * G52 / 1000, 0) -> 2.4 | I52: 19.2 | J52: =IFERROR(I52*VLOOKUP(D52,'Crafting Tables'!$1:$1000, 4, false)*F52,"") -> 0 | K52: TRUE | L52: Lumber | M52: 2 | N52: =IF(ISBLANK(M52), "", $B52 / M52) -> #N/A | P52: Nails | Q52: 2 | R52: FALSE | S52: =IF(ISBLANK(Q52), "", IF(R52, Q52, Q52*$F52 ) ) -> 2 | T52: =IF(ISBLANK(P52), 0, VLOOKUP(P52, 'Price Sheet'!$A$2:$B1015, 2, false)) -> 0.2 | U52: =IF(OR(ISBLANK(Q52), ISBLANK(T52)), "", T52*S52) -> 0.4 | V52: Flaxeed Oil | W52: 0.5 | X52: FALSE | Y52: =IF(ISBLANK(W52), "", IF(X52, W52, W52*$F52 ) ) -> 0.5 | Z52: =IF(ISBLANK(V52), 0, VLOOKUP(V52, 'Price Sheet'!$A$2:$B1015, 2, false)) -> #N/A | AA52: =IF(OR(ISBLANK(W52), ISBLANK(Z52)), "", Z52*Y52) -> #N/A | AB52: Board | AC52: 10 | AD52: FALSE | AE52: =IF(ISBLANK(AC52), "", IF(AD52, AC52, AC52*$F52 ) ) -> 10 | AF52: =IF(ISBLANK(AB52), 0, VLOOKUP(AB52, 'Price Sheet'!$A$2:$B1015, 2, false)) -> 0.45 | AG52: =IF(OR(ISBLANK(AC52), ISBLANK(AF52)), "", AF52*AE52) -> 4.5 | AJ52: FALSE | AK52: =IF(ISBLANK(AI52), "", IF(AJ52, AI52, AI52*$F52 ) ) | AL52: =IF(ISBLANK(AH52), 0, VLOOKUP(AH52, 'Price Sheet'!$A$2:$B1015, 2, false)) -> 0 | AM52: =IF(OR(ISBLANK(AI52), ISBLANK(AL52)), "", AL52*AK52) | AP52: FALSE | AQ52: =IF(ISBLANK(AO52), "", IF(AP52, AO52, AO52*$F52 ) ) | AR52: =IF(ISBLANK(AN52), 0, VLOOKUP(AN52, 'Price Sheet'!$A$2:$B1015, 2, false)) -> 0 | AS52: =IF(OR(ISBLANK(AO52), ISBLANK(AR52)), "", AR52*AQ52) | AV52: FALSE | AW52: =IF(ISBLANK(AU52), "", IF(AV52, AU52, AU52*$F52 ) ) | AX52: =IF(ISBLANK(AT52), 0, VLOOKUP(AT52, 'Price Sheet'!$A$2:$B1015, 2, false)) -> 0 | AY52: =IF(OR(ISBLANK(AU52), ISBLANK(AX52)), "", AX52*AW52) | BB52: FALSE | BC52: =IF(ISBLANK(BA52), "", IF(BB52, BA52, BA52*$F52 ) ) | BD52: =IF(ISBLANK(AZ52), 0, VLOOKUP(AZ52, 'Price Sheet'!$A$2:$B1015, 2, false)) -> 0 | BE52: =IF(OR(ISBLANK(BA52), ISBLANK(BD52)), "", BD52*BC52) | BH52: FALSE | BI52: =IF(ISBLANK(BG52), "", IF(BH52, BG52, BG52*$F52 ) ) | BJ52: =IF(ISBLANK(BF52), 0, VLOOKUP(BF52, 'Price Sheet'!$A$2:$B1015, 2, false)) -> 0 | BK52: =IF(OR(ISBLANK(BG52), ISBLANK(BJ52)), "", BJ52*BI52) | BN52: FALSE | BO52: =IF(ISBLANK(BM52), "", IF(BN52, BM52, BM52*$F52 ) ) | BP52: =IF(ISBLANK(BL52), 0, VLOOKUP(BL52, 'Price Sheet'!$A$2:$B1015, 2, false)) -> 0 | BQ52: =IF(OR(ISBLANK(BM52), ISBLANK(BP52)), "", BP52*BO52)
A53: Large Lumber Stockpile | B53: =H53+U53+AA53+AG53+AM53+AS53+AY53+BE53+BK53+J53+BQ53 -> 124.75 | C53: Carpentry | D53: Sawmill | E53: =IF(ISBLANK(D53), "", VLOOKUP(D53,'Crafting Tables'!$A$2:$B1015, 2, false)) -> Advanced | F53: =IFERROR(IF(E53 = "None", 1, VLOOKUP(C53,General!$A$5:$L$35, SWITCH(E53, "Basic", 8, "Advanced", 10, "Modern", 12), false)),"") -> 1 | G53: 1200 | H53: =IFERROR(VLOOKUP(C53, General!$A$5:$L$35, 6, false) * G53 / 1000, 0) -> 48 | J53: =IFERROR(I53*VLOOKUP(D53,'Crafting Tables'!$1:$1000, 4, false)*F53,"") -> 0 | K53: TRUE | L53: Large Lumber Stockpile | M53: 1 | N53: =IF(ISBLANK(M53), "", $B53 / M53) -> 124.75 | P53: Lumber | Q53: 20 | R53: FALSE | S53: =IF(ISBLANK(Q53), "", IF(R53, Q53, Q53*$F53 ) ) -> 20 | T53: =IF(ISBLANK(P53), 0, VLOOKUP(P53, 'Price Sheet'!$A$2:$B1015, 2, false)) -> 3.5 | U53: =IF(OR(ISBLANK(Q53), ISBLANK(T53)), "", T53*S53) -> 70 | V53: Board | W53: 15 | X53: FALSE | Y53: =IF(ISBLANK(W53), "", IF(X53, W53, W53*$F53 ) ) -> 15 | Z53: =IF(ISBLANK(V53), 0, VLOOKUP(V53, 'Price Sheet'!$A$2:$B1015, 2, false)) -> 0.45 | AA53: =IF(OR(ISBLANK(W53), ISBLANK(Z53)), "", Z53*Y53) -> 6.75 | AD53: FALSE | AE53: =IF(ISBLANK(AC53), "", IF(AD53, AC53, AC53*$F53 ) ) | AF53: =IF(ISBLANK(AB53), 0, VLOOKUP(AB53, 'Price Sheet'!$A$2:$B1015, 2, false)) -> 0 | AG53: =IF(OR(ISBLANK(AC53), ISBLANK(AF53)), "", AF53*AE53) | AJ53: FALSE | AK53: =IF(ISBLANK(AI53), "", IF(AJ53, AI53, AI53*$F53 ) ) | AL53: =IF(ISBLANK(AH53), 0, VLOOKUP(AH53, 'Price Sheet'!$A$2:$B1015, 2, false)) -> 0 | AM53: =IF(OR(ISBLANK(AI53), ISBLANK(AL53)), "", AL53*AK53) | AP53: FALSE | AQ53: =IF(ISBLANK(AO53), "", IF(AP53, AO53, AO53*$F53 ) ) | AR53: =IF(ISBLANK(AN53), 0, VLOOKUP(AN53, 'Price Sheet'!$A$2:$B1015, 2, false)) -> 0 | AS53: =IF(OR(ISBLANK(AO53), ISBLANK(AR53)), "", AR53*AQ53) | AV53: FALSE | AW53: =IF(ISBLANK(AU53), "", IF(AV53, AU53, AU53*$F53 ) ) | AX53: =IF(ISBLANK(AT53), 0, VLOOKUP(AT53, 'Price Sheet'!$A$2:$B1015, 2, false)) -> 0 | AY53: =IF(OR(ISBLANK(AU53), ISBLANK(AX53)), "", AX53*AW53) | BB53: FALSE | BC53: =IF(ISBLANK(BA53), "", IF(BB53, BA53, BA53*$F53 ) ) | BD53: =IF(ISBLANK(AZ53), 0, VLOOKUP(AZ53, 'Price Sheet'!$A$2:$B1015, 2, false)) -> 0 | BE53: =IF(OR(ISBLANK(BA53), ISBLANK(BD53)), "", BD53*BC53) | BH53: FALSE | BI53: =IF(ISBLANK(BG53), "", IF(BH53, BG53, BG53*$F53 ) ) | BJ53: =IF(ISBLANK(BF53), 0, VLOOKUP(BF53, 'Price Sheet'!$A$2:$B1015, 2, false)) -> 0 | BK53: =IF(OR(ISBLANK(BG53), ISBLANK(BJ53)), "", BJ53*BI53) | BN53: FALSE | BO53: =IF(ISBLANK(BM53), "", IF(BN53, BM53, BM53*$F53 ) ) | BP53: =IF(ISBLANK(BL53), 0, VLOOKUP(BL53, 'Price Sheet'!$A$2:$B1015, 2, false)) -> 0 | BQ53: =IF(OR(ISBLANK(BM53), ISBLANK(BP53)), "", BP53*BO53)
A54: Lumber Stockpile | B54: =H54+U54+AA54+AG54+AM54+AS54+AY54+BE54+BK54+J54+BQ54 -> 0 | E54: =IF(ISBLANK(D54), "", VLOOKUP(D54,'Crafting Tables'!$A$2:$B1015, 2, false)) | F54: =IFERROR(IF(E54 = "None", 1, VLOOKUP(C54,General!$A$5:$L$35, SWITCH(E54, "Basic", 8, "Advanced", 10, "Modern", 12), false)),"") | H54: =IFERROR(VLOOKUP(C54, General!$A$5:$L$35, 6, false) * G54 / 1000, 0) -> 0 | J54: =IFERROR(I54*VLOOKUP(D54,'Crafting Tables'!$1:$1000, 4, false)*F54,"") | K54: FALSE | N54: =IF(ISBLANK(M54), "", $B54 / M54) | R54: FALSE | S54: =IF(ISBLANK(Q54), "", IF(R54, Q54, Q54*$F54 ) ) | T54: =IF(ISBLANK(P54), 0, VLOOKUP(P54, 'Price Sheet'!$A$2:$B1015, 2, false)) -> 0 | U54: =IF(OR(ISBLANK(Q54), ISBLANK(T54)), "", T54*S54) | X54: FALSE | Y54: =IF(ISBLANK(W54), "", IF(X54, W54, W54*$F54 ) ) | Z54: =IF(ISBLANK(V54), 0, VLOOKUP(V54, 'Price Sheet'!$A$2:$B1015, 2, false)) -> 0 | AA54: =IF(OR(ISBLANK(W54), ISBLANK(Z54)), "", Z54*Y54) | AD54: FALSE | AE54: =IF(ISBLANK(AC54), "", IF(AD54, AC54, AC54*$F54 ) ) | AF54: =IF(ISBLANK(AB54), 0, VLOOKUP(AB54, 'Price Sheet'!$A$2:$B1015, 2, false)) -> 0 | AG54: =IF(OR(ISBLANK(AC54), ISBLANK(AF54)), "", AF54*AE54) | AJ54: FALSE | AK54: =IF(ISBLANK(AI54), "", IF(AJ54, AI54, AI54*$F54 ) ) | AL54: =IF(ISBLANK(AH54), 0, VLOOKUP(AH54, 'Price Sheet'!$A$2:$B1015, 2, false)) -> 0 | AM54: =IF(OR(ISBLANK(AI54), ISBLANK(AL54)), "", AL54*AK54) | AP54: FALSE | AQ54: =IF(ISBLANK(AO54), "", IF(AP54, AO54, AO54*$F54 ) ) | AR54: =IF(ISBLANK(AN54), 0, VLOOKUP(AN54, 'Price Sheet'!$A$2:$B1015, 2, false)) -> 0 | AS54: =IF(OR(ISBLANK(AO54), ISBLANK(AR54)), "", AR54*AQ54) | AV54: FALSE | AW54: =IF(ISBLANK(AU54), "", IF(AV54, AU54, AU54*$F54 ) ) | AX54: =IF(ISBLANK(AT54), 0, VLOOKUP(AT54, 'Price Sheet'!$A$2:$B1015, 2, false)) -> 0 | AY54: =IF(OR(ISBLANK(AU54), ISBLANK(AX54)), "", AX54*AW54) | BB54: FALSE | BC54: =IF(ISBLANK(BA54), "", IF(BB54, BA54, BA54*$F54 ) ) | BD54: =IF(ISBLANK(AZ54), 0, VLOOKUP(AZ54, 'Price Sheet'!$A$2:$B1015, 2, false)) -> 0 | BE54: =IF(OR(ISBLANK(BA54), ISBLANK(BD54)), "", BD54*BC54) | BH54: FALSE | BI54: =IF(ISBLANK(BG54), "", IF(BH54, BG54, BG54*$F54 ) ) | BJ54: =IF(ISBLANK(BF54), 0, VLOOKUP(BF54, 'Price Sheet'!$A$2:$B1015, 2, false)) -> 0 | BK54: =IF(OR(ISBLANK(BG54), ISBLANK(BJ54)), "", BJ54*BI54) | BN54: FALSE | BO54: =IF(ISBLANK(BM54), "", IF(BN54, BM54, BM54*$F54 ) ) | BP54: =IF(ISBLANK(BL54), 0, VLOOKUP(BL54, 'Price Sheet'!$A$2:$B1015, 2, false)) -> 0 | BQ54: =IF(OR(ISBLANK(BM54), ISBLANK(BP54)), "", BP54*BO54)
A55: Large Hanging Lumber Sign | B55: =H55+U55+AA55+AG55+AM55+AS55+AY55+BE55+BK55+J55+BQ55 -> 37.3 | C55: Carpentry | D55: Sawmill | E55: =IF(ISBLANK(D55), "", VLOOKUP(D55,'Crafting Tables'!$A$2:$B1015, 2, false)) -> Advanced | F55: =IFERROR(IF(E55 = "None", 1, VLOOKUP(C55,General!$A$5:$L$35, SWITCH(E55, "Basic", 8, "Advanced", 10, "Modern", 12), false)),"") -> 1 | G55: 120 | H55: =IFERROR(VLOOKUP(C55, General!$A$5:$L$35, 6, false) * G55 / 1000, 0) -> 4.8 | J55: =IFERROR(I55*VLOOKUP(D55,'Crafting Tables'!$1:$1000, 4, false)*F55,"") -> 0 | K55: TRUE | L55: Large Hanging Lumber Sign | M55: 1 | N55: =IF(ISBLANK(M55), "", $B55 / M55) -> 37.3 | P55: Lumber | Q55: 8 | R55: FALSE | S55: =IF(ISBLANK(Q55), "", IF(R55, Q55, Q55*$F55 ) ) -> 8 | T55: =IF(ISBLANK(P55), 0, VLOOKUP(P55, 'Price Sheet'!$A$2:$B1015, 2, false)) -> 3.5 | U55: =IF(OR(ISBLANK(Q55), ISBLANK(T55)), "", T55*S55) -> 28 | V55: Board | W55: 10 | X55: FALSE | Y55: =IF(ISBLANK(W55), "", IF(X55, W55, W55*$F55 ) ) -> 10 | Z55: =IF(ISBLANK(V55), 0, VLOOKUP(V55, 'Price Sheet'!$A$2:$B1015, 2, false)) -> 0.45 | AA55: =IF(OR(ISBLANK(W55), ISBLANK(Z55)), "", Z55*Y55) -> 4.5 | AD55: FALSE | AE55: =IF(ISBLANK(AC55), "", IF(AD55, AC55, AC55*$F55 ) ) | AF55: =IF(ISBLANK(AB55), 0, VLOOKUP(AB55, 'Price Sheet'!$A$2:$B1015, 2, false)) -> 0 | AG55: =IF(OR(ISBLANK(AC55), ISBLANK(AF55)), "", AF55*AE55) | AJ55: FALSE | AK55: =IF(ISBLANK(AI55), "", IF(AJ55, AI55, AI55*$F55 ) ) | AL55: =IF(ISBLANK(AH55), 0, VLOOKUP(AH55, 'Price Sheet'!$A$2:$B1015, 2, false)) -> 0 | AM55: =IF(OR(ISBLANK(AI55), ISBLANK(AL55)), "", AL55*AK55) | AP55: FALSE | AQ55: =IF(ISBLANK(AO55), "", IF(AP55, AO55, AO55*$F55 ) ) | AR55: =IF(ISBLANK(AN55), 0, VLOOKUP(AN55, 'Price Sheet'!$A$2:$B1015, 2, false)) -> 0 | AS55: =IF(OR(ISBLANK(AO55), ISBLANK(AR55)), "", AR55*AQ55) | AV55: FALSE | AW55: =IF(ISBLANK(AU55), "", IF(AV55, AU55, AU55*$F55 ) ) | AX55: =IF(ISBLANK(AT55), 0, VLOOKUP(AT55, 'Price Sheet'!$A$2:$B1015, 2, false)) -> 0 | AY55: =IF(OR(ISBLANK(AU55), ISBLANK(AX55)), "", AX55*AW55) | BB55: FALSE | BC55: =IF(ISBLANK(BA55), "", IF(BB55, BA55, BA55*$F55 ) ) | BD55: =IF(ISBLANK(AZ55), 0, VLOOKUP(AZ55, 'Price Sheet'!$A$2:$B1015, 2, false)) -> 0 | BE55: =IF(OR(ISBLANK(BA55), ISBLANK(BD55)), "", BD55*BC55) | BH55: FALSE | BI55: =IF(ISBLANK(BG55), "", IF(BH55, BG55, BG55*$F55 ) ) | BJ55: =IF(ISBLANK(BF55), 0, VLOOKUP(BF55, 'Price Sheet'!$A$2:$B1015, 2, false)) -> 0 | BK55: =IF(OR(ISBLANK(BG55), ISBLANK(BJ55)), "", BJ55*BI55) | BN55: FALSE | BO55: =IF(ISBLANK(BM55), "", IF(BN55, BM55, BM55*$F55 ) ) | BP55: =IF(ISBLANK(BL55), 0, VLOOKUP(BL55, 'Price Sheet'!$A$2:$B1015, 2, false)) -> 0 | BQ55: =IF(OR(ISBLANK(BM55), ISBLANK(BP55)), "", BP55*BO55)
A56: Large Standing Lumber Sign | B56: =H56+U56+AA56+AG56+AM56+AS56+AY56+BE56+BK56+J56+BQ56 -> 37.3 | C56: Carpentry | D56: Sawmill | E56: =IF(ISBLANK(D56), "", VLOOKUP(D56,'Crafting Tables'!$A$2:$B1015, 2, false)) -> Advanced | F56: =IFERROR(IF(E56 = "None", 1, VLOOKUP(C56,General!$A$5:$L$35, SWITCH(E56, "Basic", 8, "Advanced", 10, "Modern", 12), false)),"") -> 1 | G56: 120 | H56: =IFERROR(VLOOKUP(C56, General!$A$5:$L$35, 6, false) * G56 / 1000, 0) -> 4.8 | J56: =IFERROR(I56*VLOOKUP(D56,'Crafting Tables'!$1:$1000, 4, false)*F56,"") -> 0 | K56: TRUE | L56: Large Standing Lumber Sign | M56: 1 | N56: =IF(ISBLANK(M56), "", $B56 / M56) -> 37.3 | P56: Lumber | Q56: 8 | R56: FALSE | S56: =IF(ISBLANK(Q56), "", IF(R56, Q56, Q56*$F56 ) ) -> 8 | T56: =IF(ISBLANK(P56), 0, VLOOKUP(P56, 'Price Sheet'!$A$2:$B1015, 2, false)) -> 3.5 | U56: =IF(OR(ISBLANK(Q56), ISBLANK(T56)), "", T56*S56) -> 28 | V56: Board | W56: 10 | X56: FALSE | Y56: =IF(ISBLANK(W56), "", IF(X56, W56, W56*$F56 ) ) -> 10 | Z56: =IF(ISBLANK(V56), 0, VLOOKUP(V56, 'Price Sheet'!$A$2:$B1015, 2, false)) -> 0.45 | AA56: =IF(OR(ISBLANK(W56), ISBLANK(Z56)), "", Z56*Y56) -> 4.5 | AD56: FALSE | AE56: =IF(ISBLANK(AC56), "", IF(AD56, AC56, AC56*$F56 ) ) | AF56: =IF(ISBLANK(AB56), 0, VLOOKUP(AB56, 'Price Sheet'!$A$2:$B1015, 2, false)) -> 0 | AG56: =IF(OR(ISBLANK(AC56), ISBLANK(AF56)), "", AF56*AE56) | AJ56: FALSE | AK56: =IF(ISBLANK(AI56), "", IF(AJ56, AI56, AI56*$F56 ) ) | AL56: =IF(ISBLANK(AH56), 0, VLOOKUP(AH56, 'Price Sheet'!$A$2:$B1015, 2, false)) -> 0 | AM56: =IF(OR(ISBLANK(AI56), ISBLANK(AL56)), "", AL56*AK56) | AP56: FALSE | AQ56: =IF(ISBLANK(AO56), "", IF(AP56, AO56, AO56*$F56 ) ) | AR56: =IF(ISBLANK(AN56), 0, VLOOKUP(AN56, 'Price Sheet'!$A$2:$B1015, 2, false)) -> 0 | AS56: =IF(OR(ISBLANK(AO56), ISBLANK(AR56)), "", AR56*AQ56) | AV56: FALSE | AW56: =IF(ISBLANK(AU56), "", IF(AV56, AU56, AU56*$F56 ) ) | AX56: =IF(ISBLANK(AT56), 0, VLOOKUP(AT56, 'Price Sheet'!$A$2:$B1015, 2, false)) -> 0 | AY56: =IF(OR(ISBLANK(AU56), ISBLANK(AX56)), "", AX56*AW56) | BB56: FALSE | BC56: =IF(ISBLANK(BA56), "", IF(BB56, BA56, BA56*$F56 ) ) | BD56: =IF(ISBLANK(AZ56), 0, VLOOKUP(AZ56, 'Price Sheet'!$A$2:$B1015, 2, false)) -> 0 | BE56: =IF(OR(ISBLANK(BA56), ISBLANK(BD56)), "", BD56*BC56) | BH56: FALSE | BI56: =IF(ISBLANK(BG56), "", IF(BH56, BG56, BG56*$F56 ) ) | BJ56: =IF(ISBLANK(BF56), 0, VLOOKUP(BF56, 'Price Sheet'!$A$2:$B1015, 2, false)) -> 0 | BK56: =IF(OR(ISBLANK(BG56), ISBLANK(BJ56)), "", BJ56*BI56) | BN56: FALSE | BO56: =IF(ISBLANK(BM56), "", IF(BN56, BM56, BM56*$F56 ) ) | BP56: =IF(ISBLANK(BL56), 0, VLOOKUP(BL56, 'Price Sheet'!$A$2:$B1015, 2, false)) -> 0 | BQ56: =IF(OR(ISBLANK(BM56), ISBLANK(BP56)), "", BP56*BO56)
A57: Small Hanging Lumber Sign | B57: =H57+U57+AA57+AG57+AM57+AS57+AY57+BE57+BK57+J57+BQ57 -> 19.1 | C57: Carpentry | D57: Sawmill | E57: =IF(ISBLANK(D57), "", VLOOKUP(D57,'Crafting Tables'!$A$2:$B1015, 2, false)) -> Advanced | F57: =IFERROR(IF(E57 = "None", 1, VLOOKUP(C57,General!$A$5:$L$35, SWITCH(E57, "Basic", 8, "Advanced", 10, "Modern", 12), false)),"") -> 1 | G57: 60 | H57: =IFERROR(VLOOKUP(C57, General!$A$5:$L$35, 6, false) * G57 / 1000, 0) -> 2.4 | J57: =IFERROR(I57*VLOOKUP(D57,'Crafting Tables'!$1:$1000, 4, false)*F57,"") -> 0 | K57: TRUE | L57: Small Hanging Lumber Sign | M57: 1 | N57: =IF(ISBLANK(M57), "", $B57 / M57) -> 19.1 | P57: Lumber | Q57: 4 | R57: FALSE | S57: =IF(ISBLANK(Q57), "", IF(R57, Q57, Q57*$F57 ) ) -> 4 | T57: =IF(ISBLANK(P57), 0, VLOOKUP(P57, 'Price Sheet'!$A$2:$B1015, 2, false)) -> 3.5 | U57: =IF(OR(ISBLANK(Q57), ISBLANK(T57)), "", T57*S57) -> 14 | V57: Board | W57: 6 | X57: FALSE | Y57: =IF(ISBLANK(W57), "", IF(X57, W57, W57*$F57 ) ) -> 6 | Z57: =IF(ISBLANK(V57), 0, VLOOKUP(V57, 'Price Sheet'!$A$2:$B1015, 2, false)) -> 0.45 | AA57: =IF(OR(ISBLANK(W57), ISBLANK(Z57)), "", Z57*Y57) -> 2.7 | AD57: FALSE | AE57: =IF(ISBLANK(AC57), "", IF(AD57, AC57, AC57*$F57 ) ) | AF57: =IF(ISBLANK(AB57), 0, VLOOKUP(AB57, 'Price Sheet'!$A$2:$B1015, 2, false)) -> 0 | AG57: =IF(OR(ISBLANK(AC57), ISBLANK(AF57)), "", AF57*AE57) | AJ57: FALSE | AK57: =IF(ISBLANK(AI57), "", IF(AJ57, AI57, AI57*$F57 ) ) | AL57: =IF(ISBLANK(AH57), 0, VLOOKUP(AH57, 'Price Sheet'!$A$2:$B1015, 2, false)) -> 0 | AM57: =IF(OR(ISBLANK(AI57), ISBLANK(AL57)), "", AL57*AK57) | AP57: FALSE | AQ57: =IF(ISBLANK(AO57), "", IF(AP57, AO57, AO57*$F57 ) ) | AR57: =IF(ISBLANK(AN57), 0, VLOOKUP(AN57, 'Price Sheet'!$A$2:$B1015, 2, false)) -> 0 | AS57: =IF(OR(ISBLANK(AO57), ISBLANK(AR57)), "", AR57*AQ57) | AV57: FALSE | AW57: =IF(ISBLANK(AU57), "", IF(AV57, AU57, AU57*$F57 ) ) | AX57: =IF(ISBLANK(AT57), 0, VLOOKUP(AT57, 'Price Sheet'!$A$2:$B1015, 2, false)) -> 0 | AY57: =IF(OR(ISBLANK(AU57), ISBLANK(AX57)), "", AX57*AW57) | BB57: FALSE | BC57: =IF(ISBLANK(BA57), "", IF(BB57, BA57, BA57*$F57 ) ) | BD57: =IF(ISBLANK(AZ57), 0, VLOOKUP(AZ57, 'Price Sheet'!$A$2:$B1015, 2, false)) -> 0 | BE57: =IF(OR(ISBLANK(BA57), ISBLANK(BD57)), "", BD57*BC57) | BH57: FALSE | BI57: =IF(ISBLANK(BG57), "", IF(BH57, BG57, BG57*$F57 ) ) | BJ57: =IF(ISBLANK(BF57), 0, VLOOKUP(BF57, 'Price Sheet'!$A$2:$B1015, 2, false)) -> 0 | BK57: =IF(OR(ISBLANK(BG57), ISBLANK(BJ57)), "", BJ57*BI57) | BN57: FALSE | BO57: =IF(ISBLANK(BM57), "", IF(BN57, BM57, BM57*$F57 ) ) | BP57: =IF(ISBLANK(BL57), 0, VLOOKUP(BL57, 'Price Sheet'!$A$2:$B1015, 2, false)) -> 0 | BQ57: =IF(OR(ISBLANK(BM57), ISBLANK(BP57)), "", BP57*BO57)
A58: Small Standing Lumber Sign | B58: =H58+U58+AA58+AG58+AM58+AS58+AY58+BE58+BK58+J58+BQ58 -> 19.1 | C58: Carpentry | D58: Sawmill | E58: =IF(ISBLANK(D58), "", VLOOKUP(D58,'Crafting Tables'!$A$2:$B1015, 2, false)) -> Advanced | F58: =IFERROR(IF(E58 = "None", 1, VLOOKUP(C58,General!$A$5:$L$35, SWITCH(E58, "Basic", 8, "Advanced", 10, "Modern", 12), false)),"") -> 1 | G58: 60 | H58: =IFERROR(VLOOKUP(C58, General!$A$5:$L$35, 6, false) * G58 / 1000, 0) -> 2.4 | J58: =IFERROR(I58*VLOOKUP(D58,'Crafting Tables'!$1:$1000, 4, false)*F58,"") -> 0 | K58: TRUE | L58: Small Standing Lumber Sign | M58: 1 | N58: =IF(ISBLANK(M58), "", $B58 / M58) -> 19.1 | P58: Lumber | Q58: 4 | R58: FALSE | S58: =IF(ISBLANK(Q58), "", IF(R58, Q58, Q58*$F58 ) ) -> 4 | T58: =IF(ISBLANK(P58), 0, VLOOKUP(P58, 'Price Sheet'!$A$2:$B1015, 2, false)) -> 3.5 | U58: =IF(OR(ISBLANK(Q58), ISBLANK(T58)), "", T58*S58) -> 14 | V58: Board | W58: 6 | X58: FALSE | Y58: =IF(ISBLANK(W58), "", IF(X58, W58, W58*$F58 ) ) -> 6 | Z58: =IF(ISBLANK(V58), 0, VLOOKUP(V58, 'Price Sheet'!$A$2:$B1015, 2, false)) -> 0.45 | AA58: =IF(OR(ISBLANK(W58), ISBLANK(Z58)), "", Z58*Y58) -> 2.7 | AD58: FALSE | AE58: =IF(ISBLANK(AC58), "", IF(AD58, AC58, AC58*$F58 ) ) | AF58: =IF(ISBLANK(AB58), 0, VLOOKUP(AB58, 'Price Sheet'!$A$2:$B1015, 2, false)) -> 0 | AG58: =IF(OR(ISBLANK(AC58), ISBLANK(AF58)), "", AF58*AE58) | AJ58: FALSE | AK58: =IF(ISBLANK(AI58), "", IF(AJ58, AI58, AI58*$F58 ) ) | AL58: =IF(ISBLANK(AH58), 0, VLOOKUP(AH58, 'Price Sheet'!$A$2:$B1015, 2, false)) -> 0 | AM58: =IF(OR(ISBLANK(AI58), ISBLANK(AL58)), "", AL58*AK58) | AP58: FALSE | AQ58: =IF(ISBLANK(AO58), "", IF(AP58, AO58, AO58*$F58 ) ) | AR58: =IF(ISBLANK(AN58), 0, VLOOKUP(AN58, 'Price Sheet'!$A$2:$B1015, 2, false)) -> 0 | AS58: =IF(OR(ISBLANK(AO58), ISBLANK(AR58)), "", AR58*AQ58) | AV58: FALSE | AW58: =IF(ISBLANK(AU58), "", IF(AV58, AU58, AU58*$F58 ) ) | AX58: =IF(ISBLANK(AT58), 0, VLOOKUP(AT58, 'Price Sheet'!$A$2:$B1015, 2, false)) -> 0 | AY58: =IF(OR(ISBLANK(AU58), ISBLANK(AX58)), "", AX58*AW58) | BB58: FALSE | BC58: =IF(ISBLANK(BA58), "", IF(BB58, BA58, BA58*$F58 ) ) | BD58: =IF(ISBLANK(AZ58), 0, VLOOKUP(AZ58, 'Price Sheet'!$A$2:$B1015, 2, false)) -> 0 | BE58: =IF(OR(ISBLANK(BA58), ISBLANK(BD58)), "", BD58*BC58) | BH58: FALSE | BI58: =IF(ISBLANK(BG58), "", IF(BH58, BG58, BG58*$F58 ) ) | BJ58: =IF(ISBLANK(BF58), 0, VLOOKUP(BF58, 'Price Sheet'!$A$2:$B1015, 2, false)) -> 0 | BK58: =IF(OR(ISBLANK(BG58), ISBLANK(BJ58)), "", BJ58*BI58) | BN58: FALSE | BO58: =IF(ISBLANK(BM58), "", IF(BN58, BM58, BM58*$F58 ) ) | BP58: =IF(ISBLANK(BL58), 0, VLOOKUP(BL58, 'Price Sheet'!$A$2:$B1015, 2, false)) -> 0 | BQ58: =IF(OR(ISBLANK(BM58), ISBLANK(BP58)), "", BP58*BO58)
